Workbook

Sheet Pack
B1: PACK | Q1: Parametros ajustables
B2: Bajada 32x47 | C2: 350g | E2: 300g | G2: 200g | I2: 150g | K2: 90g | M2: autoadhesivo | P2: Precio del papel por hoja
C3: 4/0 | D3: 4/4 | E3: 4/0 | F3: 4/4 | G3: 4/0 | H3: 4/4 | I3: 4/0 | J3: 4/4 | K3: 4/0 | L3: 4/4 | M3: 4/0 | O3: precio de papel | P3: XL | Q3: 33X48 | R3: 32X47 | S3: A4
B4: 100 a 300 | C4: =P37+$R$4 -> 10.346 | D4: =P37+$W$38*T37+$R$4 -> 18.046 | E4: =P37+$R$5 -> 9.5988 | F4: =P37+$W$38*T37+$R$5 -> 17.2988 | G4: =P37+$R$6 -> 9.0785 | H4: =P37+T37*$W$38+$R$6 -> 16.7785 | I4: =P37+$R$7 -> 8.7639 | J4: =P37+T37*$W$38+$R$7 -> 16.4639 | K4: =P37+$R$8 -> 8.4977 | L4: =P37+T37*$W$38+$R$8 -> 16.1977 | M4: =P37+$R$9 -> 10.6515 | O4: 350g | P4: =P24*P14 -> 3.64 | Q4: =Q24*Q14 -> 2.73 | R4: =R24*R14 -> 2.296 | S4: =S24*S14 -> 1.498
B5: 301 a 500 | C5: =P38+$R$4 -> 9.996 | D5: =P38+$W$38*T38+$R$4 -> 17.346 | E5: =P38+$R$5 -> 9.2488 | F5: =P38+$W$38*T38+$R$5 -> 16.5988 | G5: =P38+$R$6 -> 8.7285 | H5: =P38+T38*$W$38+$R$6 -> 16.0785 | I5: =P38+$R$7 -> 8.4139 | J5: =P38+T38*$W$38+$R$7 -> 15.7639 | K5: =P38+$R$8 -> 8.1477 | L5: =P38+T38*$W$38+$R$8 -> 15.4977 | M5: =P38+$R$9 -> 10.3015 | O5: 300g | P5: =P25*P15 -> 2.44904 | Q5: =Q25*Q15 -> 1.83678 | R5: =R25*R15 -> 1.5488 | S5: =S25*S15 -> 1.0769
B6: 501 a 1000 | C6: =P39+$R$4 -> 9.646 | D6: =P39+$W$38*T39+$R$4 -> 16.996 | E6: =P39+$R$5 -> 8.8988 | F6: =P39+$W$38*T39+$R$5 -> 16.2488 | G6: =P39+$R$6 -> 8.3785 | H6: =P39+T39*$W$38+$R$6 -> 15.7285 | I6: =P39+$R$7 -> 8.0639 | J6: =P39+T39*$W$38+$R$7 -> 15.4139 | K6: =P39+$R$8 -> 7.7977 | L6: =P39+T39*$W$38+$R$8 -> 15.1477 | M6: =P39+$R$9 -> 9.9515 | O6: 200g | P6: =P26*P16 -> 1.63229 | Q6: =Q26*Q16 -> 1.22452 | R6: =R26*R16 -> 1.0285 | S6: =S26*S16 -> 0.8228
O7: 150g | P7: =P27*P17 -> 1.089 | Q7: =Q27*Q17 -> 0.81675 | R7: =R27*R17 -> 0.7139 | S7: =S27*S17 -> 0.6534
B8: Bajada 33x48 | C8: 350g | E8: 300g | G8: 200g | I8: 150g | K8: 90g | M8: autoadhesivo | O8: 90g | P8: =P28*P18 -> 0 | Q8: =Q28*Q18 -> 0.5324 | R8: =R28*R18 -> 0.4477 | S8: =S28*S18 -> 0.5324
C9: 4/0 | D9: 4/4 | E9: 4/0 | F9: 4/4 | G9: 4/0 | H9: 4/4 | I9: 4/0 | J9: 4/4 | K9: 4/0 | L9: 4/4 | M9: 4/0 | O9: autoadhesivo | P9: =P29*P19 -> 5.203 | Q9: =Q29*Q19 -> 5.203 | R9: =R29*R19 -> 2.6015 | S9: =S29*S19 -> 1.6093
B10: 100 a 300 | C10: =P37+$Q$4 -> 10.78 | D10: =P37+T37*$W$38+$Q$4 -> 18.48 | E10: =P37+$Q$5 -> 9.88678 | F10: =P37+T37*$W$38+$Q$5 -> 17.58678 | G10: =P37+$Q$6 -> 9.27452 | H10: =P37+T37*$W$38+$Q$6 -> 16.97452 | I10: =P37+$Q$7 -> 8.86675 | J10: =P37+T37*$W$38+$Q$7 -> 16.56675 | K10: =P37+$Q$8 -> 8.5824 | L10: =P37+T37*$W$38+$Q$8 -> 16.2824 | M10: =P37+$Q$9 -> 13.253 | O10: cartulina triplex 300g | P10: =P30*P20 -> 0 | Q10: =Q30*Q20 -> 0 | R10: =R30*R20 -> 0 | S10: =S30*S20 -> 0
B11: 301 a 500 | C11: =P38+$Q$4 -> 10.43 | D11: =P38+T38*$W$38+$Q$4 -> 17.78 | E11: =P38+$Q$5 -> 9.53678 | F11: =P38+T38*$W$38+$Q$5 -> 16.88678 | G11: =P38+$Q$6 -> 8.92452 | H11: =P38+T38*$W$38+$Q$6 -> 16.27452 | I11: =P38+$Q$7 -> 8.51675 | J11: =P38+T38*$W$38+$Q$7 -> 15.86675 | K11: =P38+$Q$8 -> 8.2324 | L11: =P38+T38*$W$38+$Q$8 -> 15.5824 | M11: =P38+$Q$9 -> 12.903
B12: 501 a 1000 | C12: =P39+$Q$4 -> 10.08 | D12: =P39+T39*$W$38+$Q$4 -> 17.43 | E12: =P39+$Q$5 -> 9.18678 | F12: =P39+T39*$W$38+$Q$5 -> 16.53678 | G12: =P39+$Q$6 -> 8.57452 | H12: =P39+T39*$W$38+$Q$6 -> 15.92452 | I12: =P39+$Q$7 -> 8.16675 | J12: =P39+T39*$W$38+$Q$7 -> 15.51675 | K12: =P39+$Q$8 -> 7.8824 | L12: =P39+T39*$W$38+$Q$8 -> 15.2324 | M12: =P39+$Q$9 -> 12.553 | O12: Coeficiente papel
P13: XL | Q13: 33X48 | R13: 32X47 | S13: A4
B14: Bajada XL | C14: 350gr | E14: 300gr | G14: 200gr | I14: 150gr | K14: 90gr | M14: autoadhesivo | O14: 350g | P14: 1.4 | Q14: 1.4 | R14: 1.4 | S14: 1.4 | U14: COSTO DE BAJADA | V14: (costo de papel x coef ganacia) + (costo clic * coef 4/0) + (costo clic x coef 4/4)
C15: 4/0 | D15: 4/4 | E15: 4/0 | F15: 4/4 | G15: 4/0 | H15: 4/4 | I15: 4/0 | J15: 4/4 | K15: 4/0 | L15: 4/4 | M15: 4/0 | O15: 300g | P15: 1.21 | Q15: 1.21 | R15: 1.21 | S15: 1.21 | U15: COSTO DE PAPEL | V15: costo de pliego/coef de corte
B16: 100 a 300 | C16: =Q37+$P$4 -> 23.765 | D16: =Q37+T37*$W$38+$P$4 -> 31.465 | E16: =Q37+$P$5 -> 22.57404 | F16: =Q37+T37*$W$38+$P$5 -> 30.27404 | G16: =Q37+$P$6 -> 21.75729 | H16: =Q37+T37*$W$38+$P$6 -> 29.45729 | I16: =Q37+$P$7 -> 21.214 | J16: =Q37+T37*$W$38+$P$7 -> 28.914 | K16: =Q37+$P$8 -> 20.125 | L16: =Q37+T37*$W$38+$P$8 -> 27.825 | M16: =Q37+$P$9 -> 25.328 | O16: 200g | P16: 1.21 | Q16: 1.21 | R16: 1.21 | S16: 1.21 | U16: costo de clic | V16: toner + gastos amortiz
B17: 301 a 500 | C17: =Q38+$P$4 -> 22.89 | D17: =Q38+T38*$W$38+$P$4 -> 30.24 | E17: =Q38+$P$5 -> 21.69904 | F17: =Q38+T38*$W$38+$P$5 -> 29.04904 | G17: =Q38+$P$6 -> 20.88229 | H17: =Q38+T38*$W$38+$P$6 -> 28.23229 | I17: =Q38+$P$7 -> 20.339 | J17: =Q38+T38*$W$38+$P$7 -> 27.689 | K17: =Q38+$P$8 -> 19.25 | L17: =Q38+T38*$W$38+$P$8 -> 26.6 | M17: =Q38+$P$9 -> 24.453 | O17: 150g | P17: 1.21 | Q17: 1.21 | R17: 1.21 | S17: 1.21
B18: 501 a 1000 | C18: =Q39+$P$4 -> 22.015 | D18: =Q39+T39*$W$38+$P$4 -> 29.365 | E18: =Q39+$P$5 -> 20.82404 | F18: =Q39+T39*$W$38+$P$5 -> 28.17404 | G18: =Q39+$P$6 -> 20.00729 | H18: =Q39+T39*$W$38+$P$6 -> 27.35729 | I18: =Q39+$P$7 -> 19.464 | J18: =Q39+T39*$W$38+$P$7 -> 26.814 | K18: =Q39+$P$8 -> 18.375 | L18: =Q39+T39*$W$38+$P$8 -> 25.725 | M18: =Q39+$P$9 -> 23.578 | O18: 90g | Q18: 1.21 | R18: 1.21 | S18: 1.21
O19: autoadhesivo | P19: 1.21 | Q19: 1.21 | R19: 1.21 | S19: 1.21
B20: Bajada A4 | C20: 350gr | E20: 300gr | G20: 200gr | I20: 150gr | K20: 90gr | M20: autoadhesivo
C21: 4/0 | D21: 4/4 | E21: 4/0 | F21: 4/4 | G21: 4/0 | H21: 4/4 | I21: 4/0 | J21: 4/4 | K21: 4/0 | L21: 4/4 | M21: 4/0
B22: 100 a 300 | C22: =R37+$S$4 -> 5.523 | D22: =R37+T37*$W$38+$S$4 -> 13.223 | E22: =R37+$S$5 -> 5.1019 | F22: =R37+T37*$W$38+$S$5 -> 12.8019 | G22: =R37+$S$6 -> 4.8478 | H22: =R37+T37*$W$38+$S$6 -> 12.5478 | I22: =R37+$S$7 -> 4.6784 | J22: =R37+T37*$W$38+$S$7 -> 12.3784 | K22: =R37+$S$8 -> 4.5574 | L22: =R37+T37*$W$38+$S$8 -> 12.2574 | M22: =R37+$S$9 -> 5.6343 | O22: costo de papel
B23: 301 a 500 | C23: =R38+$S$4 -> 5.348 | D23: =R38+T38*$W$38+$S$4 -> 12.698 | E23: =R38+$S$5 -> 4.9269 | F23: =R38+T38*$W$38+$S$5 -> 12.2769 | G23: =R38+$S$6 -> 4.6728 | H23: =R38+T38*$W$38+$S$6 -> 12.0228 | I23: =R38+$S$7 -> 4.5034 | J23: =R38+T38*$W$38+$S$7 -> 11.8534 | K23: =R38+$S$8 -> 4.3824 | L23: =R38+T38*$W$38+$S$8 -> 11.7324 | M23: =R38+$S$9 -> 5.4593 | P23: XL | Q23: 33X48 | R23: 32X47 | S23: A4
B24: 501 a 1000 | C24: =R39+$S$4 -> 5.173 | D24: =R39+T39*$W$38+$S$4 -> 12.523 | E24: =R39+$S$5 -> 4.7519 | F24: =R39+T39*$W$38+$S$5 -> 12.1019 | G24: =R39+$S$6 -> 4.4978 | H24: =R39+T39*$W$38+$S$6 -> 11.8478 | I24: =R39+$S$7 -> 4.3284 | J24: =R39+T39*$W$38+$S$7 -> 11.6784 | K24: =R39+$S$8 -> 4.2074 | L24: =R39+T39*$W$38+$S$8 -> 11.5574 | M24: =R39+$S$9 -> 5.2843 | O24: 350g | P24: 2.6 | Q24: 1.95 | R24: 1.64 | S24: 1.07
O25: 300g | P25: 2.024 | Q25: 1.518 | R25: 1.28 | S25: 0.89 | U25: 3000
O26: 200g | P26: 1.349 | Q26: 1.012 | R26: 0.85 | S26: 0.68 | U26: 1000
O27: 150g | P27: 0.9 | Q27: 0.675 | R27: 0.59 | S27: 0.54 | U27: 200
B28: BLANCO Y NEGRO | O28: 90g | P28: 0.587 | Q28: 0.44 | R28: 0.37 | S28: 0.44 | U28: 5000
B29: 32x47 | C29: 350gr | E29: 300gr | G29: 200gr | I29: 150gr | K29: 90gr | M29: autoadhesivo | O29: autoadhesivo | P29: 4.3 | Q29: 4.3 | R29: 2.15 | S29: 1.33 | U29: 2200
B30: Bajada ByN | C30: 1/0 | D30: 1/1 | E30: 1/0 | F30: 1/1 | G30: 1/0 | H30: 1/1 | I30: 1/0 | J30: 1/1 | K30: 1/0 | L30: 1/1 | M30: 1/0 | U30: 6900
B31: 101 a 500 | C31: =P43+$R$4 -> 4.796 | D31: =P43+$W$39*T43+$R$4 -> 5.996 | E31: =P43+$R$5 -> 4.0488 | F31: =P43+$W$39*T43+$R$5 -> 5.2488 | G31: =P43+$R$6 -> 3.5285 | H31: =P43+T43*$W$39+$R$6 -> 4.7285 | I31: =P43+$R$7 -> 3.2139 | J31: =P43+T43*$W$39+$R$7 -> 4.4139 | K31: =P43+$R$8 -> 2.9477 | L31: =P43+T43*$W$39+$R$8 -> 4.1477 | M31: =P43+$R$9 -> 5.1015 | U31: 300
B32: 501 a 1000 | C32: =P44+$R$4 -> 4.596 | D32: =P44+$W$39*T44+$R$4 -> 5.696 | E32: =P44+$R$5 -> 3.8488 | F32: =P44+$W$39*T44+$R$5 -> 4.9488 | G32: =P44+$R$6 -> 3.3285 | H32: =P44+T44*$W$39+$R$6 -> 4.4285 | I32: =P44+$R$7 -> 3.0139 | J32: =P44+T44*$W$39+$R$7 -> 4.1139 | K32: =P44+$R$8 -> 2.7477 | L32: =P44+T44*$W$39+$R$8 -> 3.8477 | M32: =P44+$R$9 -> 4.9015 | U32: 200
B33: 1001 a 5000 | C33: =P45+$R$4 -> 4.496 | D33: =P45+$W$39*T45+$R$4 -> 5.596 | E33: =P45+$R$5 -> 3.7488 | F33: =P45+$W$39*T45+$R$5 -> 4.8488 | G33: =P45+$R$6 -> 3.2285 | H33: =P45+T45*$W$39+$R$6 -> 4.3285 | I33: =P45+$R$7 -> 2.9139 | J33: =P45+T45*$W$39+$R$7 -> 4.0139 | K33: =P45+$R$8 -> 2.6477 | L33: =P45+T45*$W$39+$R$8 -> 3.7477 | M33: =P45+$R$9 -> 4.8015 | P33: precio x clic | U33: =SUM(U25:U32) -> 18800
O34: Rango Pack color | P34: A3 | Q34: XL | R34: A4 | S34: Coef 4/0 | T34: coef 4/4
B35: 33x48 | C35: 350gr | E35: 300gr | G35: 200gr | I35: 150gr | K35: 90gr | M35: autoadhesivo | O35: 1 a 20 | P35: =S35*$W$38 -> 10.5 | Q35: =P35*$W$36 -> 26.25 | R35: =P35*$W$37 -> 5.25 | S35: 1.5 | T35: 1.2
B36: Bajada ByN | C36: 1/0 | D36: 1/1 | E36: 1/0 | F36: 1/1 | G36: 1/0 | H36: 1/1 | I36: 1/0 | J36: 1/1 | K36: 1/0 | L36: 1/1 | M36: 1/0 | O36: 20 a 100 | P36: =S36*$W$38 -> 9.1 | Q36: =P36*$W$36 -> 22.75 | R36: =P36*$W$37 -> 4.55 | S36: 1.3 | T36: 1.2 | V36: Coeficiente XL | W36: 2.5
B37: 101 a 500 | C37: =P43+$Q$4 -> 5.23 | D37: =P43+$W$39*T43+$Q$4 -> 6.43 | E37: =P43+$Q$5 -> 4.33678 | F37: =P43+$W$39*T43+$Q$5 -> 5.53678 | G37: =P43+$Q$6 -> 3.72452 | H37: =P43+$W$39*T43+$Q$6 -> 4.92452 | I37: =P43+$Q$7 -> 3.31675 | J37: =P43+$W$39*T43+$Q$7 -> 4.51675 | K37: =P43+$Q$8 -> 3.0324 | L37: =P43+$W$39*T43+$Q$8 -> 4.2324 | M37: =P43+$Q$9 -> 7.703 | O37: 100 a 300 | P37: =S37*$W$38 -> 8.05 | Q37: =P37*$W$36 -> 20.125 | R37: =P37*$W$37 -> 4.025 | S37: 1.15 | T37: 1.1 | V37: Coeficiente A4 | W37: 0.5
B38: 501 a 1000 | C38: =P44+$Q$4 -> 5.03 | D38: =P44+$W$39*T44+$Q$4 -> 6.13 | E38: =P44+$Q$5 -> 4.13678 | F38: =P44+$W$39*T44+$Q$5 -> 5.23678 | G38: =P44+$Q$6 -> 3.52452 | H38: =P44+$W$39*T44+$Q$6 -> 4.62452 | I38: =P44+$Q$7 -> 3.11675 | J38: =P44+$W$39*T44+$Q$7 -> 4.21675 | K38: =P44+$Q$8 -> 2.8324 | L38: =P44+$W$39*T44+$Q$8 -> 3.9324 | M38: =P44+$Q$9 -> 7.503 | O38: 301 a 500 | P38: =S38*$W$38 -> 7.7 | Q38: =P38*$W$36 -> 19.25 | R38: =P38*$W$37 -> 3.85 | S38: 1.1 | T38: 1.05 | V38: costo clic color | W38: 7
B39: 1001 a 5000 | C39: =P45+$Q$4 -> 4.93 | D39: =P45+$W$39*T45+$Q$4 -> 6.03 | E39: =P45+$Q$5 -> 4.03678 | F39: =P45+$W$39*T45+$Q$5 -> 5.13678 | G39: =P45+$Q$6 -> 3.42452 | H39: =P45+$W$39*T45+$Q$6 -> 4.52452 | I39: =P45+$Q$7 -> 3.01675 | J39: =P45+$W$39*T45+$Q$7 -> 4.11675 | K39: =P45+$Q$8 -> 2.7324 | L39: =P45+$W$39*T45+$Q$8 -> 3.8324 | M39: =P45+$Q$9 -> 7.403 | O39: 501 a 1000 | P39: =S39*$W$38 -> 7.35 | Q39: =P39*$W$36 -> 18.375 | R39: =P39*$W$37 -> 3.675 | S39: 1.05 | T39: 1.05 | V39: costo clic ByN | W39: 1
O40: 502 a 1000 | P40: =S40*$W$38 -> 7 | Q40: =P40*$W$36 -> 17.5 | R40: =P40*$W$37 -> 3.5 | S40: 1 | T40: 1.05
B41: XL | C41: 350gr | E41: 300gr | G41: 200gr | I41: 150gr | K41: 90gr | M41: autoadhesivo
B42: Bajada ByN | C42: 1/0 | D42: 1/1 | E42: 1/0 | F42: 1/1 | G42: 1/0 | H42: 1/1 | I42: 1/0 | J42: 1/1 | K42: 1/0 | L42: 1/1 | M42: 1/0 | O42: Rango Pack ByN | P42: A3 | Q42: XL | R42: A4 | S42: Coef 1/0 | T42: coef 1/1
B43: 101 a 500 | C43: =Q43+$P$4 -> 9.89 | D43: =Q43+$W$39*T43+$P$4 -> 11.09 | E43: =Q43+$P$5 -> 8.69904 | F43: =P43+$W$39*T43+$P$5 -> 6.14904 | G43: =Q43+$P$6 -> 7.88229 | H43: =Q43+$W$39*T43+$P$6 -> 9.08229 | I43: =Q43+$P$7 -> 7.339 | J43: =Q43+$W$39*T43+$P$7 -> 8.539 | K43: =Q43+$P$8 -> 6.25 | L43: =Q43+$W$39*T43+$P$8 -> 7.45 | M43: =Q43+$P$9 -> 11.453 | O43: 101 a 500 | P43: =$W$39*S43 -> 2.5 | Q43: =P43*$W$36 -> 6.25 | R43: =P43*$W$37 -> 1.25 | S43: 2.5 | T43: 1.2
B44: 501 a 1000 | C44: =Q44+$P$4 -> 9.39 | D44: =Q44+$W$39*T44+$P$4 -> 10.49 | E44: =Q44+$P$5 -> 8.19904 | F44: =P44+$W$39*T44+$P$5 -> 5.84904 | G44: =Q44+$P$6 -> 7.38229 | H44: =Q44+$W$39*T44+$P$6 -> 8.48229 | I44: =Q44+$P$7 -> 6.839 | J44: =Q44+$W$39*T44+$P$7 -> 7.939 | K44: =Q44+$P$8 -> 5.75 | L44: =Q44+$W$39*T44+$P$8 -> 6.85 | M44: =Q44+$P$9 -> 10.953 | O44: 501 a 1000 | P44: =$W$39*S44 -> 2.3 | Q44: =P44*$W$36 -> 5.75 | R44: =P44*$W$37 -> 1.15 | S44: 2.3 | T44: 1.1
B45: 1001 a 5000 | C45: =Q45+$P$4 -> 9.14 | D45: =Q45+$W$39*T45+$P$4 -> 10.24 | E45: =Q45+$P$5 -> 7.94904 | F45: =P45+$W$39*T45+$P$5 -> 5.74904 | G45: =Q45+$P$6 -> 7.13229 | H45: =Q45+$W$39*T45+$P$6 -> 8.23229 | I45: =Q45+$P$7 -> 6.589 | J45: =Q45+$W$39*T45+$P$7 -> 7.689 | K45: =Q45+$P$8 -> 5.5 | L45: =Q45+$W$39*T45+$P$8 -> 6.6 | M45: =Q45+$P$9 -> 10.703 | O45: 1001 a 5000 | P45: =$W$39*S45 -> 2.2 | Q45: =P45*$W$36 -> 5.5 | R45: =P45*$W$37 -> 1.1 | S45: 2.2 | T45: 1.1
B47: A4 | C47: 350gr | E47: 300gr | G47: 200gr | I47: 150gr | K47: 90gr | M47: autoadhesivo
B48: Bajada ByN | C48: 1/0 | D48: 1/1 | E48: 1/0 | F48: 1/1 | G48: 1/0 | H48: 1/1 | I48: 1/0 | J48: 1/1 | K48: 1/0 | L48: 1/1 | M48: 1/0
B49: 101 a 500 | C49: =R43+$S$4 -> 2.748 | D49: =R43+$W$39*T43+$S$4 -> 3.948 | E49: =R43+$S$5 -> 2.3269 | F49: =R43+$W$39*T43+$S$5 -> 3.5269 | G49: =R43+$S$6 -> 2.0728 | H49: =R43+$W$39*T43+$S$6 -> 3.2728 | I49: =R43+$S$7 -> 1.9034 | J49: =R43+$W$39*T43+$S$7 -> 3.1034 | K49: =R43+$S$8 -> 1.7824 | L49: =R43+$W$39*T43+$S$8 -> 2.9824 | M49: =R43+$S$9 -> 2.8593
B50: 501 a 1000 | C50: =R44+$S$4 -> 2.648 | D50: =R44+$W$39*T44+$S$4 -> 3.748 | E50: =R44+$S$5 -> 2.2269 | F50: =R44+$W$39*T44+$S$5 -> 3.3269 | G50: =R44+$S$6 -> 1.9728 | H50: =R44+$W$39*T44+$S$6 -> 3.0728 | I50: =R44+$S$7 -> 1.8034 | J50: =R44+$W$39*T44+$S$7 -> 2.9034 | K50: =R44+$S$8 -> 1.6824 | L50: =R44+$W$39*T44+$S$8 -> 2.7824 | M50: =R44+$S$9 -> 2.7593
B51: 1001 a 5000 | C51: =R45+$S$4 -> 2.598 | D51: =R45+$W$39*T45+$S$4 -> 3.698 | E51: =R45+$S$5 -> 2.1769 | F51: =R45+$W$39*T45+$S$5 -> 3.2769 | G51: =R45+$S$6 -> 1.9228 | H51: =R45+$W$39*T45+$S$6 -> 3.0228 | I51: =R45+$S$7 -> 1.7534 | J51: =R45+$W$39*T45+$S$7 -> 2.8534 | K51: =R45+$S$8 -> 1.6324 | L51: =R45+$W$39*T45+$S$8 -> 2.7324 | M51: =R45+$S$9 -> 2.7093
R54: =T54*S54 -> 0.63 | S54: 0.21 | T54: 3
R55: =S55*T55 -> 0.625 | S55: 0.25 | T55: 2.5
S58: =R55/3 -> 0.20833333

Sheet Laminado
A1: =A3/C1*B1 -> 320366.86 | B1: 1.21 | C1: 1 | I1: ,
A2: =A3*B1 -> 320366.86 | B2: Laminado x lado | C2: 1.2 | D2: 1.16 | G2: 1.1 | I2: 1.2
A3: 264766 | B3: Tamaño de hoja A3Plus (32x47cm) | K3: NUEVA TERMINACION
A4: 1 | B4: 300000 | C4: 33 | E4: =B4/C4 -> 9090.9091 | F4: 52x72 | H4: 72x102
A5: costo | B5: =A3/A4 -> 264766 | C5: =A2/B4*C4*C1 -> 35.240355
A6: frente | B6: Cantidad | C6: brillo | D6: mate | E6: Laca UV | F6: Brillo | G6: Mate | H6: Brillo | I6: mate | J6: Laca UV | K6: Soft Touch | N6: =C6 -> brillo | O6: =D6 -> mate | P6: =E6 -> Laca UV | Q6: =F6 -> Brillo | R6: =G6 -> Mate
B7: 0 - 10 | C7: =C5*L7*D2 -> 163.51525 | D7: =C7*D2 -> 189.67768 | E7: =C7/I2 -> 136.2627 | F7: =C7 -> 163.51525 | G7: =D7 -> 189.67768 | J7: =E7 -> 136.2627 | K7: 8.6 | L7: 4 | N7: =C7*1.9 -> 310.67897 | O7: =D7*1.9 -> 360.3876 | P7: =E7*1.9 -> 258.89914 | Q7: =F7*1.9 -> 310.67897 | R7: =G7*1.9 -> 360.3876
B8: 11-50 | C8: =C5*L8*D2 -> 151.2516 | D8: =C8*D2 -> 175.45186 | E8: =C8/I2 -> 126.043 | F8: =C8 -> 151.2516 | G8: =D8 -> 175.45186 | J8: =E8 -> 126.043 | K8: 6.6 | L8: 3.7 | N8: =C8*1.9 -> 287.37804 | O8: =D8*1.9 -> 333.35853 | P8: =E8*1.9 -> 239.4817 | Q8: =F8*1.9 -> 287.37804 | R8: =G8*1.9 -> 333.35853
B9: 51-100 | C9: =C5*L9*D2 -> 138.98796 | D9: =C9*D2 -> 161.22603 | E9: =C9/I2 -> 115.8233 | F9: =C9 -> 138.98796 | G9: =D9 -> 161.22603 | J9: =E9 -> 115.8233 | K9: 6 | L9: 3.4 | N9: =C9*1.9 -> 264.07712 | O9: =D9*1.9 -> 306.32946 | P9: =E9*1.9 -> 220.06427 | Q9: =F9*1.9 -> 264.07712 | R9: =G9*1.9 -> 306.32946
B10: 101-500 | C10: =C5*L10*D2 -> 126.72432 | D10: =C10*D2 -> 147.00021 | E10: =C10/I2 -> 105.6036 | F10: =C10 -> 126.72432 | G10: =D10 -> 147.00021 | J10: =E10 -> 105.6036 | K10: 5.7 | L10: 3.1 | N10: =C10*1.9 -> 240.7762 | O10: =D10*1.9 -> 279.30039 | P10: =E10*1.9 -> 200.64683 | Q10: =F10*1.9 -> 240.7762 | R10: =G10*1.9 -> 279.30039
B11: 501-1000 | C11: =C5*L11*D2 -> 118.54855 | D11: =C11*D2 -> 137.51632 | E11: =C11/I2 -> 98.790461 | F11: =C11 -> 118.54855 | G11: =D11 -> 137.51632 | J11: =E11 -> 98.790461 | K11: 5.2 | L11: 2.9 | N11: =C11*1.9 -> 225.24225 | O11: =D11*1.9 -> 261.28101 | P11: =E11*1.9 -> 187.70188 | Q11: =F11*1.9 -> 225.24225 | R11: =G11*1.9 -> 261.28101
B12: 1001 + | C12: =C5*L12*D2 -> 110.37279 | D12: =C12*D2 -> 128.03244 | E12: =C12/I2 -> 91.977326 | F12: =C12 -> 110.37279 | G12: =D12 -> 128.03244 | J12: 4 | K12: aterciopelado | L12: 2.7 | N12: =C12*1.9 -> 209.7083 | O12: =D12*1.9 -> 243.26163 | P12: =E12*1.9 -> 174.75692 | Q12: =F12*1.9 -> 209.7083 | R12: =G12*1.9 -> 243.26163
B13: 1001 + | C13: =C5*L13*D2 -> 102.19703 | D13: =C13*D2 -> 118.54855 | E13: =C13/I2 -> 85.16419 | F13: =C13 -> 102.19703 | G13: =D13 -> 118.54855 | J13: 4 | K13: aterciopelado | L13: 2.5 | N13: =C13*1.9 -> 194.17435 | O13: =D13*1.9 -> 225.24225 | P13: =E13*1.9 -> 161.81196 | Q13: =F13*1.9 -> 194.17435 | R13: =G13*1.9 -> 225.24225
B16: Plastificado x unid | C16: A4 | D16: Oficio | G16: A3
B17: precio | C17: 15 | D17: 21 | G17: 25
B19: Adicional Trabajo EXPRESS | D19: + 40%
A23: 45415 | B23: uss | C23: 901 | N23: 25.74 | O23: 24.024 | P23: 24.024
A24: medida | N24: 24.024 | O24: 20.592 | P24: 20.592
A25: PROBOP | B25: bobina | C25: cm | D25: costo | E25: IVA | F25: $ cm lineal | G25: hoja A3+ 33x48 | N25: 20.592 | O25: 18.876 | P25: 18.876
A26: mate | B26: 52 cm | C26: 300000 | D26: 264766 | E26: =D26*1.21 -> 320366.86 | F26: =E26/C26 -> 1.0678895 | G26: =F26*33 -> 35.240355 | N26: 18.876 | O26: 17.16 | P26: 17.16
N27: 17.16 | O27: 15.444 | P27: 15.444
A28: LACA UV | B28: US x kilo | C28: 44 | D28: 4000 | N28: 15.444 | O28: 13.728 | P28: 13.728
A29: 4 | B29: =C28*A29 -> 176 | C29: =B29*C23 -> 158576 | D29: =C29/D28 -> 39.644

Sheet corte
A3: corte | N3: Ejemplo: | R3: Ejemplo:
N4: CUANTO SALE CORTAR 100 bajadas para postales 10x15cm de 300g | R4: CUANTO SALE CORTAR 500 bajadas para tarjetas 9x5cm de 350g (corte seco)
N6: DATOS: | R6: DATOS:
A7: CORTE | N7: Cantidad | O7: 100 bajadas | R7: Cantidad | S7: 500 bajadas
A8: Medidas | B8: Posturas x pliego | C8: Cortes | E8: 1 cm equivale, aproximadamente y a modo de referencia, a las siguientes cantidades de papel sin laminar. | N8: Papel | O8: 300g | R8: Papel | S8: 350g
A9: Al medio | B9: 2 | C9: 1 | N9: Cortes | O9: 8 cortes | R9: Cortes | S9: 13 cortes
A10: A3 - refilado | B10: 1 | C10: 4 | F10: Gramos | G10: Unid
A11: A4 | B11: 2 | C11: 5 | F11: 350 g | G11: 35 | N11: Ciclo de corte: 100/46= 2,17cm = $60 | R11: Ciclo de corte: 500/35= 14,28cm = $70
A12: 15x21 | B12: 4 | C12: 6 | F12: 300 g | G12: 46 | N12: Cantidad de cortes: 8 cortes: $20 | R12: Cantidad de cortes: $40
A13: 10x15 | B13: 9 | C13: 8 | F13: 200 g | G13: 70 | N13: Precio total por corte: $20+$60=$80 | R13: Precio total por corte: $70+$40=$110
A14: 10x10 | B14: 12 | C14: 9 | F14: 150 g | G14: 81
A15: 9x5 corte seco | B15: 30 | C15: 13 | F15: 90 g | G15: 95
A16: 9x5 doble corte | B16: 24 | C16: 24 | F16: Autoadhesivo | G16: 60 | N16: Ejemplo:
A17: 7x5 | B17: 32 | C17: 45 | F17: Imantada | G17: 14 | N17: CUANTO SALE CORTAR 2000 bajadas para folletos 10x15cm de 90g
A18: 5x5 | B18: 40 | C18: 54
A19: 6x4 | B19: 55 | C19: 73 | N19: DATOS:
N20: Cantidad | O20: 2000 bajadas
N21: Papel | O21: 90g
N22: Cortes | O22: 8 cortes
A23: Ciclo de corte hasta 33X70 cm | E23: Cantidad de cortes
A24: hasta 2 cm | B24: 70 | E24: Cantidad de cortes | F24: $ | N24: Ciclo de corte: 2000/95= 21,05 cm = $90 + (5cm extras x $15) = $165
A25: hasta 6 cm | B25: 90 | C25: 1275+60+200 | E25: 1 a 5 cortes | F25: 0 | N25: Cantidad de cortes: $20
A26: hasta 10 cm | B26: 120 | E26: 6 a 10 cortes | F26: 40 | N26: Precio total por corte: $165+$20 =$185
A27: hasta 16 cm | B27: 150 | E27: 11 a 15 cortes | F27: 60
A28: Adicional por cada cm extra $10 | E28: 16 a 20 cortes | F28: 80 | N28: FORMULA: CICLO DE CORTE + CANTIDAD DE CORTES = PRECIO POR CORTE
E29: 21 a 40 cortes | F29: 100
E30: 40 a 80 cortes | F30: 150
A31: Adicional por corte EXPRESS: 40%
A32: (en el momento)

Sheet circulares
O4: COSTO DÓLAR
D5: troq circularf frente | O5: 230
C7: 1CM | D7: 2CM | E7: 3CM | F7: 4CM | G7: 5CM | H7: 6CM | I7: 7CM | J7: 8CM | K7: 9CM
B8: 100 | C8: =(P23+Y33)*C25 -> 227147.85 | D8: =(P23+Y33)*D25 -> 227147.85 | E8: =(P23+X33)*E25 -> 227031.04 | F8: =(P24+X33)*F25 -> 406389.03 | G8: =(P24+W34)*G25 -> 609158.77 | H8: =(P24+V34)*H25 -> 811916.72 | I8: =(P24+V34)*I25 -> 1014895.9 | J8: =(P24+U34)*J25 -> 1420424.1 | K8: =(P24+U34)*K25 -> 1826259.5 | O8: CLICK A3+ | P8: PAPEL
B9: 200 | C9: =(P23+Y33)*C26 -> 227147.85 | D9: =(P23+Y33)*D26 -> 227147.85 | E9: =(P24+X33)*E26 -> 406389.03 | F9: =(P24+X34)*F26 -> 609424.26 | G9: =(P24+W34)*G26 -> 1015264.6 | H9: =(P24+V34)*H26 -> 1623833.4 | I9: =(P24+V34)*I26 -> 1826812.6 | J9: =(P24+U35)*J26 -> 2840457.1 | K9: =(P24+U35)*K26 -> 3449126.4 | O9: 0.147 | P9: 0.21175
B10: 300 | C10: =(P23+Y33)*C27 -> 227147.85 | D10: =(P24+Y33)*D27 -> 406622.66 | E10: =(P24+X34)*E27 -> 609424.26 | F10: =(P24+X34)*F27 -> 1015707.1 | G10: =(P24+W34)*G27 -> 1624423.4 | H10: =(P24+V35)*H27 -> 2232402.2 | I10: =(P24+V35)*I27 -> 2638293.6 | J10: =(P24+U35)*J27 -> 4057795.8 | K10: =(P25+U35)*K27 -> 4923266.5
B11: 500 | C11: =(P23+Y33)*C28 -> 227147.85 | D11: =(P24+Y34)*D28 -> 406495.23 | E11: =(P24+X34)*E28 -> 812565.68 | F11: =(P24+X34)*F28 -> 1625131.4 | G11: =(P24+W35)*G28 -> 2639165.1 | H11: =(P24+V35)*H28 -> 3653021.9 | I11: =(P24+V35)*I28 -> 4261858.8 | J11: =(P25+U36)*J28 -> 6694779 | K11: =(P25+U36)*K28 -> 8270021.1
B12: 1000 | C12: =(P23+Y33)*C29 -> 227147.85 | D12: =(P24+Y34)*D29 -> 812990.45 | E12: =(P24+X34)*E29 -> 1625131.4 | F12: =(P24+X35)*F29 -> 3046397.2 | G12: =(P24+W35)*G29 -> 5075317.5 | H12: =(P25+V36)*H29 -> 7090418 | I12: =(P25+V36)*I29 -> 8272154.3 | J12: =(P26+U37)*J29 -> 12791844 | K12: =(P26+U37)*K29 -> 16037536
C14: troq circular frente y dorso
C15: 1CM | D15: 2CM | E15: 3CM | F15: 4CM | G15: 5CM | H15: 6CM | I15: 7CM | J15: 8CM | K15: 9CM
B16: 100 | C16: =C8*S23 -> 227408.01 | D16: =D8*S23 -> 227408.01 | E16: =E8*S23 -> 227291.06 | F16: =F8*S23 -> 406854.47 | G16: =G8*S23 -> 609856.44 | H16: =H8*S23 -> 812846.61 | I16: =I8*S23 -> 1016058.3 | J16: =J8*S23 -> 1422050.9 | K16: =K8*S23 -> 1828351.1
B17: 200 | C17: =C9*S24 -> 227408.01 | D17: =D9*S24 -> 227408.01 | E17: =E9*S24 -> 406854.47 | F17: =F9*S24 -> 610122.23 | G17: =G9*S24 -> 1016427.4 | H17: =H9*S24 -> 1625693.2 | I17: =I9*S24 -> 1828904.9 | J17: =J9*S24 -> 2843710.2 | K17: =K9*S24 -> 3453076.7
B18: 300 | C18: =C10*S25 -> 227408.01 | D18: =D10*S25 -> 407088.36 | E18: =E10*S25 -> 610122.23 | F18: =F10*S25 -> 1016870.4 | G18: =G10*S25 -> 1626283.9 | H18: =H10*S25 -> 2234959 | I18: =I10*S25 -> 2641315.2 | J18: =J10*S25 -> 4062443.2 | K18: =K10*S25 -> 4928905.1
B19: 500 | C19: =C11*S26 -> 227408.01 | D19: =D11*S26 -> 406960.78 | E19: =E11*S26 -> 813496.31 | F19: =F11*S26 -> 1626992.6 | G19: =G11*S26 -> 2642187.7 | H19: =H11*S26 -> 3657205.7 | I19: =I11*S26 -> 4266739.9 | J19: =J11*S26 -> 6702446.6 | K19: =K11*S26 -> 8279492.8
B20: 1000 | C20: =C12*S27 -> 227408.01 | D20: =D12*S27 -> 813921.57 | E20: =E12*S27 -> 1626992.6 | F20: =F12*S27 -> 3049886.3 | G20: =G12*S27 -> 5081130.3 | H20: =H12*S27 -> 7098538.6 | I20: =I12*S27 -> 8281628.4 | J20: =J12*S27 -> 12806495 | K20: =K12*S27 -> 16055904
O22: CLICK A3+ | P22: 4/0 | Q22: CLICK FYD | R22: x pliegos
N23: 1 | O23: 1 | P23: =Bajadas!E4 -> 226446.98 | Q23: =Bajadas!F4 -> 226706.33 | R23: =Bajadas!AH48 -> 1.9 | S23: =Q23/P23 -> 1.0011453
C24: 1CM | D24: 2CM | E24: 3CM | F24: 4CM | G24: 5CM | H24: 6CM | I24: 7CM | J24: 8CM | K24: 9CM | N24: 2 a 25 | O24: 1 | P24: =Bajadas!E5 -> 202610.45 | Q24: =Bajadas!F5 -> 202842.5 | R24: =Bajadas!AH49 -> 1.7 | S24: =Q24/P24 -> 1.0011453
B25: 100 | C25: 1 | D25: 1 | E25: 1 | F25: 2 | G25: 3 | H25: 4 | I25: 5 | J25: 7 | K25: 9 | N25: 26 a 50 | O25: 1 | P25: =Bajadas!E6 -> 196651.32 | Q25: =Bajadas!F6 -> 196876.55 | R25: =Bajadas!AH50 -> 1.65 | S25: =Q25/P25 -> 1.0011453
B26: 200 | C26: 1 | D26: 1 | E26: 2 | F26: 3 | G26: 5 | H26: 8 | I26: 9 | J26: 14 | K26: 17 | N26: 51 a 100 | O26: 1 | P26: =Bajadas!E7 -> 190692.19 | Q26: =Bajadas!F7 -> 190910.59 | R26: =Bajadas!AH51 -> 1.6 | S26: =Q26/P26 -> 1.0011453
B27: 300 | C27: 1 | D27: 2 | E27: 3 | F27: 5 | G27: 8 | H27: 11 | I27: 13 | J27: 20 | K27: 25 | N27: 101 a 300 | O27: 1 | P27: =Bajadas!E8 -> 184733.06 | Q27: =Bajadas!F8 -> 184944.63 | R27: =Bajadas!AH52 -> 1.55 | S27: =Q27/P27 -> 1.0011453
B28: 500 | C28: 1 | D28: 2 | E28: 4 | F28: 8 | G28: 13 | H28: 18 | I28: 21 | J28: 34 | K28: 42 | N28: 301 a 500 | O28: 1 | P28: =Bajadas!E9 -> 178773.93 | Q28: =Bajadas!F9 -> 178978.68 | R28: =Bajadas!AH53 -> 1.5 | S28: =Q28/P28 -> 1.0011453
B29: 1000 | C29: 1 | D29: 4 | E29: 8 | F29: 15 | G29: 25 | H29: 36 | I29: 42 | J29: 67 | K29: 84 | N29: 501 a 1000 | O29: 1 | P29: =Bajadas!E10 -> 172814.8 | Q29: =Bajadas!F10 -> 173012.72 | R29: =Bajadas!AH54 -> 1.45 | S29: =Q29/P29 -> 1.0011453
N30: 1000 | O30: 1 | P30: =Bajadas!E11 -> 166855.67 | Q30: =Bajadas!F11 -> 167046.77 | R30: =Bajadas!AH55 -> 1.4 | S30: =Q30/P30 -> 1.0011453
O32: Laminado x 1 | P32: Laminado x 2 | T32: =troquelados!W44 | U32: =troquelados!X44 -> SIMPLE | V32: =troquelados!Y44 -> MEDIO | W32: =troquelados!Z44 -> COMPLEJO | X32: =troquelados!AA44 -> MUY COMPLEJO | Y32: =troquelados!AB44 -> ULTRA COMPLEJO
N33: 1 a 10 | O33: =Laminado!C7 -> 163.51525 | P33: =O33*2 -> 327.03049 | T33: =troquelados!W45 -> 1 a 2 | U33: =troquelados!X45 -> 338 | V33: =troquelados!Y45 -> 405.6 | W33: =troquelados!Z45 -> 486.72 | X33: =troquelados!AA45 -> 584.064 | Y33: =troquelados!AB45 -> 700.8768
N34: 11 a 50 | O34: =Laminado!C8 -> 151.2516 | P34: =O34*2 -> 302.5032 | T34: =troquelados!W46 -> 3 a 9 | U34: =troquelados!X46 -> 307.27273 | V34: =troquelados!Y46 -> 368.72727 | W34: =troquelados!Z46 -> 442.47273 | X34: =troquelados!AA46 -> 530.96727 | Y34: =troquelados!AB46 -> 637.16073
N35: 51 a 100 | O35: =Laminado!C9 -> 138.98796 | P35: =O35*2 -> 277.97592 | T35: =troquelados!W47 -> 10 a 25 | U35: =troquelados!X47 -> 279.33884 | V35: =troquelados!Y47 -> 335.20661 | W35: =troquelados!Z47 -> 402.24793 | X35: =troquelados!AA47 -> 482.69752 | Y35: =troquelados!AB47 -> 579.23702
N36: 100 | O36: =Laminado!C10 -> 126.72432 | P36: =O36*2 -> 253.44863 | T36: =troquelados!W48 -> 26 a 50 | U36: =troquelados!X48 -> 253.9444 | V36: =troquelados!Y48 -> 304.73328 | W36: =troquelados!Z48 -> 365.67994 | X36: =troquelados!AA48 -> 438.81593 | Y36: =troquelados!AB48 -> 526.57911
O37: =Laminado!C11 -> 118.54855 | P37: =O37*2 -> 237.09711 | T37: =troquelados!W49 -> 51 a 100 | U37: =troquelados!X49 -> 230.85855 | V37: =troquelados!Y49 -> 277.03026 | W37: =troquelados!Z49 -> 332.43631 | X37: =troquelados!AA49 -> 398.92357 | Y37: =troquelados!AB49 -> 478.70828
P38: =O38*2 -> 0 | T38: =troquelados!W50 -> mas de 100 | U38: =troquelados!X50 -> 209.87141 | V38: =troquelados!Y50 -> 251.84569 | W38: =troquelados!Z50 -> 302.21483 | X38: =troquelados!AA50 -> 362.65779 | Y38: =troquelados!AB50 -> 435.18935

Sheet troquelados
R1: 1 | S1: 1.15 | T1: 1.3 | U1: 1.45 | V1: 1.6
R2: 15x15 cm. | S2: 7x7 cm. | T2: 4x4 cm. | U2: 2x2 cm. | V2: 1x1 cm,
C3: planchas troqueladas | R3: SIMPLE | S3: MEDIO | T3: COMPLEJO | U3: MUY COMPLEJO | V3: ULTRA COMPLEJO | X3: Dólar | Y3: 168
P4: 1.7 | Q4: 1 a 2 | R4: 118.8 | S4: 145.2 | T4: 171.6 | U4: 184.8 | V4: 211.2
A5: stickers | B5: 1CM | C5: 2CM | D5: 3CM | E5: 4CM | F5: 5CM | G5: 6CM | H5: 7CM | I5: 8CM | J5: 9CM | K5: 10cm | L5: 11cm. | M5: 12-13-14-15cm. | N5: 16/17 | O5: 18/19/20cm. | P5: 1.6 | Q5: 3 a 9 | R5: 99 | S5: 125.4 | T5: 151.8 | U5: 165 | V5: 191.4 | W5: 0.356 | X5: Coeficiente XL | Y5: =Y7*Z5 -> 73.92 | Z5: 2 | AB5: 100
A6: 100 | B6: =(Q20+AB20)*$B$42 -> 523932.14 | C6: =(Q20+AB20)*$C$42 -> 523932.14 | D6: =(Q20+AA20)*$D$42 -> 523842.28 | E6: =(Q21+Z20)*$E$42 -> 937346.8 | F6: =(Q21+Z21)*$F$42 -> 1405918.1 | G6: =(Q21+Z21)*$G$42 -> 1874557.5 | H6: =(Q21+Y21)*$H$42 -> 2342913.2 | I6: =(Q21+Y21)*$I$42 -> 3280078.5 | J6: =(Q21+Y21)*$J$42 -> 4217243.7 | K6: =(Q21+Y21)*$J$42 -> 4217243.7 | L6: =(Q21+X21)*$L$42 -> 6090959.7 | M6: =(Q21+X22)*$M$42 -> 7964735.9 | N6: =(Q22+X23)*$N$42 -> 15460509 | O6: =(Q22+X23)*$O$42 -> 22736042 | P6: 1.5 | Q6: 10 a 25 | R6: 92.4 | S6: 118.8 | T6: 145.2 | U6: 158.4 | V6: 184.8 | W6: 0.11 | X6: Coeficiente A4 | Y6: =W6*Y3 -> 18.48 | AB6: 200
A7: 200 | B7: =(Q20+AB20)*$B$42 -> 523932.14 | C7: =(Q20+AB20)*$C$42 -> 523932.14 | D7: =(Q21+AA20)*$D$43 -> 937496.56 | E7: =(Q21+Z21)*$E$43 -> 1405918.1 | F7: =(Q21+Z21)*$F$43 -> 2343196.8 | G7: =(Q21+Z21)*$G$43 -> 3749114.9 | H7: =(Q21+Y21)*$H$43 -> 4217243.7 | I7: =(Q21+Y21)*$I$43 -> 6560156.9 | J7: =(Q21+Y22)*$J$43 -> 7965466.5 | K7: =(Q21+Y22)*$J$43 -> 7965466.5 | L7: =(Q21+X22)*$L$43 -> 11712847 | M7: =(Q22+X23)*$M$43 -> 15460509 | N7: =(Q23+X24)*$N$43 -> 29542282 | O7: =(Q23+X24)*$O$43 -> 44092958 | P7: 1.4 | Q7: 26 a 50 | R7: 85.8 | S7: 112.2 | T7: 138.6 | U7: 151.8 | V7: 178.2 | W7: 0.22 | X7: costo clic color A3 | Y7: =W7*Y3 -> 36.96 | AB7: 300
A8: 300 | B8: =(Q20+AB20)*$B$42 -> 523932.14 | C8: =(Q21+AB20)*$C$44 -> 937676.27 | D8: =(Q21+AA21)*$D$44 -> 1406122.3 | E8: =(Q21+Z21)*$E$44 -> 2343196.8 | F8: =(Q21+Z21)*$F$44 -> 3280475.5 | G8: =(Q21+Z22)*$G$44 -> 5154692.6 | H8: =(Q21+Y22)*$H$44 -> 6091239.1 | I8: =(Q21+Y22)*$I$44 -> 9371137 | J8: =(Q21+Y22)*$J$44 -> 11713921 | K8: =(Q21+Y22)*$J$44 -> 11713921 | L8: =(Q22+X22)*$L$44 -> 17280134 | M8: =(Q22+X23)*$M$44 -> 22736042 | N8: =(Q23+X24)*$N$44 -> 44092958 | O8: =(Q24+X24)*$O$44 -> 64073413 | P8: 1.3 | Q8: 51 a 100 | R8: 79.2 | S8: 105.6 | T8: 132 | U8: 145.2 | V8: 171.6 | W8: 0.22 | X8: costo clic XA3 | Y8: =W8*Y3 -> 36.96
A9: 500 | B9: =(Q20+AB20)*$B$42 -> 523932.14 | C9: =(Q21+AB20)*$C$45 -> 937676.27 | D9: =(Q21+AA21)*$D$45 -> 2343537.2 | E9: =(Q21+Z21)*$E$45 -> 3749114.9 | F9: =(Q21+Z22)*$F$45 -> 5623301.1 | G9: =(Q21+Z22)*$G$45 -> 8434951.6 | H9: =(Q21+Y22)*$H$45 -> 9839693.9 | I9: =(Q22+Y23)*$I$45 -> 15461837 | J9: =(Q23+Y23)*$J$45 -> 18521429 | K9: =(Q23+Y23)*$J$45 -> 18521429 | L9: =(Q23+X23)*$L$45 -> 27779683 | M9: =(Q23+X24)*$M$45 -> 37038085 | N9: =(Q24+X24)*$N$45 -> 71335066 | O9: =(Q24+X24)*$O$45 -> 85431217 | P9: 1.2 | Q9: mas de 100 | R9: 78 | S9: 99 | T9: 125.4 | U9: 138.6 | V9: 165
A10: 1000 | B10: =(Q20+AB20)*$B$42 -> 523932.14 | C10: =(Q21+AB21)*$C$46 -> 1875156.5 | D10: =(Q21+AA21)*$D$46 -> 4218366.9 | E10: =(Q21+Z22)*$E$46 -> 7029126.3 | F10: =(Q21+Z22)*$F$46 -> 10777994 | G10: =(Q22+Z23)*$G$46 -> 16373045 | H10: =(Q22+Y23)*$H$46 -> 19099916 | I10: =(Q23+Y24)*$I$46 -> 29544662 | J10: =(Q23+Y24)*$J$46 -> 37041068 | K10: =(Q23+Y24)*$J$46 -> 37041068 | L10: =(Q24+X24)*$L$46 -> 53394510 | M10: =(Q24+X24)*$M$46 -> 71335066 | N10: =(Q25+X24)*$N$46 -> 1.3806978e+08 | O10: =(Q25+X24)*$O$46 -> 2.0669129e+08 | W10: 0.055555 | X10: costo clic ByN | Y10: =W10*Y3 -> 9.33324 | Z10: 2
R11: SIMPLE | S11: MEDIO | T11: COMPLEJO | U11: MUY COMPLEJO | V11: ULTRA COMPLEJO
P12: 320 | Q12: 1 a 2 | R12: =R4/P12 -> 0.37125 | S12: =S4/P12 -> 0.45375 | T12: =T4/P12 -> 0.53625 | U12: =U4/P12 -> 0.5775 | V12: =V4/P12 -> 0.66
A13: stickers | B13: 1cm. | C13: 2cm. | D13: 3cm. | E13: 4cm. | F13: 5cm. | G13: 6cm. | H13: 7cm. | I13: 8cm. | J13: 9cm. | K13: 10cm | L13: 11cm. | M13: 12-13-14-15cm. | N13: 16/17cm. | O13: 18/19/20cm. | P13: 320 | Q13: 3 a 9 | R13: =R5/P13 -> 0.309375 | S13: =S5/P13 -> 0.391875 | T13: =T5/P13 -> 0.474375 | U13: =U5/P13 -> 0.515625 | V13: =V5/P13 -> 0.598125
A14: 100 | B14: =B6+(T32*B42) -> 524068.4 | C14: =C6+(T32*C42) -> 524068.4 | D14: =D6+(T32*D42) -> 523978.54 | E14: =E6+(T32*E42) -> 937619.33 | F14: =F6+(T32*F42) -> 1406326.9 | G14: =G6+(T32*G42) -> 1875102.5 | H14: =H6+(T32*H42) -> 2343594.5 | I14: =I6+(T32*I42) -> 3281032.3 | J14: =J6+(T32*J42) -> 4218470.1 | K14: =K6+(T32*K42) -> 4218470.1 | L14: =L6+(T32*L42) -> 6092731.1 | M14: =M6+(T32*M42) -> 7967052.4 | N14: =N6+(T32*N42) -> 15465142 | O14: =O6+(T33*O42) -> 22742344 | P14: 320 | Q14: 10 a 25 | R14: =R6/P14 -> 0.28875 | S14: =S6/P14 -> 0.37125 | T14: =T6/P14 -> 0.45375 | U14: =U6/P14 -> 0.495 | V14: =V6/P14 -> 0.5775
A15: 200 | B15: =B7+(T32*B43) -> 524068.4 | C15: =C7+(T32*C43) -> 524068.4 | D15: =D7+(T32*D43) -> 937769.09 | E15: =E7+(T32*E43) -> 1406326.9 | F15: =F7+(T32*F43) -> 2343878.1 | G15: =G7+(T32*G43) -> 3750205 | H15: =H7+(T32*H43) -> 4218470.1 | I15: =I7+(T33*I43) -> 6561921.5 | J15: =J7+(T33*J43) -> 7967609.2 | K15: =K7+(T33*K43) -> 7967609.2 | L15: =L7+(T33*L43) -> 11715998 | M15: =M7+(T33*M43) -> 15464794 | N15: =N7+(T33*N43) -> 29550727 | O15: =O7+(T34*O43) -> 44104541 | P15: 320 | Q15: 26 a 50 | R15: =R7/P15 -> 0.268125 | S15: =S7/P15 -> 0.350625 | T15: =T7/P15 -> 0.433125 | U15: =U7/P15 -> 0.474375 | V15: =V7/P15 -> 0.556875
A16: 300 | B16: =B8+(T32*B44) -> 524068.4 | C16: =C8+(T32*C44) -> 937948.8 | D16: =D8+(T32*D44) -> 1406531.1 | E16: =E8+(T32*E44) -> 2343878.1 | F16: =F8+(T32*F44) -> 3281429.4 | G16: =G8+(T33*G44) -> 5156079.1 | H16: =H8+(T33*H44) -> 6092877.6 | I16: =I8+(T33*I44) -> 9373657.9 | J16: =J8+(T33*J44) -> 11717072 | K16: =K8+(T33*K44) -> 11717072 | L16: =L8+(T33*L44) -> 17284924 | M16: =M8+(T34*M44) -> 22741833 | N16: =N8+(T34*N44) -> 44104541 | O16: =O8+(T34*O44) -> 64090786 | P16: 320 | Q16: 51 a 100 | R16: =R8/P16 -> 0.2475 | S16: =S8/P16 -> 0.33 | T16: =T8/P16 -> 0.4125 | U16: =U8/P16 -> 0.45375 | V16: =V8/P16 -> 0.53625
A17: 500 | B17: =B9+(T32*B45) -> 524068.4 | C17: =C9+(T32*C45) -> 937948.8 | D17: =D9+(T32*D45) -> 2344218.5 | E17: =E9+(T32*E45) -> 3750205 | F17: =F9+(T33*F45) -> 5624813.6 | G17: =G9+(T33*G45) -> 8437220.4 | H17: =H9+(T33*H45) -> 9842340.8 | I17: =I9+(T33*I45) -> 15466122 | J17: =J9+(T33*J45) -> 18526723 | K17: =K9+(T33*K45) -> 18526723 | L17: =L9+(T34*L45) -> 27786979 | M17: =M9+(T34*M45) -> 37047814 | N17: =N9+(T34*N45) -> 71354408 | O17: =O9+(T35*O45) -> 85452337 | P17: 320 | Q17: mas de 100 | R17: =R9/P17 -> 0.24375 | S17: =S9/P17 -> 0.309375 | T17: =T9/P17 -> 0.391875 | U17: =U9/P17 -> 0.433125 | V17: =V9/P17 -> 0.515625 | X17: 1 | Y17: 2 | Z17: 1.2 | AA17: 1.2 | AB17: 1.2
A18: 1000 | B18: =B10+(T32*B46) -> 524068.4 | C18: =C10+(T32*C46) -> 1875701.5 | D18: =D10+(T32*D46) -> 4219593.3 | E18: =E10+(T33*E46) -> 7031017 | F18: =F10+(T33*F46) -> 10780893 | G18: =G10+(T33*G46) -> 16377582 | H18: =H10+(T33*H46) -> 19105210 | I18: =I10+(T34*I46) -> 29552422 | J18: =J10+(T34*J46) -> 37050798 | K18: =K10+(T34*K46) -> 37050798 | L18: =L10+(T35*L46) -> 53407711 | M18: =M10+(T35*M46) -> 71352702 | N18: =N10+(T35*N46) -> 1.3810505e+08 | O18: =O10+(T35*O46) -> 2.0674409e+08 | T18: hoja | U18: 29 | V18: 44 | X18: mas de 15x15 cm. | Y18: de 10x10 a 14x14 cm | Z18: de 5x5 a 9x9 cm, | AA18: de2x2 a 4x4 cm, | AB18: de 1x1 a 2x2cm. | AE18: PAPEL | AF18: opp | AG18: 5to color
Q19: Sticker | S19: x pliegos | T19: cm2 | U19: TROQUELADO | V19: GEMINI | W19: medio corte | X19: simple | Y19: medio | Z19: complejo | AA19: muy complejo | AB19: ultra complejo | AC19: CM | AE19: =Bajadas!S4 -> 523393 | AF19: =Bajadas!U4 -> 1341.8275 | AG19: =Bajadas!AT38 -> 370.5
Q20: =Bajadas!S4 -> 523393 | R20: 1 | S20: 1 | T20: cm2 | U20: =U18*V18 -> 1276 | V20: minimo | W20: 1 a 2 | X20: 260 | Y20: =X20*Z17 -> 312 | Z20: =Y20*Z17 -> 374.4 | AA20: =Z20*AA17 -> 449.28 | AB20: =AA20*AB17 -> 539.136 | AC20: 387 | AE20: =Bajadas!S5 -> 468299 | AF20: =Bajadas!U5 -> 1200.5825 | AG20: =Bajadas!AT39 -> 351
A21: calcos | B21: 1cm. | C21: 2cm. | D21: 3cm. | E21: 4cm. | F21: 5cm. | G21: 6cm. | H21: 7cm. | I21: 8cm. | J21: 9cm. | K21: 10cm | L21: 11cm. | M21: 12-13-14-15cm. | N21: 16/17cm. | O21: 18/19/20cm. | Q21: =Bajadas!S5 -> 468299 | R21: 2 a 25 | S21: 1 | T21: cm2 | U21: =U20 -> 1276 | V21: 1.1 | W21: 3 a 9 | X21: =X20/V22 -> 236.36364 | Y21: =Y20/V22 -> 283.63636 | Z21: =Z20/V22 -> 340.36364 | AA21: =AA20/V22 -> 408.43636 | AB21: =AB20/V22 -> 490.12364 | AC21: 352 | AE21: =Bajadas!S6 -> 454525.5 | AF21: =Bajadas!U6 -> 1165.2713 | AG21: =Bajadas!AT40 -> 331.5
A22: 100 | B22: =(Q32+AB45)*$B$42 -> 2042.7043 | C22: =(Q32+AB45)*$C$42 -> 2042.7043 | D22: =(Q32+AA45)*$D$42 -> 1925.8915 | E22: =(Q32+Z45)*$E$42 -> 3657.095 | F22: =(Q33+Z46)*$F$42 -> 4929.1657 | G22: =(Q33+Z46)*$G$42 -> 6572.2209 | H22: =(Q33+Y46)*$H$42 -> 7846.5489 | I22: =(Q33+Y46)*$I$42 -> 10985.168 | J22: =(Q33+Y46)*$J$42 -> 14123.788 | K22: =(Q33+Y46)*$J$42 -> 14123.788 | L22: =(Q33+X47)*$L$42 -> 19238.977 | M22: =(Q33+X47)*$M$42 -> 25158.663 | N22: =(Q34+X48)*$N$42 -> 48253.332 | O22: =(Q39+X48)*$O$42 -> 62132.97 | Q22: =Bajadas!S6 -> 454525.5 | R22: 26 a 50 | S22: 1 | T22: cm2 | U22: =U21 -> 1276 | V22: 1.1 | W22: 10 a 25 | X22: =X21/V23 -> 214.87603 | Y22: =Y21/V23 -> 257.85124 | Z22: =Z21/V23 -> 309.42149 | AA22: =AA21/V23 -> 371.30579 | AB22: =AB21/V23 -> 445.56694 | AC22: 320 | AE22: =Bajadas!S7 -> 440752 | AF22: =Bajadas!U7 -> 1129.96 | AG22: =Bajadas!AT41 -> 312
A23: 200 | B23: =(Q32+AB45)*$B$42 -> 2042.7043 | C23: =(Q32+AB45)*$C$43 -> 2042.7043 | D23: =(Q32+AA45)*$D$43 -> 3851.783 | E23: =(Q33+Z46)*$E$43 -> 4929.1657 | F23: =(Q33+Z46)*$F$43 -> 8215.2761 | G23: =(Q33+Z46)*$G$43 -> 13144.442 | H23: =(Q33+Y46)*$H$43 -> 14123.788 | I23: =(Q33+Y47)*$I$43 -> 21501.048 | J23: =(Q33+Y47)*$J$43 -> 26108.415 | K23: =(Q33+Y47)*$J$43 -> 26108.415 | L23: =(Q33+X47)*$L$43 -> 36998.034 | M23: =(Q34+X48)*$M$43 -> 48253.332 | N23: =(Q35+X49)*$N$43 -> 91174.843 | O23: =(Q35+X49)*$O$43 -> 136081.85 | Q23: =Bajadas!S7 -> 440752 | R23: 51 a 100 | S23: 1 | T23: cm2 | U23: =U22 -> 1276 | V23: 1.1 | W23: 26 a 50 | X23: =X22/V24 -> 195.34185 | Y23: =Y22/V24 -> 234.41022 | Z23: =Z22/V24 -> 281.29226 | AA23: =AA22/V24 -> 337.55071 | AB23: =AB22/V24 -> 405.06086 | AC23: 291 | AE23: =Bajadas!S8 -> 426978.5 | AF23: =Bajadas!U8 -> 1094.6488 | AG23: =Bajadas!AT42 -> 292.5
A24: 300 | B24: =(Q32+AB45)*$B$42 -> 2042.7043 | C24: =(Q33+AB45)*$C$44 -> 3802.9186 | D24: =(Q33+AA46)*$D$44 -> 5194.6493 | E24: =(Q33+Z46)*$E$44 -> 8215.2761 | F24: =(Q33+Z46)*$F$44 -> 11501.387 | G24: =(Q33+Z47)*$G$44 -> 17631.135 | H24: =(Q33+Y47)*$H$44 -> 19965.258 | I24: =(Q33+Y47)*$I$44 -> 30715.782 | J24: =(Q33+Y47)*$J$44 -> 38394.728 | K24: =(Q33+Y47)*$J$44 -> 38394.728 | L24: =(Q34+X48)*$L$44 -> 53930.195 | M24: =(Q34+X48)*$M$44 -> 70960.783 | N24: =(Q35+X49)*$N$44 -> 136081.85 | O24: =(Q36+X49)*$O$44 -> 198826.09 | Q24: =Bajadas!S8 -> 426978.5 | R24: 101 a 300 | S24: 1 | T24: cm2 | U24: =U23 -> 1276 | V24: 1.1 | W24: 51 a 100 | X24: =X23/V25 -> 177.5835 | Y24: =Y23/V25 -> 213.1002 | Z24: =Z23/V25 -> 255.72024 | AA24: =AA23/V25 -> 306.86429 | AB24: =AB23/V25 -> 368.23714 | AC24: 264 | AE24: =Bajadas!S9 -> 413205 | AF24: =Bajadas!U9 -> 1059.3375 | AG24: =Bajadas!AT43 -> 273
A25: 500 | B25: =(Q32+AB45)*$B$42 -> 2042.7043 | C25: =(Q33+AB45)*$C$45 -> 3802.9186 | D25: =(Q33+AA46)*$D$45 -> 8657.7489 | E25: =(Q33+Z46)*$E$45 -> 13144.442 | F25: =(Q33+Z47)*$F$45 -> 19233.965 | G25: =(Q33+Z47)*$G$45 -> 28850.948 | H25: =(Q33+Y47)*$H$45 -> 32251.571 | I25: =(Q34+Y48)*$I$45 -> 49980.154 | J25: =(Q34+Y48)*$J$45 -> 61740.19 | K25: =(Q34+Y48)*$J$45 -> 61740.19 | L25: =(Q35+X49)*$L$45 -> 85731.569 | M25: =(Q35+X49)*$M$45 -> 114308.76 | N25: =(Q36+X49)*$N$45 -> 221359.72 | O25: =(Q36+X49)*$O$45 -> 265101.46 | Q25: =Bajadas!S9 -> 413205 | R25: 301 a 500 | S25: 1 | U25: =U24 -> 1276 | V25: 1.1 | W25: mas de 100 | X25: =X24/V25 -> 161.43954 | Y25: =Y24/V26 -> 193.72745 | Z25: =Z24/V26 -> 232.47294 | AA25: =AA24/V26 -> 278.96753 | AB25: =AB24/V26 -> 334.76104 | AC25: 240 | AE25: =Bajadas!S10 -> 399431.5 | AF25: =Bajadas!U10 -> 1024.0262 | AG25: =Bajadas!AT44 -> 253.5
A26: 1000 | B26: =(Q37+AB45)*$B$42 -> 1760.2143 | C26: =(Q33+AB46)*$C$46 -> 7350.9729 | D26: =(Q33+AA46)*$D$46 -> 15583.948 | E26: =(Q33+Z47)*$E$46 -> 24042.457 | F26: =(Q33+Z47)*$F$46 -> 36865.1 | G26: =(Q34+Z48)*$G$46 -> 55114.243 | H26: =(Q34+Y48)*$H$46 -> 61740.19 | I26: =(Q35+Y49)*$I$46 -> 94268.347 | J26: =(Q35+Y49)*$J$46 -> 118187.18 | K26: =(Q35+Y49)*$J$46 -> 118187.18 | L26: =(Q36+X49)*$L$46 -> 165688.41 | M26: =(Q36+X49)*$M$46 -> 221359.72 | N26: =(Q37+X49)*$N$46 -> 430925.48 | O26: =(Q37+X49)*$O$46 -> 645098.02 | Q26: =Bajadas!S10 -> 399431.5 | R26: 501 a 1000 | S26: 1 | V26: 1.1
Q27: =Bajadas!S11 -> 385658 | R27: 1000
S28: 1 | V28: cm2 | W28: medio corte | X28: simple | Y28: medio | Z28: complejo | AA28: muy complejo | AB28: ultra complejo | AE28: sticker | AF28: opp | AG28: 5to color
W29: 1 a 2 | X29: =X20/U20 -> 0.20376176 | Y29: =Y20/U20 -> 0.24451411 | Z29: =Z20/U20 -> 0.29341693 | AA29: =AA20/U20 -> 0.35210031 | AB29: =AB20/U20 -> 0.42252038 | AE29: =AE19/U20 -> 410.1826 | AF29: =AF19/U20 -> 1.0515889 | AG29: =AG19/U20 -> 0.2903605
A30: calcos | B30: 1cm. | C30: 2cm. | D30: 3cm. | E30: 4cm. | F30: 5cm. | G30: 6cm. | H30: 7cm. | I30: 8cm. | J30: 9cm. | K30: 10cm | L30: 11cm. | M30: 12-13-14-15cm. | N30: 16/17cm. | O30: 18/19/20cm. | Q30: =Bajadas!U2 -> OPP blco o blanco | W30: 3 a 9 | X30: =X21/U20 -> 0.18523796 | Y30: =Y21/U20 -> 0.22228555 | Z30: =Z21/U20 -> 0.26674266 | AA30: =AA21/U20 -> 0.32009119 | AB30: =AB21/U20 -> 0.38410943 | AE30: =AE20/U21 -> 367.00549 | AF30: =AF20/U21 -> 0.94089538 | AG30: =AG20/U21 -> 0.27507837
A31: 100 | B31: =B23+(T32*B59) -> 2178.967 | C31: =C23+(T32*C59) -> 2178.967 | D31: =D22+(T32*D59) -> 2062.1542 | E31: =E22+(T32*E59) -> 3929.6204 | F31: =F22+(T33*F59) -> 5307.2947 | G31: =G22+(T33*G59) -> 7076.3929 | H31: =H22+(T33*H59) -> 8476.7639 | I31: =I22+(T33*I59) -> 11867.469 | J31: =J22+(T33*J59) -> 15258.175 | K31: =K22+(T33*K59) -> 15258.175 | L31: =L22+(T33*L59) -> 20877.536 | M31: =M22+(T33*M59) -> 27301.394 | N31: =N22+(T33*N59) -> 52538.794 | O31: =O22+(T33*O59) -> 68435.12 | T31: laca uv | W31: 10 a 25 | X31: =X22/U20 -> 0.16839814 | Y31: =Y22/U20 -> 0.20207777 | Z31: =Z22/U20 -> 0.24249333 | AA31: =AA22/U20 -> 0.29099199 | AB31: =AB22/U20 -> 0.34919039 | AE31: =AE21/U22 -> 356.21121 | AF31: =AF21/U22 -> 0.91322198 | AG31: =AG21/U22 -> 0.25979624
A32: 200 | B32: =B24+(T32*B60) -> 2178.967 | C32: =C23+(T32*C60) -> 2178.967 | D32: =D23+(T32*D60) -> 4124.3084 | E32: =E23+(T33*E60) -> 5307.2947 | F32: =F23+(T33*F60) -> 8845.4911 | G32: =G23+(T33*G60) -> 14152.786 | H32: =H23+(T33*H60) -> 15258.175 | I32: =I23+(T33*I60) -> 23265.65 | J32: =J23+(T33*J60) -> 28251.146 | K32: =K23+(T33*K60) -> 28251.146 | L32: =L23+(T33*L60) -> 40149.109 | M32: =M23+(T33*M60) -> 52538.794 | N32: =N23+(T34*N60) -> 98935.004 | O32: =O23+(T34*O60) -> 147664.18 | Q32: =Bajadas!U4 -> 1341.8275 | R32: 1 | S32: 1 a 10 | T32: =Laminado!E7 -> 136.2627 | W32: 26 a 50 | X32: =X23/U20 -> 0.15308922 | Y32: =Y23/U20 -> 0.18370707 | Z32: =Z23/U20 -> 0.22044848 | AA32: =AA23/U20 -> 0.26453818 | AB32: =AB23/U20 -> 0.31744581 | AE32: =AE22/U23 -> 345.41693 | AF32: =AF22/U23 -> 0.88554859 | AG32: =AG22/U23 -> 0.24451411
A33: 300 | B33: =B25+(T32*B61) -> 2178.967 | C33: =C24+(T33*C61) -> 4055.0046 | D33: =D24+(T33*D61) -> 5572.7783 | E33: =E24+(T33*E61) -> 8845.4911 | F33: =F24+(T33*F61) -> 12383.688 | G33: =G24+(T33*G61) -> 19017.608 | H33: =H24+(T33*H61) -> 21603.817 | I33: =I24+(T33*I61) -> 33236.642 | J33: =J24+(T33*J61) -> 41545.803 | K33: =K24+(T33*K61) -> 41545.803 | L33: =L24+(T33*L61) -> 58719.829 | M33: =M24+(T33*M61) -> 77262.933 | N33: =N24+(T34*N61) -> 147664.18 | O33: =O24+(T35*O61) -> 214666.63 | Q33: =Bajadas!U5 -> 1200.5825 | R33: 2 a 25 | S33: 11 a 50 | T33: =Laminado!E8 -> 126.043 | W33: 51 a 100 | X33: =X24/U20 -> 0.13917202 | Y33: =Y24/U20 -> 0.16700642 | Z33: =Z24/U20 -> 0.20040771 | AA33: =AA24/U20 -> 0.24048925 | AB33: =AB24/U20 -> 0.2885871 | AE33: =AE23/U24 -> 334.62265 | AF33: =AF23/U24 -> 0.8578752 | AG33: =AG23/U24 -> 0.22923197
A34: 500 | B34: =B25+(T32*B62) -> 2178.967 | C34: =C25+(T33*C62) -> 4055.0046 | D34: =D25+(T33*D62) -> 9287.9639 | E34: =E25+(T33*E62) -> 14152.786 | F34: =F25+(T33*F62) -> 20746.481 | G34: =G25+(T33*G62) -> 31119.722 | H34: =H25+(T33*H62) -> 34898.474 | I34: =I25+(T33*I62) -> 54265.616 | J34: =J25+(T33*J62) -> 67033.996 | K34: =K25+(T33*K62) -> 67033.996 | L34: =L25+(T33*L62) -> 93672.278 | M34: =M25+(T34*M62) -> 124037.92 | N34: =N25+(T35*N62) -> 238995.52 | O34: =O25+(T36*O62) -> 284859.55 | Q34: =Bajadas!U6 -> 1165.2713 | R34: 26 a 50 | S34: 51 a 100 | T34: =Laminado!E9 -> 115.8233 | W34: mas de 100 | X34: =X25/U21 -> 0.12652002 | Y34: =Y25/U21 -> 0.15182402 | Z34: =Z25/U21 -> 0.18218883 | AA34: =AA25/U21 -> 0.21862659 | AB34: =AB25/U21 -> 0.26235191 | AC34: 0.2529 | AE34: =AE24/U25 -> 323.82837 | AF34: =AF24/U25 -> 0.8302018 | AG34: =AG24/U25 -> 0.21394984 | AH34: 0.88
A35: 1000 | B35: =B26+(T32*B63) -> 1896.477 | C35: =C26+(T33*C63) -> 7855.1449 | D35: =D26+(T33*D63) -> 16592.292 | E35: =E26+(T33*E63) -> 25933.102 | F35: =F26+(T33*F63) -> 39764.089 | G35: =G26+(T33*G63) -> 59651.791 | H35: =H26+(T33*H63) -> 67033.996 | I35: =I26+(T34*I63) -> 102028.51 | J35: =J26+(T34*J63) -> 127916.34 | K35: =K26+(T34*K63) -> 127916.34 | L35: =L26+(T35*L63) -> 178888.86 | M35: =M26+(T35*M63) -> 238995.52 | N35: =N26+(T36*N63) -> 463921.49 | O35: =O26+(T37*O63) -> 691086.69 | Q35: =Bajadas!U7 -> 1129.96 | R35: 51 a 100 | S35: 100 | T35: =Laminado!E10 -> 105.6036
Q36: =Bajadas!U8 -> 1094.6488 | R36: 101 a 300 | T36: =Laminado!E11 -> 98.790461
Q37: =Bajadas!U9 -> 1059.3375 | R37: 301 a 500 | T37: =Laminado!E12 -> 91.977326
Q38: =Bajadas!U10 -> 1024.0262 | R38: 501 a 1000 | T38: =Laminado!E13 -> 85.16419
Q39: =Bajadas!U11 -> 988.715 | R39: 1000
B40: 1204 | C40: 294 | D40: 117 | E40: 70 | F40: 45 | G40: 28 | H40: 24 | I40: 15 | J40: 12 | K40: 12 | L40: 8 | M40: 6 | N40: 3 | O40: 2 | Q40: =Bajadas!U12
B41: 1CM | C41: 2CM | D41: 3CM | E41: 4CM | F41: 5CM | G41: 6CM | H41: 7CM | I41: 8CM | J41: 9CM | K41: 10 | L41: 11 | M41: 12-13-14-15 | N41: 16/17 | O41: 18/19/20/21/22 | T41: laca uv
A42: 100 | B42: 1 | C42: 1 | D42: 1 | E42: 2 | F42: 3 | G42: 4 | H42: 5 | I42: 7 | J42: 9 | K42: 9 | L42: 13 | M42: 17 | N42: 34 | O42: 50 | S42: 1 a 10 | T42: =T32 -> 136.2627
A43: 200 | B43: 1 | C43: 1 | D43: 2 | E43: 3 | F43: 5 | G43: 8 | H43: 9 | I43: 14 | J43: 17 | K43: 17 | L43: 25 | M43: 34 | N43: 67 | O43: 100 | S43: 11 a 50 | T43: =T33 -> 126.043 | W43: 1.3 | X43: 1.3 | Y43: 1.3 | Z43: 1.3 | AA43: 1.3 | AB43: 1.3
A44: 300 | B44: 1 | C44: 2 | D44: 3 | E44: 5 | F44: 7 | G44: 11 | H44: 13 | I44: 20 | J44: 25 | K44: 25 | L44: 38 | M44: 50 | N44: 100 | O44: 150 | S44: 51 a 100 | T44: =T34 -> 115.8233 | U44: TROQUELADO | V44: OPP | X44: SIMPLE | Y44: MEDIO | Z44: COMPLEJO | AA44: MUY COMPLEJO | AB44: ULTRA COMPLEJO
A45: 500 | B45: 1 | C45: 2 | D45: 5 | E45: 8 | F45: 12 | G45: 18 | H45: 21 | I45: 34 | J45: 42 | K45: 42 | L45: 63 | M45: 84 | N45: 167 | O45: 200 | S45: 100 | T45: =T35 -> 105.6036 | V45: 1.3 | W45: 1 a 2 | X45: =X20*W43 -> 338 | Y45: =Y20*X43 -> 405.6 | Z45: =Z20*Y43 -> 486.72 | AA45: =AA20*Z43 -> 584.064 | AB45: =AB20*AA43 -> 700.8768
A46: 1000 | B46: 1 | C46: 4 | D46: 9 | E46: 15 | F46: 23 | G46: 36 | H46: 42 | I46: 67 | J46: 84 | K46: 84 | L46: 125 | M46: 167 | N46: 334 | O46: 500 | W46: 3 a 9 | X46: =X21*W43 -> 307.27273 | Y46: =Y21*X43 -> 368.72727 | Z46: =Z21*Y43 -> 442.47273 | AA46: =AA21*Z43 -> 530.96727 | AB46: =AB21*AA43 -> 637.16073
W47: 10 a 25 | X47: =X22*W43 -> 279.33884 | Y47: =Y22*X43 -> 335.20661 | Z47: =Z22*Y43 -> 402.24793 | AA47: =AA22*Z43 -> 482.69752 | AB47: =AB22*AA43 -> 579.23702 | AE47: sticker | AF47: opp | AG47: 5to color
W48: 26 a 50 | X48: =X23*W43 -> 253.9444 | Y48: =Y23*X43 -> 304.73328 | Z48: =Z23*Y43 -> 365.67994 | AA48: =AA23*Z43 -> 438.81593 | AB48: =AB23*AA43 -> 526.57911 | AE48: =AE29*U53 -> 4101826 | AF48: =AF29*U53 -> 10515.889 | AG48: =AG29*U53 -> 2903.605
W49: 51 a 100 | X49: =X24*W43 -> 230.85855 | Y49: =Y24*X43 -> 277.03026 | Z49: =Z24*Y43 -> 332.43631 | AA49: =AA24*Z43 -> 398.92357 | AB49: =AB24*AA43 -> 478.70828 | AE49: =AE30*U54 -> 3670054.9 | AF49: =AF30*U54 -> 9408.9538 | AG49: =AG30*U54 -> 2750.7837
W50: mas de 100 | X50: =X25*W43 -> 209.87141 | Y50: =Y25*X43 -> 251.84569 | Z50: =Z25*Y43 -> 302.21483 | AA50: =AA25*Z43 -> 362.65779 | AB50: =AB25*AA43 -> 435.18935 | AC50: 420 | AE50: =AE31*U55 -> 3562112.1 | AF50: =AF31*U55 -> 9132.2198 | AG50: =AG31*U55 -> 2597.9624
T51: GIGANTO | U51: u opp | AE51: =AE32*U56 -> 3454169.3 | AF51: =AF32*U56 -> 8855.4859 | AG51: =AG32*U56 -> 2445.1411
T52: 1 m2 | U52: 100 | V52: 100 | X52: SIMPLE | Y52: MEDIO | Z52: COMPLEJO | AA52: MUY COMPLEJO | AB52: ULTRA COMPLEJO | AE52: =AE33*U57 -> 3346226.5 | AF52: =AF33*U57 -> 8578.752 | AG52: =AG33*U57 -> 2292.3197
T53: cm2 | U53: =U52*V52 -> 10000 | V53: cm2 | W53: 1 a 2 | X53: =X29*X43 -> 0.26489028 | Y53: =Y29*Y43 -> 0.31786834 | Z53: =Z29*Z43 -> 0.38144201 | AA53: =AA29*AA43 -> 0.45773041 | AB53: =AB29*AB43 -> 0.54927649 | AE53: =AE34*U58 -> 3238283.7 | AF53: =AF34*U58 -> 8302.018 | AG53: =AG34*U58 -> 2139.4984
T54: cm2 | U54: =U53 -> 10000 | W54: 3 a 9 | X54: =X30*X43 -> 0.24080935 | Y54: =Y30*Y43 -> 0.28897122 | Z54: =Z30*Z43 -> 0.34676546 | AA54: =AA30*AA43 -> 0.41611855 | AB54: =AB30*AB43 -> 0.49934226 | AE54: =AE35*U59 -> 0 | AG54: =AG35*U59 -> 0 | AH54: 88209
T55: cm2 | U55: =U54 -> 10000 | W55: 10 a 25 | X55: =X31*X43 -> 0.21891759 | Y55: =Y31*Y43 -> 0.26270111 | Z55: =Z31*Z43 -> 0.31524133 | AA55: =AA31*AA43 -> 0.37828959 | AB55: =AB31*AB43 -> 0.45394751
T56: cm2 | U56: =U55 -> 10000 | W56: 26 a 50 | X56: =X32*X43 -> 0.19901599 | Y56: =Y32*Y43 -> 0.23881919 | Z56: =Z32*Z43 -> 0.28658302 | AA56: =AA32*AA43 -> 0.34389963 | AB56: =AB32*AB43 -> 0.41267956
B57: 1204 | C57: 260 | D57: 117 | E57: 70 | F57: 45 | G57: 28 | H57: 24 | I57: 15 | J57: 12 | K57: 12 | L57: 8 | M57: 6 | N57: 3 | O57: 2 | T57: cm2 | U57: =U56 -> 10000 | W57: 51 a 100 | X57: =X33*X43 -> 0.18092363 | Y57: =Y33*Y43 -> 0.21710835 | Z57: =Z33*Z43 -> 0.26053002 | AA57: =AA33*AA43 -> 0.31263603 | AB57: =AB33*AB43 -> 0.37516323
B58: 1CM | C58: 2CM | D58: 3CM | E58: 4CM | F58: 5CM | G58: 6CM | H58: 7CM | I58: 8CM | J58: 9CM | K58: 10 | L58: 11 | M58: 12-13-14-15 | N58: 16/17 | O58: 18/19/20/21/22 | T58: cm2 | U58: =U57 -> 10000 | W58: mas de 100 | AC58: 0.328
A59: 100 | B59: 1 | C59: 1 | D59: 1 | E59: 2 | F59: 3 | G59: 4 | H59: 5 | I59: 7 | J59: 9 | K59: 9 | L59: 13 | M59: 17 | N59: 34 | O59: 50
A60: 200 | B60: 1 | C60: 1 | D60: 2 | E60: 3 | F60: 5 | G60: 8 | H60: 9 | I60: 14 | J60: 17 | K60: 17 | L60: 25 | M60: 34 | N60: 67 | O60: 100
A61: 300 | B61: 1 | C61: 2 | D61: 3 | E61: 5 | F61: 7 | G61: 11 | H61: 13 | I61: 20 | J61: 25 | K61: 25 | L61: 38 | M61: 50 | N61: 100 | O61: 150
A62: 500 | B62: 1 | C62: 2 | D62: 5 | E62: 8 | F62: 12 | G62: 18 | H62: 21 | I62: 34 | J62: 42 | K62: 42 | L62: 63 | M62: 84 | N62: 167 | O62: 200 | V62: m2 | X62: SIMPLE | Y62: MEDIO | Z62: COMPLEJO | AA62: MUY COMPLEJO | AB62: ULTRA COMPLEJO
A63: 1000 | B63: 1 | C63: 4 | D63: 8 | E63: 15 | F63: 23 | G63: 36 | H63: 42 | I63: 67 | J63: 84 | K63: 84 | L63: 125 | M63: 167 | N63: 334 | O63: 500 | V63: m2 | W63: 1 a 2 | X63: =X53*U53 -> 2648.9028 | Y63: =Y53*U53 -> 3178.6834 | Z63: =Z53*U53 -> 3814.4201 | AA63: =AA53*U53 -> 4577.3041 | AB63: =AB53*U53 -> 5492.7649
V64: m2 | W64: 3 a 9 | X64: =X54*U54 -> 2408.0935 | Y64: =Y54*U54 -> 2889.7122 | Z64: =Z54*U54 -> 3467.6546 | AA64: =AA54*U54 -> 4161.1855 | AB64: =AB54*U54 -> 4993.4226
V65: m2 | W65: 10 a 25 | X65: =X55*U55 -> 2189.1759 | Y65: =Y55*U55 -> 2627.0111 | Z65: =Z55*U55 -> 3152.4133 | AA65: =AA55*U55 -> 3782.8959 | AB65: =AB55*U55 -> 4539.4751
V66: m2 | W66: 26 a 50 | X66: =X56*U56 -> 1990.1599 | Y66: =Y56*U56 -> 2388.1919 | Z66: =Z56*U56 -> 2865.8302 | AA66: =AA56*U56 -> 3438.9963 | AB66: =AB56*U56 -> 4126.7956
V67: m2 | W67: 51 a 100 | X67: =X57*U57 -> 1809.2363 | Y67: =Y57*U57 -> 2171.0835 | Z67: =Z57*U57 -> 2605.3002 | AA67: =AA57*U57 -> 3126.3603 | AB67: =AB57*U57 -> 3751.6323
W68: mas de 100 | AC68: 3287
V71: alto | W71: ancho | X71: material | Y71: medio corte | Z71: corte final | AA71: descartonado | AB71: cantidad | AC71: total
V72: 10 | W72: 10 | X72: 0.88 | Y72: 0.328 | AB72: 100 | AC72: =V72*W72*X72+Y72*AB72 -> 120.8

Sheet Bajadas
B1: BAJADAS | W1: tienda | AA1: 2 | AD1: 0.6 | AG1: 1.5 | AJ1: 0.6
B2: A3+ (32x47) | C2: Triplex | E2: 350g | G2: 300g | I2: 200g | K2: 150g | M2: 115g | O2: 90g | Q2: 80 grs | S2: Sticker | T2: Imán | U2: OPP blco o blanco | W2: 350 | AA2: Precio del papel por hoja | AG2: Precio del papel por hoja
B3: 30x46 | C3: 4/0 | D3: 4/4 | E3: 4/0 | F3: 4/4 | G3: 4/0 | H3: 4/4 | I3: 4/0 | J3: 4/4 | K3: 4/0 | L3: 4/4 | M3: 4/0 | N3: 4/4 | O3: 4/0 | P3: 4/4 | Q3: 4/0 | R3: 4/4 | S3: 4/0 | T3: 4/0 | U3: 4/0 | Z3: Precio de papel | AA3: XL | AB3: 33X48 | AC3: 32X47 | AD3: A4 | AF3: Precio de papel | AG3: XL | AH3: 33X48 | AI3: 32X47 | AJ3: A4
B4: 1 | C4: =(AC48+AC11)*$AH$48 -> 226922.93 | D4: =(AC48*AG48+AC11)*AH48 -> 227182.28 | E4: =(AC48+AC4)*$AH$48 -> 226446.98 | F4: =(AC48*AG48+AC4)*AH48 -> 226706.33 | G4: =(AC48+AC5)*$AH$48 -> 194150.34 | H4: =(AC48*AG48+AC5)*AH48 -> 194409.69 | I4: =(AC48+AC6)*$AH$48 -> 142475.71 | J4: =(AC48*AG48+AC6)*AH48 -> 142735.06 | K4: =(AC48+AC7)*$AH$48 -> 97260.418 | L4: =(AC48*AG48+AC7)*AH48 -> 97519.768 | M4: =(AC48+AC8)*$AH$48 -> 74652.771 | N4: =(AC48*AG48+AC8)*AH48 -> 74912.121 | O4: =(AC48+AC9)*AH$48 -> 58504.451 | P4: =(AC48*AG48+AC9)*AH48 -> 58763.801 | Q4: =(AC48+AC10)*AH$48 -> 58504.451 | R4: =(AC48*AG48+AC10)*AH48 -> 58763.801 | S4: =(AC48+AC12)*AH48 -> 523393 | T4: =(AC48+$AC$14)*AH48+AC5 -> 104248.03 | U4: =(AC48+$AC$13*AF48)*AH48 -> 1341.8275 | W4: 460 | X4: 588 | Z4: 350g | AA4: =AG4*$AM$38*AA18 -> 212270.06 | AB4: =AH4*$AM$38 -> 141513.37 | AC4: =AI4*$AM$38*AC18 -> 118987.62 | AD4: =AJ4*$AM$38 -> 71392.571 | AE4: =AC4 -> 118987.62 | AF4: 350g | AG4: =AH4*$AG$1 -> 326.56932 | AH4: ='PAPEL US$'!I24 -> 217.71288 | AI4: ='PAPEL US$'!J23 -> 183.05787 | AJ4: =AI4*$AJ$1 -> 109.83473 | AN4: 28 | AO4: 71 | AQ4: 2.2
B5: 2 a 25 | C5: =(AC49+AC11)*$AH$49 -> 203036.3 | D5: =(AC49*AG49+AC11)*AH49 -> 203268.35 | E5: =(AC49+AC4)*AH$49 -> 202610.45 | F5: =(AC49*AG49+AC4)*AH49 -> 202842.5 | G5: =(AC49+AC5)*$AH$49 -> 173713.46 | H5: =(AC49*AG49+AC5)*AH49 -> 173945.51 | I5: =(AC49+AC6)*$AH$49 -> 127478.27 | J5: =(AC49*AG49+AC6)*AH49 -> 127710.32 | K5: =(AC49+AC7)*$AH$49 -> 87022.479 | L5: =(AC49*AG49+AC7)*AH49 -> 87254.529 | M5: =(AC49+AC8)*$AH$49 -> 66794.584 | N5: =(AC49*AG49+AC8)*AH49 -> 67026.634 | O5: =(AC49+AC9)*AH$49 -> 52346.088 | P5: =(AC49*AG49+AC9)*AH49 -> 52578.138 | Q5: =(AC49+AC10)*AH$49 -> 52346.088 | R5: =(AC49*AG49+AC9)*AH49 -> 52578.138 | S5: =(AC49+$AC$12*AF49)*$AH$49 -> 468299 | T5: =(AC49+$AC$14)*AH49+AC5 -> 104010.28 | U5: =(AC49+$AC$13*AF49)*AH49 -> 1200.5825 | W5: 436 | X5: 557 | Z5: 300g | AA5: =AG5*$AM$38 -> 181945.76 | AB5: =AH5*$AM$38 -> 121297.18 | AC5: =AI5*$AM$38*AC19 -> 101989.39 | AD5: =AJ5*$AM$38 -> 61193.632 | AE5: =AC5 -> 101989.39 | AF5: 300g | AG5: =AH5*$AG$1 -> 279.91656 | AH5: ='PAPEL US$'!I21 -> 186.61104 | AI5: ='PAPEL US$'!J20 -> 156.90675 | AJ5: =AI5*$AJ$1 -> 94.14405 | AQ5: 2
B6: 26 a 50 | C6: =(AC50+AC11)*$AH$50 -> 197064.65 | D6: =(AC50*AG50+AC11)*AH50 -> 197289.87 | E6: =(AC50+AC4)*AH$50 -> 196651.32 | F6: =(AC50*AG50+AC4)*AH50 -> 196876.55 | G6: =(AC50+AC5)*$AH$50 -> 168604.24 | H6: =(AC50*AG50+AC5)*AH50 -> 168829.46 | I6: =(AC50+AC6)*$AH$50 -> 123728.91 | J6: =(AC50*AG50+AC6)*AH50 -> 123954.13 | K6: =(AC50+AC7)*$AH$50 -> 84462.995 | L6: =(AC50*AG50+AC7)*AH50 -> 84688.22 | M6: =(AC50+AC8)*$AH$50 -> 64830.038 | N6: =(AC50*AG50+AC8)*AH50 -> 65055.263 | O6: =(AC50+AC9)*AH$50 -> 50806.497 | P6: =(AC50*AG50+AC9)*AH50 -> 51031.722 | Q6: =(AC50+AC10)*AH$50 -> 50806.497 | R6: =(AC50*AG50+AC10)*AH50 -> 51031.722 | S6: =(AC50+$AC$12*AF50)*$AH$50 -> 454525.5 | T6: =(AC50+$AC$14)*AH50+AC5 -> 103950.84 | U6: =(AC50+$AC$13*AF50)*AH50 -> 1165.2713 | W6: 412 | X6: 526 | Z6: 200g | AA6: =AG6*$AM$38 -> 133426.89 | AB6: =AH6*$AM$38 -> 88951.262 | AC6: =AI6*$AM$38*AC20 -> 74792.217 | AD6: =AJ6*$AM$38 -> 44875.33 | AE6: =AC6 -> 74792.217 | AF6: 200g | AG6: =AH6*$AG$1 -> 205.27214 | AH6: ='PAPEL US$'!I18 -> 136.8481 | AI6: ='PAPEL US$'!J13 -> 115.06495 | AJ6: =AI6*$AJ$1 -> 69.03897 | AQ6: 1.8
B7: 51 a 100 | C7: =(AC51+AC11)*$AH$51 -> 191092.99 | D7: =(AC51*AG51+AC11)*AH51 -> 191311.39 | E7: =(AC51+AC4)*AH$51 -> 190692.19 | F7: =(AC51*AG51+AC4)*AH51 -> 190910.59 | G7: =(AC51+AC5)*$AH$51 -> 163495.02 | H7: =(AC51*AG51+AC5)*AH51 -> 163713.42 | I7: =(AC51+AC6)*$AH$51 -> 119979.55 | J7: =(AC51*AG51+AC6)*AH51 -> 120197.95 | K7: =(AC51+AC7)*$AH$51 -> 81903.51 | L7: =(AC51*AG51+AC7)*AH51 -> 82121.91 | M7: =(AC51+AC8)*$AH$51 -> 62865.491 | N7: =(AC51*AG51+AC8)*AH51 -> 63083.891 | O7: =(AC51+AC9)*AH$51 -> 49266.906 | P7: =(AC51*AG51+AC9)*AH51 -> 49485.306 | Q7: =(AC51+AC10)*AH$51 -> 49266.906 | R7: =(AC51*AG51+AC10)*AH51 -> 49485.306 | S7: =(AC51+$AC$12*AF51)*$AH$51 -> 440752 | T7: =(AC51+$AC$14)*AH51+AC5 -> 103891.4 | U7: =(AC51+$AC$13*AF51)*AH51 -> 1129.96 | W7: 388 | X7: 495 | Z7: 150g | AA7: =AG7*$AM$38 -> 90972.882 | AB7: =AH7*$AM$38 -> 60648.588 | AC7: =AI7*$AM$38*AC21 -> 50994.694 | AD7: =AJ7*$AM$38 -> 30596.816 | AE7: =AC7 -> 50994.694 | AF7: 150g | AG7: =AH7*$AG$1 -> 139.95828 | AH7: ='PAPEL US$'!I17 -> 93.30552 | AI7: ='PAPEL US$'!J12 -> 78.453375 | AJ7: =AI7*$AJ$1 -> 47.072025 | AQ7: 1.7
B8: 101 a 300 | C8: =(AC52+AC11)*AH$52 -> 185121.33 | D8: =(AC52*AG52+AC11)*AH52 -> 185332.91 | E8: =(AC52+AC4)*AH$52 -> 184733.06 | F8: =(AC52*AG52+AC4)*AH52 -> 184944.63 | G8: =(AC52+AC5)*$AH$52 -> 158385.8 | H8: =(AC52*AG52+AC5)*AH52 -> 158597.38 | I8: =(AC52+AC6)*$AH$52 -> 116230.19 | J8: =(AC52*AG52+AC6)*AH52 -> 116441.76 | K8: =(AC52+AC7)*$AH$52 -> 79344.025 | L8: =(AC52*AG52+AC7)*AH52 -> 79555.6 | M8: =(AC52+AC8)*$AH$52 -> 60900.944 | N8: =(AC52*AG52+AC8)*AH52 -> 61112.519 | O8: =(AC52+AC9)*AH$52 -> 47727.315 | P8: =(AC52*AG52+AC9)*AH52 -> 47938.89 | Q8: =(AC52+AC10)*AH$52 -> 47727.315 | R8: =(AC52*AG52+AC10)*AH52 -> 47938.89 | S8: =(AC52+$AC$12*AF52)*$AH$52 -> 426978.5 | T8: =(AC52+$AC$14)*AH52+AC5 -> 103831.97 | U8: =(AC52+$AC$13*AF52)*AH52 -> 1094.6488 | W8: 363 | X8: 464 | Z8: 115g | AA8: =AG8*$AM$38 -> 69745.876 | AB8: =AH8*$AM$38 -> 46497.251 | AC8: =AI8*$AM$38*AC22 -> 39095.932 | AD8: =AJ8*$AM$38 -> 23457.559 | AE8: =AC8 -> 39095.932 | AF8: 115g | AG8: =AH8*$AG$1 -> 107.30135 | AH8: ='PAPEL US$'!I16 -> 71.534232 | AI8: ='PAPEL US$'!J11 -> 60.147588 | AJ8: =AI8*$AJ$1 -> 36.088552
B9: 301 a 500 | C9: =(AC53+AC11)*AH$53 -> 179149.68 | D9: =(AC53*AG52+AC11)*AH53 -> 179354.43 | E9: =(AC53+AC4)*AH$53 -> 178773.93 | F9: =(AC53*AG53+AC4)*AH53 -> 178978.68 | G9: =(AC53+AC5)*$AH$53 -> 153276.58 | H9: =(AC53*AG53+AC5)*AH53 -> 153481.33 | I9: =(AC53+AC6)*$AH$53 -> 112480.83 | J9: =(AC53*AG53+AC6)*AH53 -> 112685.58 | K9: =(AC53+AC7)*$AH$53 -> 76784.541 | L9: =(AC53*AG53+AC7)*AH53 -> 76989.291 | M9: =(AC53+AC8)*$AH$53 -> 58936.398 | N9: =(AC53*AG53+AC8)*AH53 -> 59141.148 | O9: =(AC53+AC9)*AH$53 -> 46187.724 | P9: =(AC53*AG53+AC9)*AH53 -> 46392.474 | Q9: =(AC53+AC10)*AH$53 -> 46187.724 | R9: =(AC53*AG53+AC10)*AH53 -> 46392.474 | S9: =(AC53+$AC$12*AF53)*$AH$53 -> 413205 | T9: =(AC53+$AC$14)*AH53+AC5 -> 103772.53 | U9: =(AC53+$AC$13*AF53)*AH53 -> 1059.3375 | W9: 339 | X9: 433 | Z9: 90g | AA9: =AG9*$AM$38 -> 54583.729 | AB9: =AH9*$AM$38 -> 36389.153 | AC9: =AI9*$AM$38*AC23 -> 30596.816 | AD9: =AJ9*$AM$38 -> 18358.09 | AE9: =AC9 -> 30596.816 | AF9: 90g | AG9: =AH9*$AG$1 -> 83.974968 | AH9: ='PAPEL US$'!I15 -> 55.983312 | AI9: ='PAPEL US$'!J10 -> 47.072025 | AJ9: =AI9*$AJ$1 -> 28.243215
B10: 501 a 1000 | C10: =(AC54+AC11)*AH$54 -> 173178.02 | D10: =(AC54*AG54+AC11)*AH54 -> 173375.95 | E10: =(AC54+AC4)*AH$54 -> 172814.8 | F10: =(AC54*AG54+AC4)*AH54 -> 173012.72 | G10: =(AC54+AC5)*$AH$54 -> 148167.36 | H10: =(AC54*AG54+AC5)*AH54 -> 148365.29 | I10: =(AC54+AC6)*$AH$54 -> 108731.47 | J10: =(AC54*AG54+AC6)*AH54 -> 108929.39 | K10: =(AC54+AC7)*$AH$54 -> 74225.056 | L10: =(AC54*AG54+AC7)*AH54 -> 74422.981 | M10: =(AC54+AC8)*$AH$54 -> 56971.851 | N10: =(AC54*AG54+AC8)*AH54 -> 57169.776 | O10: =(AC54+AC9)*AH$54 -> 44648.134 | P10: =(AC54*AG54+AC9)*AH54 -> 44846.059 | Q10: =(AC54+AC10)*AH$54 -> 44648.134 | R10: =(AC54*AG54+AC10)*AH54 -> 44846.059 | S10: =(AC54+$AC$12*AF54)*$AH$54 -> 399431.5 | T10: =(AC54+$AC$14)*AH54+AC5 -> 103713.09 | U10: =(AC54+$AC$13*AF54)*AH54 -> 1024.0262 | W10: 315 | X10: 402 | Z10: Obra | AA10: =AG10*$AM$38 -> 54583.729 | AB10: =AH10*$AM$38 -> 36389.153 | AC10: =AI10*$AM$38*AC24 -> 30596.816 | AD10: =AJ10*$AM$38 -> 18358.09 | AE10: =AC10 -> 30596.816 | AF10: Obra | AG10: =AH10*$AG$1 -> 83.974968 | AH10: ='PAPEL US$'!I8 -> 55.983312 | AI10: ='PAPEL US$'!J6 -> 47.072025 | AJ10: =AI10*$AJ$1 -> 28.243215
B11: 1000 | C11: =(AC55+AC11)*AH$55 -> 167206.37 | D11: =(AC55*AG55+AC11)*AH55 -> 167397.47 | E11: =(AC55+AC4)*AH$55 -> 166855.67 | F11: =(AC55*AG55+AC4)*AH55 -> 167046.77 | G11: =(AC55+AC5)*$AH$55 -> 143058.14 | H11: =(AC55*AG55+AC5)*AH55 -> 143249.24 | I11: =(AC55+AC6)*$AH$55 -> 104982.1 | J11: =(AC55*AG55+AC6)*AH55 -> 105173.2 | K11: =(AC55+AC7)*$AH$55 -> 71665.571 | L11: =(AC55*AG55+AC7)*AH55 -> 71856.671 | M11: =(AC55+AC8)*$AH$55 -> 55007.305 | N11: =(AC55*AG55+AC8)*AH55 -> 55198.405 | O11: =(AC55+AC9)*AH$55 -> 43108.543 | P11: =(AC55*AG55+AC9)*AH55 -> 43299.643 | Q11: =(AC55+AC10)*AH$55 -> 43108.543 | R11: =(AC55*AG55+AC10)*AH55 -> 43299.643 | S11: =(AC55+$AC$12*AF55)*$AH$55 -> 385658 | T11: =(AC55+$AC$14)*AH55+AC5 -> 103653.65 | U11: =(AC55+$AC$13*AF55)*AH55 -> 988.715 | W11: 291 | X11: 371 | Z11: Triplex | AA11: =AG11*$AM$38 -> 178857.18 | AB11: =AH11*$AM$38 -> 119238.12 | AC11: =AI11*$AM$38*AC25 -> 119238.12 | AD11: =AJ11*$AM$38 -> 71542.871 | AE11: =AC11 -> 119238.12 | AF11: Triplex | AG11: =AH11*$AG$1 -> 275.16489 | AH11: ='PAPEL US$'!I29 -> 183.44326 | AI11: ='PAPEL US$'!J29 -> 183.44326 | AJ11: =AI11*$AJ$1 -> 110.06596
B12: XA3 (33x48) | C12: Triplex | E12: 350g | G12: 300g | I12: 200g | K12: 150g | M12: 115g | O12: 90g | Q12: OBRA | S12: Sticker | Z12: Sticker | AA12: =AG12*$AM$38 -> 495495 | AB12: =AH12*$AM$38 -> 330330 | AC12: =AI12*$AM$38*AC26 -> 275275 | AD12: =AJ12*$AM$38 -> 165165 | AE12: =AC12 -> 275275 | AF12: Sticker | AG12: =AH12*$AG$1 -> 762.3 | AH12: ='PAPEL US$'!L33 -> 508.2 | AI12: ='PAPEL US$'!J31 -> 423.5 | AJ12: =AI12*$AJ$1 -> 254.1
B13: 31x47 | C13: 4/0 | D13: 4/4 | E13: 4/0 | F13: 4/4 | G13: 4/0 | H13: 4/4 | I13: 4/0 | J13: 4/4 | K13: 4/0 | L13: 4/4 | M13: 4/0 | N13: 4/4 | O13: 4/0 | P13: 4/4 | Q13: 4/0 | R13: 4/4 | S13: 4/0 | Z13: OPP | AA13: =AG13*$AM$38 -> 0 | AB13: =AH13*$AM$38 -> 511.225 | AC13: =AI13*$AM$38*AC27 -> 511.225 | AD13: =AJ13*$AM$38 -> 0 | AE13: =AC13 -> 511.225 | AF13: OPP | AH13: ='PAPEL US$'!I36 -> 0.7865 | AI13: ='PAPEL US$'!J36 -> 0.7865
B14: 1 | C14: =(AB48+AB11)*$AH$48 -> 226922.93 | D14: =(AB48*AG48+AB11)*AH48 -> 227182.28 | E14: =(AB48+AB4)*$AH$48 -> 269245.91 | F14: =(AB48*AG48+AB4)*AH48 -> 269505.26 | G14: =(AB48+AB5)*$AH$48 -> 230835.13 | H14: =(AB48*AG48+AB5)*AH48 -> 231094.48 | I14: =(AB48+AB6)*$AH$48 -> 169377.9 | J14: =(AB48*AG48+AB6)*AH48 -> 169637.25 | K14: =(AB48+AB7)*$AH$48 -> 115602.82 | L14: =(AB48*AG48+AB7)*AH48 -> 115862.17 | M14: =(AB48+AB8)*$AH$48 -> 88715.277 | N14: =(AB48*AG48+AB8)*AH48 -> 88974.627 | O14: =(AB48+AB9)*$AH$48 -> 69509.89 | P14: =(AB48*AG48+AB9)*AH48 -> 69769.24 | Q14: =(AB48+AB10)*$AH$48 -> 69509.89 | R14: =(AB48*AG48+AB10)*AH48 -> 69769.24 | S14: =(AB48+AB12)*$AH$48 -> 627997.5 | W14: 533 | X14: 660 | Z14: Imán | AA14: =AG14*$AM$38 -> 0 | AB14: =AH14*$AM$38 -> #VALUE! | AC14: ='PAPEL US$'!H48 -> 993.76 | AF14: Imán | AH14: =AM41*AH26 -> #VALUE! | AI14: =AI5+'PAPEL US$'!J49 -> 1288.6534 | AJ14: 0
B15: 2 a 25 | C15: =(AB49+AB11)*$AH$49 -> 203036.3 | D15: =(AB49*AG49+AB11)*AH49 -> 203268.35 | E15: =(AB49+AB4)*$AH$49 -> 240904.23 | F15: =(AB49*AG49+AB4)*AH49 -> 241136.28 | G15: =(AB49+AB5)*$AH$49 -> 206536.7 | H15: =(AB49*AG49+AB5)*AH49 -> 206768.75 | I15: =(AB49+AB6)*$AH$49 -> 151548.65 | J15: =(AB49*AG49+AB6)*AH49 -> 151780.7 | K15: =(AB49+AB7)*$AH$49 -> 103434.1 | L15: =(AB49*AG49+AB8)*AH49 -> 79608.876 | M15: =(AB49+AB8)*$AH$49 -> 79376.826 | N15: =(AB49*AG49+AB8)*AH49 -> 79608.876 | O15: =(AB49+AB9)*$AH$49 -> 62193.06 | P15: =(AB49*AG49+AB9)*AH49 -> 62425.11 | Q15: =(AB49+AB10)*$AH$49 -> 62193.06 | R15: =(AB49*AG49+AD10)*AH49 -> 31772.303 | S15: =(AB49+AB12)*$AH$49 -> 561892.5 | W15: 504 | X15: 625
B16: 26 a 50 | C16: =(AB50+AB11)*$AH$50 -> 197064.65 | D16: =(AB50*AG50+AB12)*AH50 -> 545591.47 | E16: =(AB50+AB4)*$AH$50 -> 233818.81 | F16: =(AB50*AG50+AB4)*AH50 -> 234044.04 | G16: =(AB50+AB5)*$AH$50 -> 200462.09 | H16: =(AB50*AG50+AB5)*AH50 -> 200687.32 | I16: =(AB50+AB6)*$AH$50 -> 147091.33 | J16: =(AB50*AG50+AB6)*AH50 -> 147316.56 | K16: =(AB50+AB7)*$AH$50 -> 100391.92 | L16: =(AB50*AG50+AB8)*AH50 -> 77267.439 | M16: =(AB50+AB8)*$AH$50 -> 77042.214 | N16: =(AB50*AG50+AB8)*AH50 -> 77267.439 | O16: =(AB50+AB9)*$AH$50 -> 60363.852 | P16: =(AB50*AG50+AB9)*AH50 -> 60589.077 | Q16: =(AB50+AB10)*$AH$50 -> 60363.852 | R16: =(AB50*AG50+AD10)*AH50 -> 30837.823 | S16: =(AB50+AB12)*$AH$50 -> 545366.25 | W16: 476 | X16: 590 | Z16: Coeficiente papel | AB16: Parametros ajustables
B17: 51 a 100 | C17: =(AB51+AB11)*$AH$51 -> 191092.99 | D17: =(AB51*AG51+AB11)*AH51 -> 191311.39 | E17: =(AB51+AB4)*$AH$51 -> 226733.4 | F17: =(AB51*AG51+AB4)*AH51 -> 226951.8 | G17: =(AB51+AB5)*$AH$51 -> 194387.48 | H17: =(AB51*AG51+AB5)*AH51 -> 194605.88 | I17: =(AB51+AB6)*$AH$51 -> 142634.02 | J17: =(AB51*AG51+AB6)*AH51 -> 142852.42 | K17: =(AB51+AB7)*$AH$51 -> 97349.741 | L17: =(AB51*AG51+AB8)*AH51 -> 74926.001 | M17: =(AB51+AB8)*$AH$51 -> 74707.601 | N17: =(AB51*AG51+AB8)*AH51 -> 74926.001 | O17: =(AB51+AB9)*$AH$51 -> 58534.644 | P17: =(AB51*AG51+AB9)*AH51 -> 58753.044 | Q17: =(AB51+AB10)*$AH$51 -> 58534.644 | R17: =(AB51*AG51+AD10)*AH51 -> 29903.344 | S17: =(AB51+AB12)*$AH$51 -> 528840 | W17: 448 | X17: 555 | AA17: XL | AB17: 33X48 | AC17: 32X47 | AD17: A4 | AF17: COSTO DE BAJADA | AG17: (costo de papel x coef ganacia) + (costo clic * coef 4/0) + (costo clic x coef 4/4)
B18: 101 a 300 | C18: =(AB52+AB11)*$AH$52 -> 185121.33 | D18: =(AB52*AG52+AB11)*AH52 -> 185332.91 | E18: =(AB52+AB4)*$AH$52 -> 219647.98 | F18: =(AB52*AG52+AB4)*AH52 -> 219859.55 | G18: =(AC52+AB5)*$AH$52 -> 188312.87 | H18: =(AB52*AG52+AB5)*AH52 -> 188524.45 | I18: =(AB52+AB6)*$AH$52 -> 138176.71 | J18: =(AB52*AG52+AB6)*AH52 -> 138388.28 | K18: =(AB52+AB7)*$AH$52 -> 94307.561 | L18: =(AB52*AG52+AB8)*AH52 -> 72584.564 | M18: =(AB52+AB8)*$AH$52 -> 72372.989 | N18: =(AB52*AG52+AB8)*AH52 -> 72584.564 | O18: =(AB52+AB9)*$AH$52 -> 56705.437 | P18: =(AB52*AG52+AB9)*AH52 -> 56917.012 | Q18: =(AB52+AB10)*$AH$52 -> 56705.437 | R18: =(AB52*AG52+AD10)*AH52 -> 28968.864 | S18: =(AB52+AB12)*$AH$52 -> 512313.75 | W18: 436 | X18: 536 | Z18: 350g | AA18: 1 | AB18: 1 | AC18: 1 | AD18: 1 | AF18: COSTO DE PAPEL | AG18: costo de pliego/coef de corte
B19: 301 a 500 | C19: =(AB53+AB11)*$AH$53 -> 179149.68 | D19: =(AB53*AG53+AB11)*AH53 -> 179354.43 | E19: =(AB53+AB4)*$AH$53 -> 212562.56 | F19: =(AB53*AG53+AB4)*AH53 -> 212767.31 | G19: =(AC53+AB5)*$AH$53 -> 182238.26 | H19: =(AB53*AG53+AB5)*AH53 -> 182443.01 | I19: =(AB53+AB6)*$AH$53 -> 133719.39 | J19: =(AB53*AG53+AB6)*AH53 -> 133924.14 | K19: =(AB53+AB7)*$AH$53 -> 91265.382 | L19: =(AB53*AG53+AB8)*AH53 -> 70243.126 | M19: =(AB53+AB8)*$AH$53 -> 70038.376 | N19: =(AB53*AG53+AB8)*AH53 -> 70243.126 | O19: =(AB53+AB9)*$AH$53 -> 54876.229 | P19: =(AB53*AG53+AB9)*AH53 -> 55080.979 | Q19: =(AB53+AB10)*$AH$53 -> 54876.229 | R19: =(AB53*AG53+AD10)*AH53 -> 28034.385 | S19: =(AB53+AB12)*$AH$53 -> 495787.5 | W19: 392 | X19: 486 | Z19: 300g | AA19: 1 | AB19: 1 | AC19: 1 | AD19: 1 | AF19: costo de clic | AG19: toner + gastos amortiz
B20: 501 a 1000 | C20: =(AB54+AB11)*$AH$54 -> 173178.02 | D20: =(AB54*AG54+AB11)*AH54 -> 173375.95 | E20: =(AB54+AB4)*$AH$54 -> 205477.14 | F20: =(AB54*AG54+AB4)*AH54 -> 205675.06 | G20: =(AC54+AB5)*$AH$54 -> 176163.66 | H20: =(AB54*AG54+AB5)*AH54 -> 176361.58 | I20: =(AB54+AB6)*$AH$54 -> 129262.08 | J20: =(AB54*AG54+AB6)*AH54 -> 129460.01 | K20: =(AB54+AB7)*$AH$54 -> 88223.203 | L20: =(AB54*AG54+AB8)*AH54 -> 67901.689 | M20: =(AB54+AB8)*$AH$54 -> 67703.764 | N20: =(AB54*AG54+AB8)*AH54 -> 67901.689 | O20: =(AB54+AB9)*$AH$54 -> 53047.022 | P20: =(AB54*AG54+AB9)*AH54 -> 53244.947 | Q20: =(AB54+AB10)*$AH$54 -> 53047.022 | R20: =(AB54*AG54+AD10)*AH54 -> 27099.905 | S20: =(AB54+AB12)*$AH$54 -> 479261.25 | W20: 363 | X20: 451 | Z20: 200g | AA20: 1 | AB20: 1 | AC20: 1 | AD20: 1
B21: 1000 | C21: =(AB55+AB11)*$AH$55 -> 167206.37 | D21: =(AB55*AG55+AB11)*AH55 -> 167397.47 | E21: =(AB55+AB4)*$AH$55 -> 198391.72 | F21: =(AB55*AG55+AB4)*AH55 -> 198582.82 | G21: =(AC55+AB5)*$AH$55 -> 170089.05 | H21: =(AB55*AG55+AB12)*AH55 -> 462926.1 | I21: =(AB55+AB6)*$AH$55 -> 124804.77 | J21: =(AB55*AG55+AB6)*AH55 -> 124995.87 | K21: =(AB55+AB7)*$AH$55 -> 85181.023 | L21: =(AB55*AG55+AB8)*AH55 -> 65560.251 | M21: =(AB55+AB8)*$AH$55 -> 65369.151 | N21: =(AB55*AG55+AB8)*AH55 -> 65560.251 | O21: =(AB55+AB9)*$AH$55 -> 51217.814 | P21: =(AB55*AG55+AB9)*AH55 -> 51408.914 | Q21: =(AB55+AB10)*$AH$55 -> 51217.814 | R21: =(AB55*AG55+AD10)*AH55 -> 26165.426 | S21: =(AB55+AB12)*$AH$55 -> 462735 | Z21: 150g | AA21: 1 | AB21: 1 | AC21: 1 | AD21: 1 | AG21: costo de bobina iman
B22: XL 32x70 | C22: Triplex | E22: 350g | G22: 300g | I22: 200g | K22: 150g | M22: 115g | O22: 90g | Q22: OBRA | S22: Sticker | W22: =W14-W4 -> 73 | X22: =X14-X4 -> 72 | Z22: 115g | AA22: 1 | AB22: 1 | AC22: 1 | AD22: 1 | AH22: 21 | AI22: IMAN A3+ | AJ22: 1.5
B23: 70x30 cm | C23: 4/0 | D23: 4/4 | E23: 4/0 | F23: 4/4 | G23: 4/0 | H23: 4/4 | I23: 4/0 | J23: 4/4 | K23: 4/0 | L23: 4/4 | M23: 4/0 | N23: 4/4 | O23: 4/0 | P23: 4/4 | Q23: 4/0 | R23: 4/4 | S23: 4/0 | W23: =W15-W5 -> 68 | X23: =X15-X5 -> 68 | Z23: 90g | AA23: 1 | AB23: 1 | AC23: 1 | AD23: 1 | AG23: 41 | AH23: ='PAPEL US$'!H48 -> 993.76 | AI23: =AH23/2000*50 -> 24.844 | AJ23: =AI23*AJ22 -> 37.266
B24: 1 | C24: =(AD48+AA11)*$AH$48 -> 340569.64 | D24: =(AD48*AG48+AA11)*AH48 -> 341088.34 | E24: =(AD48+AA4)*$AH$48 -> 404054.11 | F24: =(AD48*AG48+AA4)*AH48 -> 404572.81 | G24: =(AD48+AA5)*$AH$48 -> 346437.95 | H24: =(AD48*AG48+AA5)*AH48 -> 346956.65 | I24: =(AD48+AA6)*$AH$48 -> 254252.1 | J24: =(AD48*AG48+AA6)*AH48 -> 254770.8 | K24: =(AD48+AA7)*$AH$48 -> 173589.48 | L24: =(AD48*AG48+AA7)*AH48 -> 174108.18 | M24: =(AD48+AA8)*$AH$48 -> 133258.16 | N24: =(AD48*AG48+AA8)*AH48 -> 133776.86 | O24: =(AD48+AA9)*$AH$48 -> 104450.09 | P24: =(AD48*AG48+AA9)*AH48 -> 104968.79 | Q24: =(AD48+AA10)*$AH$48 -> 104450.09 | R24: =(AD48*AG48+AA10)*AH48 -> 104968.79 | S24: =(AD48+AA12)*$AH$48 -> 942181.5 | W24: =W16-W6 -> 64 | X24: =X16-X6 -> 64 | Z24: OBRA | AA24: 1 | AB24: 1 | AC24: 1 | AD24: 1
B25: 2 a 25 | C25: =(AD49+AA11)*$AH$49 -> 304720.2 | D25: =(AD49*AG49+AA11)*AH49 -> 305184.3 | E25: =(AD49+AA4)*$AH$49 -> 361522.1 | F25: =(AD49*AG49+AA4)*AH49 -> 361986.2 | G25: =(AD49+AA5)*$AH$49 -> 309970.8 | H25: =(AD49*AG49+AA5)*AH49 -> 310434.9 | I25: =(AD49+AA6)*$AH$49 -> 227488.72 | J25: =(AD49*AG49+AA6)*AH49 -> 227952.82 | K25: =(AD49+AA7)*$AH$49 -> 155316.9 | L25: =(AD49*AG49+AA7)*AH49 -> 155781 | M25: =(AD49+AA8)*$AH$49 -> 119230.99 | N25: =(AD49*AG49+AA8)*AH49 -> 119695.09 | O25: =(AD49+AA9)*$AH$49 -> 93455.34 | P25: =(AD49*AG49+AA9)*AH49 -> 93919.44 | Q25: =(AD49+AA10)*$AH$49 -> 93455.34 | R25: =(AD49*AG49+AA10)*AH49 -> 93919.44 | S25: =(AD49+AA12)*$AH$49 -> 843004.5 | W25: =W17-W7 -> 60 | X25: =X17-X7 -> 60 | Z25: Triplex | AA25: 1 | AB25: 1 | AC25: 1 | AD25: 1 | AH25: sobres
B26: 26 a 50 | C26: =(AD50+AA11)*$AH$50 -> 295757.84 | D26: =(AD50*AG50+AA11)*AH50 -> 296208.29 | E26: =(AD50+AA4)*$AH$50 -> 350889.1 | F26: =(AD50*AG50+AA4)*AH50 -> 351339.55 | G26: =(AD50+AA5)*$AH$50 -> 300854.01 | H26: =(AD50*AG50+AA5)*AH50 -> 301304.46 | I26: =(AD50+AA6)*$AH$50 -> 220797.87 | J26: =(AD50*AG50+AA6)*AH50 -> 221248.32 | K26: =(AD50+AA7)*$AH$50 -> 150748.76 | L26: =(AD50*AG50+AA7)*AH50 -> 151199.21 | M26: =(AD50+AA8)*$AH$50 -> 115724.2 | N26: =(AD50*AG50+AA8)*AH50 -> 116174.65 | O26: =(AD50+AA9)*$AH$50 -> 90706.653 | P26: =(AD50*AG50+AA9)*AH50 -> 91157.103 | Q26: =(AD50+AA10)*$AH$50 -> 90706.653 | R26: =(AD50*AG50+AA10)*AH50 -> 91157.103 | S26: =(AD50+AA12)*$AH$50 -> 818210.25 | W26: =W18-W8 -> 73 | X26: =X18-X8 -> 72 | Z26: Sticker | AA26: 1 | AB26: 1 | AC26: 1 | AD26: 1 | AH26: Sobre Bolsa A4 | AI26: Sobre bolsa | AJ26: Sobre bolsa | AK26: Oficio Ingles
B27: 51 a 100 | C27: =(AD51+AA11)*$AH$51 -> 286795.49 | D27: =(AD51*AG51+AA11)*AH51 -> 287232.29 | E27: =(AD51+AA4)*$AH$51 -> 340256.09 | F27: =(AD51*AG51+AA4)*AH51 -> 340692.89 | G27: =(AD51+AA5)*$AH$51 -> 291737.22 | H27: =(AD51*AG51+AA5)*AH51 -> 292174.02 | I27: =(AD51+AA6)*$AH$51 -> 214107.03 | J27: =(AD51*AG51+AA6)*AH51 -> 214543.83 | K27: =(AD51+AA7)*$AH$51 -> 146180.61 | L27: =(AD51*AG51+AA7)*AH51 -> 146617.41 | M27: =(AD51+AA8)*$AH$51 -> 112217.4 | N27: =(AD51*AG51+AA8)*AH51 -> 112654.2 | O27: =(AD51+AA9)*$AH$51 -> 87957.967 | P27: =(AD51*AG51+AA9)*AH51 -> 88394.767 | Q27: =(AD51+AA10)*$AH$51 -> 87957.967 | R27: =(AD51*AG51+AA10)*AH51 -> 88394.767 | S27: =(AD51+AA12)*$AH$51 -> 793416 | W27: =W19-W9 -> 53 | X27: =X19-X9 -> 53 | Z27: OPP | AA27: 1 | AB27: 1 | AC27: 1 | AD27: 1 | AH27: 22,9x32,4 | AI27: 27x37 | AJ27: 25x35,3 | AK27: 12x23,5
B28: 101 a 300 | C28: =(AD52+AA11)*$AH$52 -> 277833.13 | D28: =(AD52*AG52+AA11)*AH52 -> 278256.28 | E28: =(AD52+AA4)*$AH$52 -> 329623.09 | F28: =(AD52*AG52+AA4)*AH52 -> 330046.24 | G28: =(AD52+AA5)*$AH$52 -> 282620.43 | H28: =(AD52*AG52+AA5)*AH52 -> 283043.58 | I28: =(AD52+AA6)*$AH$52 -> 207416.19 | J28: =(AD52*AG52+AA6)*AH52 -> 207839.34 | K28: =(AD52+AA7)*$AH$52 -> 141612.47 | L28: =(AD52*AG52+AA7)*AH52 -> 142035.62 | M28: =(AD52+AA8)*$AH$52 -> 108710.61 | N28: =(AD52*AG52+AA8)*AH52 -> 109133.76 | O28: =(AD52+AA9)*$AH$52 -> 85209.28 | P28: =(AD52*AG52+AA9)*AH52 -> 85632.43 | Q28: =(AD52+AA10)*$AH$52 -> 85209.28 | R28: =(AD52*AG52+AA10)*AH52 -> 85632.43 | S28: =(AD52+AA12)*$AH$52 -> 768621.75 | W28: =W20-W10 -> 48 | X28: =X20-X10 -> 49 | Z28: Imán | AC28: 1 | AH28: 0.1242 | AI28: 0.1563 | AJ28: 0.14 | AK28: 0.0483011 | AO28: 2 | AP28: A4
B29: 301 a 500 | C29: =(AD53+AA11)*$AH$53 -> 268870.77 | D29: =(AD53*AG53+AA11)*AH53 -> 269280.27 | E29: =(AD53+AA4)*$AH$53 -> 318990.09 | F29: =(AD53*AG53+AA4)*AH53 -> 319399.59 | G29: =(AD53+AA5)*$AH$53 -> 273503.65 | H29: =(AD53*AG53+AA5)*AH53 -> 273913.15 | I29: =(AD53+AA6)*$AH$53 -> 200725.34 | J29: =(AD53*AG53+AA6)*AH53 -> 201134.84 | K29: =(AD53+AA7)*$AH$53 -> 137044.32 | L29: =(AD53*AG53+AA7)*AH53 -> 137453.82 | M29: =(AD53+AA8)*$AH$53 -> 105203.81 | N29: =(AD53*AG53+AA8)*AH53 -> 105613.31 | O29: =(AD53+AA9)*$AH$53 -> 82460.594 | P29: =(AD53*AG53+AA9)*AH53 -> 82870.094 | Q29: =(AD53+AA10)*$AH$53 -> 82460.594 | R29: =(AD53*AG53+AA10)*AH53 -> 82870.094 | S29: =(AD53+AA12)*$AH$53 -> 743827.5 | AH29: Sobre Bolsa A4 | AI29: Sobre bolsa | AJ29: Sobre bolsa | AK29: Oficio Ingles | AO29: Cantidad | AP29: 4--0 | AQ29: 1--0
B30: 501 a 1000 | C30: =(AD54+AA11)*$AH$54 -> 259908.41 | D30: =(AD54*AG54+AA11)*AH54 -> 260304.26 | E30: =(AD54+AA4)*$AH$54 -> 308357.08 | F30: =(AD54*AG54+AA4)*AH54 -> 308752.93 | G30: =(AD54+AA5)*$AH$54 -> 264386.86 | H30: =(AD54*AG54+AA5)*AH54 -> 264782.71 | I30: =(AD54+AA6)*$AH$54 -> 194034.5 | J30: =(AD54*AG54+AA6)*AH54 -> 194430.35 | K30: =(AD54+AA7)*$AH$54 -> 132476.18 | L30: =(AD54*AG54+AA7)*AH54 -> 132872.03 | M30: =(AD54+AA8)*$AH$54 -> 101697.02 | N30: =(AD54*AG54+AA8)*AH54 -> 102092.87 | O30: =(AD54+AA9)*$AH$54 -> 79711.907 | P30: =(AD54*AG54+AA9)*AH54 -> 80107.757 | Q30: =(AD54+AA10)*$AH$54 -> 79711.907 | R30: =(AD54*AG54+AA10)*AH54 -> 80107.757 | S30: =(AD54+AA12)*$AH$54 -> 719033.25 | Z30: costo de papel | AG30: Tamaño | AH30: 22,9x32,4 | AI30: 27x37 | AJ30: 25x35,3 | AK30: 12x23,5 | AO30: 100 | AP30: =(Q7*AO30)/AO28+$AR$30 -> 2463545.3 | AQ30: =(O48*AO30)/AO28+$AR$30 -> 2604244.4 | AR30: 200
B31: 1000 | C31: =(AD55+AA11)*$AH$55 -> 250946.05 | D31: =(AD55*AG55+AA11)*AH55 -> 251328.25 | E31: =(AD55+AA4)*$AH$55 -> 297724.08 | F31: =(AD55*AG55+AA4)*AH55 -> 298106.28 | G31: =(AD55+AA5)*$AH$55 -> 255270.07 | H31: =(AD55*AG55+AA5)*AH55 -> 255652.27 | I31: =(AD55+AA6)*$AH$55 -> 187343.65 | J31: =(AD55*AG55+AA6)*AH55 -> 187725.85 | K31: =(AD55+AA7)*$AH$55 -> 127908.03 | L31: =(AD55*AG55+AA7)*AH55 -> 128290.23 | M31: =(AD55+AA8)*$AH$55 -> 98190.227 | N31: =(AD55*AG55+AA8)*AH55 -> 98572.427 | O31: =(AD55+AA9)*$AH$55 -> 76963.221 | P31: =(AD55*AG55+AA9)*AH55 -> 77345.421 | Q31: =(AD55+AA10)*$AH$54 -> 79711.907 | R31: =(AD55*AG55+AA10)*AH55 -> 77345.421 | S31: =(AD55+AA12)*$AH$55 -> 694239 | AA31: XL | AB31: 33X48 | AC31: 32X47 | AD31: A4 | AG31: Cantidad | AH31: 4/0 | AI31: 4/0 | AJ31: 4/0 | AK31: 4/0 | AO31: 200 | AP31: =(Q8*AO31)/AO28+$AR$31 -> 4772981.5 | AQ31: =(O49*AO31)/AO28+$AR$31 -> 5055159.7 | AR31: 250
B32: Bajada A4 | C32: Triplex | E32: 350g | G32: 300g | I32: 200g | K32: 150g | M32: 115g | O32: 90g | Q32: OBRA | S32: Sticker | Z32: 350g | AA32: 18 | AB32: 12.43 | AC32: 10.48 | AD32: 7.86 | AG32: 100 | AH32: =(AH28*AL32*AM38)+$AM$42 -> 356.46 | AI32: =(AI28*AL32*AM38)+$AM$42 -> 398.19 | AJ32: =(AJ28*AL32*AM38)+$AM$42 -> 377 | AK32: =(AK28*AL32*AM38)+$AM$42 -> 257.79143 | AL32: 2 | AO32: 300 | AP32: =(Q9*AO32)/AO28+$AR$32 -> 6928458.7 | AQ32: =(O50*AO32)/AO28+$AR$32 -> 7352895.9 | AR32: 300
B33: 22x31 cm | C33: 4/0 | D33: 4/4 | E33: 4/0 | F33: 4/4 | G33: 4/0 | H33: 4/4 | I33: 4/0 | J33: 4/4 | K33: 4/0 | L33: 4/4 | M33: 4/0 | N33: 4/4 | O33: 4/0 | P33: 4/4 | Q33: 4/0 | R33: 4/4 | S33: 4/0 | Z33: 300g | AA33: 15 | AB33: 10.28 | AC33: 8.65 | AD33: 6.49 | AG33: 200 | AH33: =(AH28*AL33*AM38)+$AM$42 -> 340.314 | AI33: =(AI28*AL33*AM38)+$AM$42 -> 377.871 | AJ33: =(AJ28*AL33*AM38)+$AM$42 -> 358.8 | AK33: =(AK28*AL33*AM38)+$AM$42 -> 251.51229 | AL33: 1.8 | AO33: 500 | AP33: =(Q10*AO33)/AO28+$AR$33 -> 11162383 | AQ33: =(O51*AO33)/AO28+$AR$33 -> 11871729 | AR33: 350
B34: 1 | C34: =(AE48+AD11)*$AH$48 -> 136126.46 | D34: =(AE48*AG48+AD11)*AH48 -> 136262.96 | E34: =(AE48+AD4)*$AH$48 -> 135840.89 | F34: =(AE48*AG48+AD4)*AH48 -> 135977.39 | G34: =(AE48+AD5)*$AH$48 -> 116462.9 | H34: =(AE48*AG48+AD5)*AH48 -> 116599.4 | I34: =(AE48+AD6)*$AH$48 -> 85458.128 | J34: =(AE48*AG48+AD6)*AH48 -> 85594.628 | K34: =(AE48+AD7)*$AH$48 -> 58328.951 | L34: =(AE48*AG48+AD7)*AH48 -> 58465.451 | M34: =(AE48+AD8)*$AH$48 -> 44764.362 | N34: =(AE48*AG48+AD8)*AH48 -> 44900.862 | O34: =(AE48+AD9)*$AH$48 -> 35075.371 | P34: =(AE48*AG48+AD9)*AH48 -> 35211.871 | Q34: =(AE48+AD10)*$AH$48 -> 35075.371 | R34: =(AE48*AG48+AD10)*AH48 -> 35211.871 | S34: =(AE48+AD12)*$AH$48 -> 314008.5 | Z34: 200g | AA34: 9 | AB34: 6.59 | AC34: 5.55 | AD34: 4.16 | AG34: 300 | AH34: =(AH28*AL34*AM38)+$AM$42 -> 324.168 | AI34: =(AI28*AL34*AM38)+$AM$42 -> 357.552 | AJ34: =(AJ28*AL34*AM38)+$AM$42 -> 340.6 | AK34: =(AK28*AL34*AM38)+$AM$42 -> 245.23314 | AL34: 1.6 | AO34: 1000 | AP34: =(Q11*AO34)/AO28+$AR$31 -> 21554521 | AQ34: =(O52*AO34)/AO28+$AR$34 -> 22977262 | AR34: 400
B35: 2 a 25 | C35: =(AE49+AD11)*$AH$49 -> 121797.36 | D35: =(AE49*AG49+AD11)*AH49 -> 121919.49 | E35: =(AE49+AD4)*$AH$49 -> 121541.84 | F35: =(AE49*AG49+AD4)*AH49 -> 121663.98 | G35: =(AE49+AD5)*$AH$49 -> 104203.65 | H35: =(AE49*AG49+AD5)*AH49 -> 104325.78 | I35: =(AE49+AD6)*$AH$49 -> 76462.536 | J35: =(AE49*AG49+AD6)*AH49 -> 76584.667 | K35: =(AE49+AD7)*$AH$49 -> 52189.061 | L35: =(AE49*AG49+AD7)*AH49 -> 52311.193 | M35: =(AE49+AD8)*$AH$49 -> 40052.324 | N35: =(AE49*AG49+AD8)*AH49 -> 40174.456 | O35: =(AE49+AD9)*$AH$49 -> 31383.226 | P35: =(AE49*AG49+AD9)*AH49 -> 31505.358 | Q35: =(AE49+AD10)*$AH$49 -> 31383.226 | R35: =(AE49*AG49+AD10)*AH49 -> 31505.358 | S35: =(AE49+AD12)*$AH$49 -> 280954.97 | V35: 50 | W35: =Q7*V35/2 -> 1231672.6 | Z35: 150g | AA35: 7 | AB35: 4.82 | AC35: 4.15 | AD35: 3.11 | AG35: 500 | AH35: =(AH28*AL35*AM38)+$AM$42 -> 308.022 | AI35: =(AI28*AL35*AM38)+$AM$42 -> 337.233 | AJ35: =(AJ28*AL35*AN38)+$AM$42 -> 322.4 | AK35: =(AK28*AL35*AM38)+$AM$42 -> 238.954 | AL35: 1.4
B36: 26 a 50 | C36: =(AE50+AD11)*$AH$50 -> 118215.08 | D36: =(AE50*AG50+AD11)*AH50 -> 118333.62 | E36: =(AE50+AD4)*$AH$50 -> 117967.08 | F36: =(AE50*AG50+AD4)*AH50 -> 118085.62 | G36: =(AE50+AD5)*$AH$50 -> 101138.84 | H36: =(AE50*AG50+AD5)*AH50 -> 101257.38 | I36: =(AE50+AD6)*$AH$50 -> 74213.637 | J36: =(AE50*AG50+AD6)*AH50 -> 74332.177 | K36: =(AE50+AD7)*$AH$50 -> 50654.089 | L36: =(AE50*AG50+AD9)*AH50 -> 30578.73 | M36: =(AE50+AD8)*$AH$50 -> 38874.315 | N36: =(AE50*AG50+AD8)*AH50 -> 38992.854 | O36: =(AE50+AD9)*$AH$50 -> 30460.19 | P36: =(AE50*AG50+AD9)*AH50 -> 30578.73 | Q36: =(AE50+AD10)*$AH$50 -> 30460.19 | R36: =(AE50*AG50+AD10)*AH50 -> 30578.73 | S36: =(AE50+AD12)*$AH$50 -> 272691.59 | V36: 100 | W36: =Q8*V36/2 -> 2386365.8 | Z36: 90g | AA36: 4.67 | AB36: 3 | AC36: 2.67 | AD36: 2 | AG36: 1000 | AH36: =(AH28*AL36*AM38)+$AM$42 -> 291.876 | AI36: =(AI28*AL36*AM38)+$AM$42 -> 316.914 | AJ36: =(AJ28*AL36*AM38)+$AM$42 -> 304.2 | AK36: =(AK28*AL36*AM38)+$AM$42 -> 232.67486 | AL36: 1.2
B37: 51 a 100 | C37: =(AE51+AD11)*$AH$51 -> 114632.8 | D37: =(AE51*AG51+AD11)*AH51 -> 114747.75 | E37: =(AE51+AD4)*$AH$51 -> 114392.32 | F37: =(AE51*AG51+AD4)*AH51 -> 114507.27 | G37: =(AE51+AD5)*$AH$51 -> 98074.023 | H37: =(AE51*AG51+AD5)*AH51 -> 98188.97 | I37: =(AE51+AD6)*$AH$51 -> 71964.739 | J37: =(AE51*AG51+AD6)*AH51 -> 72079.687 | K37: =(AE51+AD7)*$AH$51 -> 49119.117 | L37: =(AE51*AG51+AD7)*AH51 -> 49234.064 | M37: =(AE51+AD8)*$AH$51 -> 37696.305 | N37: =(AE51*AG51+AD8)*AH51 -> 37811.252 | O37: =(AE51+AD9)*$AH$51 -> 29537.154 | P37: =(AE51*AG51+AD9)*AH51 -> 29652.101 | Q37: =(AE51+AD10)*$AH$51 -> 29537.154 | R37: =(AE51*AG51+AD10)*AH51 -> 29652.101 | S37: =(AE51+AD12)*$AH$51 -> 264428.21 | V37: 150 | W37: =Q9*V37/2 -> 3464079.3 | Z37: OBRA | AA37: 4.22 | AB37: 2.87 | AC37: 2.41 | AD37: 1.81 | AM37: oficial | AN37: blue | AQ37: clic | AR37: =AM42 -> 195 | AS37: 1.5 | AT37: 5 COLOR | AV37: ESPECIAL
B38: 101 a 300 | C38: =(AE52+AD12)*$AH$51 -> 264428.21 | D38: =(AE52*AG52+AD11)*AH52 -> 111161.88 | E38: =(AE52+AD4)*$AH$52 -> 110817.56 | F38: =(AE52*AG52+AD4)*AH52 -> 110928.92 | G38: =(AE52+AD5)*$AH$52 -> 95009.209 | H38: =(AE52*AG52+AD5)*AH52 -> 95120.565 | I38: =(AE52+AD6)*$AH$52 -> 69715.841 | J38: =(AE52*AG52+AD6)*AH52 -> 69827.196 | K38: =(AE52+AD7)*$AH$52 -> 47584.144 | L38: =(AE52*AG52+AD7)*AH52 -> 47695.499 | M38: =(AE52+AD8)*$AH$52 -> 36518.296 | N38: =(AE52*AG52+AD8)*AH52 -> 36629.651 | O38: =(AE52+AD8)*$AH$52 -> 36518.296 | P38: =(AE52*AG52+AD9)*AH52 -> 28725.473 | Q38: =(AE52+AD10)*$AH$52 -> 28614.118 | R38: =(AE52*AG52+AD10)*AH52 -> 28725.473 | S38: =(AE52+AD12)*$AH$52 -> 256164.83 | V38: 250 | W38: =Q10*V38/2 -> 5581016.7 | Z38: Triplex | AA38: 19.77 | AB38: 11.3 | AC38: 11.3 | AD38: 8.47 | AL38: Dólar | AM38: 650 | AN38: 650 | AR38: =AM42 -> 195 | AS38: 1.9 | AT38: =AR38*AS38 -> 370.5 | AV38: =U4 -> 1341.8275
B39: 301 a 500 | C39: =(AE53+AD11)*$AH$53 -> 107468.25 | D39: =(AE53*AG53+AD11)*AH53 -> 107576.02 | E39: =(AE53+AD4)*$AH$53 -> 107242.8 | F39: =(AE53*AG53+AD4)*AH53 -> 107350.57 | G39: =(AE53+AD5)*$AH$53 -> 91944.396 | H39: =(AE53*AG53+AD5)*AH53 -> 92052.159 | I39: =(AE53+AD6)*$AH$53 -> 67466.943 | J39: =(AE53*AG53+AD6)*AH53 -> 67574.706 | K39: =(AE53+AD7)*$AH$53 -> 46049.172 | L39: =(AE53*AG53+AD7)*AH53 -> 46156.935 | M39: =(AE53+AD8)*$AH$53 -> 35340.286 | N39: =(AE53*AG53+AD8)*AH53 -> 35448.049 | O39: =(AE53+AD9)*$AH$53 -> 27691.082 | P39: =(AE53*AG53+AD9)*AH53 -> 27798.845 | Q39: =(AE53+AD10)*$AH$53 -> 27691.082 | R39: =(AE53*AG53+AD10)*AH53 -> 27798.845 | S39: =(AE53+AD12)*$AH$53 -> 247901.45 | V39: 500 | W39: =Q11*V39/2 -> 10777136 | Z39: Sticker | AA39: 23.5 | AB39: 16.26 | AC39: 13.5 | AD39: 10 | AR39: =AM42 -> 195 | AS39: 1.8 | AT39: =AR39*AS39 -> 351 | AV39: =U5 -> 1200.5825
B40: 501 a 1000 | C40: =(AE54+AD11)*$AH$54 -> 103885.98 | D40: =(AE54*AG54+AD11)*AH54 -> 103990.15 | E40: =(AE54+AD4)*$AH$54 -> 103668.04 | F40: =(AE54*AG54+AD4)*AH54 -> 103772.22 | G40: =(AE54+AD5)*$AH$54 -> 88879.583 | H40: =(AE54*AG54+AD5)*AH54 -> 88983.754 | I40: =(AE54+AD6)*$AH$54 -> 65218.045 | J40: =(AE54*AG54+AD6)*AH54 -> 65322.216 | K40: =(AE54+AD7)*$AH$54 -> 44514.199 | L40: =(AE54*AG54+AD7)*AH54 -> 44618.37 | M40: =(AE54+AD8)*$AH$54 -> 34162.277 | N40: =(AE54*AG54+AD8)*AH54 -> 34266.448 | O40: =(AE54+AD9)*$AH$54 -> 26768.046 | P40: =(AE54*AG54+AD9)*AH54 -> 26872.217 | Q40: =(AE54+AD10)*$AH$54 -> 26768.046 | R40: =(AE54*AG54+AD10)*AH54 -> 26872.217 | S40: =(AE54+AD12)*$AH$54 -> 239638.07 | Z40: OPP | AA40: 0 | AB40: 32.7 | AC40: 32.7 | AD40: 24.5 | AK40: 0.356 | AL40: Coeficiente XL | AM40: =AM42*AN40 -> 390 | AN40: 2 | AR40: =AM42 -> 195 | AS40: 1.7 | AT40: =AR40*AS40 -> 331.5 | AV40: =U6 -> 1165.2713
B41: 1000 | C41: =(AE55+AD11)*$AH$55 -> 100303.7 | D41: =(AE55*AG55+AD11)*AH55 -> 100404.28 | E41: =(AE55+AD4)*$AH$55 -> 100093.28 | F41: =(AE55*AG55+AD4)*AH55 -> 100193.86 | G41: =(AE55+AD5)*$AH$55 -> 85814.77 | H41: =(AE55*AG55+AD5)*AH55 -> 85915.349 | I41: =(AE55+AD6)*$AH$55 -> 62969.147 | J41: =(AE55*AG55+AD6)*AH55 -> 63069.726 | K41: =(AE55+AD7)*$AH$55 -> 42979.227 | L41: =(AE55*AG55+AD7)*AH55 -> 43079.806 | M41: =(AE55+AD8)*$AH$55 -> 32984.267 | N41: =(AE55*AG55+AD8)*AH55 -> 33084.846 | O41: =(AE55+AD9)*$AH$55 -> 25845.01 | P41: =(AE55*AG55+AD9)*AH55 -> 25945.589 | Q41: =(AE55+AD10)*$AH$55 -> 25845.01 | R41: =(AE55*AG55+AD10)*AH55 -> 25945.589 | S41: =(AE55+AD12)*$AH$55 -> 231374.68 | Z41: Imán | AA41: 0 | AB41: 0 | AC41: 47 | AD41: 30 | AK41: =AK42/1.9 -> 0.15789474 | AL41: Coeficiente A4 | AM41: =AK41*AN38 -> 102.63158 | AR41: =AM42 -> 195 | AS41: 1.6 | AT41: =AR41*AS41 -> 312 | AV41: =U7 -> 1129.96
AK42: 0.3 | AL42: costo clic color A3 | AM42: =AK42*AN38 -> 195 | AR42: =AM43 -> 195 | AS42: 1.5 | AT42: =AR42*AS42 -> 292.5 | AV42: =U8 -> 1094.6488
AD43: 0.147000 | AK43: 0.3 | AL43: costo clic XA3 | AM43: =AK43*$AN$38 -> 195 | AR43: =AM43 -> 195 | AS43: 1.4 | AT43: =AR43*AS43 -> 273 | AV43: =U9 -> 1059.3375
A44: BLANCO Y NEGRO | AR44: =AM42 -> 195 | AS44: 1.3 | AT44: =AR44*AS44 -> 253.5 | AV44: =U10 -> 1024.0262
B45: A3 PLUS | C45: Triplex | E45: 350g | G45: 300g | I45: 200g | K45: 150g | M45: 115g | O45: 90g | Q45: 80 grs, | S45: Sticker | AK45: 0.06 | AL45: costo clic ByN | AM45: =AK45*AM38 -> 39 | AN45: 2
B46: 32x47 cm | C46: 1/0 | D46: 1/1 | E46: 1/0 | F46: 1/1 | G46: 1/0 | H46: 1/1 | I46: 1/0 | J46: 1/1 | K46: 1/0 | L46: 1/1 | M46: 1/0 | N46: 1/1 | O46: 1/0 | P46: 1/1 | Q46: 1/0 | R46: 1/1 | S46: 1/0 | V46: 50 | W46: =Q48*V46/2 -> 1302022.2 | AC46: precio x clic
B47: 1 | C47: =(AA48+AC11)*$AH$48 -> 226626.53 | D47: =(AA48*AG48+AC11)*$AH$48 -> 226678.4 | E47: =(AA48+AC4)*$AH$48 -> 226150.58 | F47: =(AA48*AG48+AC4)*AH$48 -> 226202.45 | G47: =(AA48+AC5)*$AH$48 -> 193853.94 | H47: =(AA48*AG48+AC5)*AH$48 -> 193905.81 | I47: =(AA48+AC6)*$AH$48 -> 142179.31 | J47: =(AA48*AG48+AC6)*AH$48 -> 142231.18 | K47: =(AA48+AC7)*$AH$48 -> 96964.018 | L47: =(AA48*AG48+AC7)*AH$48 -> 97015.888 | M47: =(AA48+AC8)*$AH$48 -> 74356.371 | N47: =(AA48*AG48+AC8)*AH$48 -> 74408.241 | O47: =(AA48+AC9)*$AH$48 -> 58208.051 | P47: =(AA48*AG48+AC9)*$AH48 -> 58259.921 | Q47: =(AA48+AC10)*AH$48 -> 58208.051 | R47: =(AA48*AG48+AC10)*AH$48 -> 58259.921 | S47: =(AA48+AC12)*$AH$48 -> 523096.6 | V47: 100 | W47: =Q49*V47/2 -> 2527454.8 | Z47: Rango Pack color | AB47: A3 | AC47: A3 | AD47: XL | AE47: A4 | AF47: Coef 4/0 | AG47: coef 4/4 | AH47: x pliegos | AI47: coef 4/4
B48: 2 a 50 | C48: =(AA49+AC11)*$AH$49 -> 202771.1 | D48: =(AA49*AG49+AC11)*$AH$49 -> 202817.51 | E48: =(AA49+AC4)*$AH$49 -> 202345.25 | F48: =(AA49*AG49+AC4)*AH$49 -> 202391.66 | G48: =(AA49+AC5)*$AH$49 -> 173448.26 | H48: =(AA49*AG49+AC5)*AH$49 -> 173494.67 | I48: =(AA49+AC6)*$AH$49 -> 127213.07 | J48: =(AA49*AG49+AC6)*AH$49 -> 127259.48 | K48: =(AA49+AC7)*$AH$49 -> 86757.279 | L48: =(AA49*AG49+AC7)*AH$49 -> 86803.689 | M48: =(AA49+AC8)*$AH$49 -> 66529.384 | N48: =(AA49*AG49+AC8)*AH$49 -> 66575.794 | O48: =(AA49+AC9)*$AH$49 -> 52080.888 | P48: =(AA49*AG49+AC9)*$AH49 -> 52127.298 | Q48: =(AA49+AC9)*AH$49 -> 52080.888 | R48: =(AA49*AG49+AC10)*AH$49 -> 52127.298 | S48: =(AA49+AC12)*$AH$49 -> 468033.8 | V48: 150 | W48: =Q50*V48/2 -> 3676298 | Z48: 1 | AA48: =AM45 -> 39 | AB48: =AM43*$AF$48 -> 195 | AC48: =AF48*$AM$42 -> 195 | AD48: =AF48*$AM$40 -> 390 | AE48: =AF48*$AM$41 -> 102.63158 | AF48: 1 | AG48: 1.7 | AH48: 1.9 | AI48: =(AF48+AG48)-1 -> 1.7 | AL48: Rango color | AM48: 4/0 | AO48: 4/4
B49: 51 a 100 | C49: =(AA50+AC11)*$AH$50 -> 196807.25 | D49: =(AA50*AG50+AC11)*$AH$50 -> 196852.29 | E49: =(AA50+AC4)*$AH$50 -> 196393.92 | F49: =(AA50*AG50+AC4)*AH$50 -> 196438.97 | G49: =(AA50+AC5)*$AH$50 -> 168346.84 | H49: =(AA50*AG50+AC5)*AH$50 -> 168391.88 | I49: =(AA50+AC6)*$AH$50 -> 123471.51 | J49: =(AA50*AG50+AC6)*AH$50 -> 123516.55 | K49: =(AA50+AC7)*$AH$50 -> 84205.595 | L49: =(AA50*AG50+AC7)*AH$50 -> 84250.64 | M49: =(AA50+AC8)*$AH$50 -> 64572.638 | N49: =(AA50*AG50+AC8)*AH$50 -> 64617.683 | O49: =(AA50+AC9)*$AH$50 -> 50549.097 | P49: =(AA50*AG50+AC9)*$AH50 -> 50594.142 | Q49: =(AA50+AC10)*AH$50 -> 50549.097 | R49: =(AA50*AG50+AC10)*AH$50 -> 50594.142 | S49: =(AA50+AC12)*$AH$50 -> 454268.1 | V49: 250 | W49: =Q51*V49/2 -> 5935689.4 | Z49: 2 a 25 | AA49: =$AM$45 -> 39 | AB49: =AM43*$AF$49 -> 195 | AC49: =AF49*$AM$42 -> 195 | AD49: =AF49*$AM$40 -> 390 | AE49: =AF49*$AM$41 -> 102.63158 | AF49: 1 | AG49: 1.7 | AH49: 1.7 | AI49: =(AF49+AG49)-1 -> 1.7 | AL49: 1 | AM49: 1.6 | AO49: =AF48+AG48 -> 2.7
B50: 101 a 500 | C50: =(AA51+AC11)*$AH$51 -> 190843.39 | D50: =(AA51*AG51+AC11)*$AH$51 -> 190887.07 | E50: =(AA51+AC4)*$AH$51 -> 190442.59 | F50: =(AA51*AG51+AC4)*AH$51 -> 190486.27 | G50: =(AA51+AC5)*$AH$51 -> 163245.42 | H50: =(AA51*AG51+AC5)*AH$51 -> 163289.1 | I50: =(AA51+AC6)*$AH$51 -> 119729.95 | J50: =(AA51*AG51+AC6)*AH$51 -> 119773.63 | K50: =(AA51+AC7)*$AH$51 -> 81653.91 | L50: =(AA51*AG51+AC7)*AH$51 -> 81697.59 | M50: =(AA51+AC8)*$AH$51 -> 62615.891 | N50: =(AA51*AG51+AC8)*AH$51 -> 62659.571 | O50: =(AA51+AC9)*$AH$51 -> 49017.306 | P50: =(AA51*AG51+AC9)*$AH51 -> 49060.986 | Q50: =(AA51+AC10)*AH$51 -> 49017.306 | R50: =(AA51*AG51+AC10)*AH$51 -> 49060.986 | S50: =(AA51+AC12)*$AH$51 -> 440502.4 | V50: 500 | W50: =Q52*V50/2 -> 11488431 | Z50: 26 a 50 | AA50: =$AM$45 -> 39 | AB50: =AM43*AF$50 -> 195 | AC50: =AF50*$AM$42 -> 195 | AD50: =AF50*$AM$40 -> 390 | AE50: =AF50*$AM$41 -> 102.63158 | AF50: 1 | AG50: 1.7 | AH50: 1.65 | AI50: =(AF50+AG50)-1 -> 1.7 | AL50: 2 a 25 | AM50: 1 | AN50: =AM50/$AM$49 -> 0.625 | AO50: =AF49+AG49 -> 2.7 | AP50: =AO50/$AO$49 -> 1
B51: 501 a 1000 | C51: =(AA52+AC11)*$AH$52 -> 184879.53 | D51: =(AA52*AG52+AC11)*$AH$52 -> 184921.85 | E51: =(AA52+AC4)*$AH$52 -> 184491.26 | F51: =(AA52*AG52+AC4)*AH$52 -> 184533.57 | G51: =(AA52+AC5)*$AH$52 -> 158144 | H51: =(AA52*AG52+AC5)*AH$52 -> 158186.32 | I51: =(AA52+AC6)*$AH$52 -> 115988.39 | J51: =(AA52*AG52+AC6)*AH$52 -> 116030.7 | K51: =(AA52+AC7)*$AH$52 -> 79102.225 | L51: =(AA52*AG52+AC7)*AH$52 -> 79144.54 | M51: =(AA52+AC8)*$AH$52 -> 60659.144 | N51: =(AA52*AG52+AC8)*AH$52 -> 60701.459 | O51: =(AA52+AC9)*$AH$52 -> 47485.515 | P51: =(AA52*AG52+AC9)*$AH52 -> 47527.83 | Q51: =(AA52+AC10)*AH$52 -> 47485.515 | R51: =(AA52*AG52+AC10)*AH$52 -> 47527.83 | S51: =(AA52+AC12)*$AH$52 -> 426736.7 | Z51: 51 a 100 | AA51: =$AM$45 -> 39 | AB51: =AM43*$AF$51 -> 195 | AC51: =AF51*$AM$42 -> 195 | AD51: =AF51*$AM$40 -> 390 | AE51: =AF51*$AM$41 -> 102.63158 | AF51: 1 | AG51: 1.7 | AH51: 1.6 | AI51: =(AF51+AG51)-1 -> 1.7 | AL51: 26 a 50 | AM51: 0.7 | AN51: =AM51/$AM$49 -> 0.4375 | AO51: =AF50+AG50 -> 2.7 | AP51: =AO51/$AO$49 -> 1
B52: 1001 a 5000 | C52: =(AA53+AC11)*$AH$53 -> 178915.68 | D52: =(AA53*AG53+AC11)*$AH$53 -> 178956.63 | E52: =(AA53+AC4)*$AH$53 -> 178539.93 | F52: =(AA53*AG53+AC4)*AH$53 -> 178580.88 | G52: =(AA53+AC5)*$AH$53 -> 153042.58 | H52: =(AA53*AG53+AC5)*AH$53 -> 153083.53 | I52: =(AA53+AC6)*$AH$53 -> 112246.83 | J52: =(AA53*AG53+AC6)*AH$53 -> 112287.78 | K52: =(AA53+AC7)*$AH$53 -> 76550.541 | L52: =(AA53*AG53+AC7)*AH$53 -> 76591.491 | M52: =(AA53+AC8)*$AH$53 -> 58702.398 | N52: =(AA53*AG53+AC8)*AH$53 -> 58743.348 | O52: =(AA53+AC9)*$AH$53 -> 45953.724 | P52: =(AA53*AG53+AC9)*$AH53 -> 45994.674 | Q52: =(AA53+AC10)*AH$53 -> 45953.724 | R52: =(AA53*AG53+AC10)*AH$53 -> 45994.674 | S52: =(AA53+AC12)*$AH$53 -> 412971 | Z52: 101 a 300 | AA52: =$AM$45 -> 39 | AB52: =AM43*$AF$52 -> 195 | AC52: =AF52*$AM$42 -> 195 | AD52: =AF52*$AM$40 -> 390 | AE52: =AF52*$AM$41 -> 102.63158 | AF52: 1 | AG52: 1.7 | AH52: 1.55 | AI52: =(AF52+AG52)-1 -> 1.7 | AL52: 51 a 100 | AM52: 0.65 | AN52: =AM52/$AM$49 -> 0.40625 | AO52: =AF51+AG51 -> 2.7 | AP52: =AO52/$AO$49 -> 1
Z53: 301 a 500 | AA53: =$AM$45 -> 39 | AB53: =AM43*$AF$53 -> 195 | AC53: =AF53*$AM$42 -> 195 | AD53: =AF53*$AM$40 -> 390 | AE53: =AF53*$AM$41 -> 102.63158 | AF53: 1 | AG53: 1.7 | AH53: 1.5 | AI53: =(AF53+AG53)-1 -> 1.7 | AL53: 101 a 300 | AM53: 0.6 | AN53: =AM53/$AM$49 -> 0.375 | AO53: =AF52+AG52 -> 2.7 | AP53: =AO53/$AO$49 -> 1
B54: XA3 | C54: Triplex | E54: 350g | G54: 300g | I54: 200g | K54: 150g | M54: 115g | O54: 90g | Q54: OBRA | S54: Sticker | Z54: 501 a 1000 | AA54: =$AM$45 -> 39 | AB54: =AM43*$AF$54 -> 195 | AC54: =AF54*$AM$42 -> 195 | AD54: =AF54*$AM$40 -> 390 | AE54: =AF54*$AM$41 -> 102.63158 | AF54: 1 | AG54: 1.7 | AH54: 1.45 | AI54: =(AF54+AG54)-1 -> 1.7 | AL54: 301 a 500 | AM54: 0.55 | AN54: =AM54/$AM$49 -> 0.34375 | AO54: =AF53+AG53 -> 2.7 | AP54: =AO54/$AO$49 -> 1
B55: 33x48 cm | C55: 1/0 | D55: 1/1 | E55: 1/0 | F55: 1/1 | G55: 1/0 | H55: 1/1 | I55: 1/0 | J55: 1/1 | K55: 1/0 | L55: 1/1 | M55: 1/0 | N55: 1/1 | O55: 1/0 | P55: 1/1 | Q55: 1/0 | R55: 1/1 | S55: 1/0 | Z55: 1000 | AA55: =$AM$45 -> 39 | AB55: =AM43*$AF$55 -> 195 | AC55: =AF55*$AM$42 -> 195 | AD55: =AF55*$AM$40 -> 390 | AE55: =AF55*$AM$41 -> 102.63158 | AF55: 1 | AG55: 1.7 | AH55: 1.4 | AI55: 1.7 | AL55: 501 a 1000 | AM55: 0.5 | AN55: =AM55/$AM$49 -> 0.3125 | AO55: =AF54+AG54 -> 2.7 | AP55: =AO55/$AO$49 -> 1
B56: 1 | C56: =(AA48+AB11)*$AH$48 -> 226626.53 | D56: =(AA48*AG48+AB11)*$AH$48 -> 226678.4 | E56: =(AA48+AB4)*$AH$48 -> 268949.51 | F56: =(AA48*AG48+AB4)*AH$48 -> 269001.38 | G56: =(AA48+AB5)*$AH$48 -> 230538.73 | H56: =(AA48*AG48+AB5)*AH$48 -> 230590.6 | I56: =(AA48+AB6)*$AH$48 -> 169081.5 | J56: =(AA48*AG48+AB6)*AH$48 -> 169133.37 | K56: =(AA48+AB7)*$AH$48 -> 115306.42 | L56: =(AA48*AG48+AB7)*AH$48 -> 115358.29 | M56: =(AA48+AB8)*$AH$48 -> 88418.877 | N56: =(AA48*AG48+AB8)*$AH48 -> 88470.747 | O56: =(AA48+AB9)*AH$48 -> 69213.49 | P56: =(AA48*AG48+AB9)*AH48 -> 69265.36 | Q56: =(AA48+AB10)*$AH$48 -> 69213.49 | R56: =(AA48*AG48+AB10)*$AH48 -> 69265.36 | S56: =(AA48+AB12)*$AH$48 -> 627701.1
B57: 2 a 50 | C57: =(AA49+AB11)*$AH$49 -> 202771.1 | D57: =(AA49*AG49+AB11)*$AH$49 -> 202817.51 | E57: =(AA49+AB4)*$AH$49 -> 240639.03 | F57: =(AA49*AG49+AB4)*AH$49 -> 240685.44 | G57: =(AA49+AB5)*$AH$49 -> 206271.5 | H57: =(AA49*AG49+AB5)*AH$49 -> 206317.91 | I57: =(AA49+AB6)*$AH$49 -> 151283.45 | J57: =(AA49*AG49+AB7)*AH$49 -> 103215.31 | K57: =(AA49+AB7)*$AH$49 -> 103168.9 | L57: =(AA49*AG49+AB7)*AH$49 -> 103215.31 | M57: =(AA49+AB8)*$AH$49 -> 79111.626 | N57: =(AA49*AG49+AB8)*$AH49 -> 79158.036 | O57: =(AA49+AB9)*AH$49 -> 61927.86 | P57: =(AA49*AG49+AB9)*AH49 -> 61974.27 | Q57: =(AA49+AB10)*$AH$49 -> 61927.86 | R57: =(AA49*AG49+AB10)*$AH49 -> 61974.27 | S57: =(AA49+AB12)*$AH$49 -> 561627.3 | AB57: Rango Pack ByN | AC57: A3 | AD57: XL | AE57: A4 | AF57: Coef 1/0 | AG57: coef 1/1
B58: 51 a 100 | C58: =(AA50+AB11)*$AH$50 -> 196807.25 | D58: =(AA50*AG50+AB11)*$AH$50 -> 196852.29 | E58: =(AA50+AB5)*$AH$50 -> 200204.69 | F58: =(AA50*AG50+AB4)*AH$50 -> 233606.46 | G58: =(AA50+AB5)*$AH$50 -> 200204.69 | H58: =(AA50*AG50+AB5)*AH$50 -> 200249.74 | I58: =(AA50+AB6)*$AH$50 -> 146833.93 | J58: =(AA50*AG50+AB6)*AH$50 -> 146878.98 | K58: =(AA50+AB7)*$AH$50 -> 100134.52 | L58: =(AA50*AG50+AB7)*AH$50 -> 100179.57 | M58: =(AA50+AB8)*$AH$50 -> 76784.814 | N58: =(AA50*AG50+AB8)*$AH50 -> 76829.859 | O58: =(AA50+AB9)*AH$50 -> 60106.452 | P58: =(AA50*AG50+AB9)*AH50 -> 60151.497 | Q58: =(AA50+AB10)*$AH$50 -> 60106.452 | R58: =(AA50*AG50+AB10)*$AH50 -> 60151.497 | S58: =(AA50+AB12)*$AH$50 -> 545108.85 | AB58: 1 | AC58: =$AM$45*AF58 -> 273 | AD58: =AC58*$AM$40 -> 106470 | AE58: =AC58*$AM$41 -> 28018.421 | AF58: 7 | AG58: 5
B59: 101 a 500 | C59: =(AA51+AB11)*$AH$51 -> 190843.39 | D59: =(AA51*AG51+AB11)*$AH$51 -> 190887.07 | E59: =(AA51+AB4)*$AH$51 -> 226483.8 | F59: =(AA51*AG51+AB4)*AH$51 -> 226527.48 | G59: =(AA51+AB5)*$AH$51 -> 194137.88 | H59: =(AA51*AG51+AB5)*AH$51 -> 194181.56 | I59: =(AA51+AB6)*$AH$51 -> 142384.42 | J59: =(AA51*AG51+AB9)*AH$51 -> 58328.724 | K59: =(AA51+AB7)*$AH$51 -> 97100.141 | L59: =(AA51*AG51+AB7)*AH$51 -> 97143.821 | M59: =(AA51+AB8)*$AH$51 -> 74458.001 | N59: =(AA51*AG51+AB8)*$AH51 -> 74501.681 | O59: =(AA51+AB9)*AH$51 -> 58285.044 | P59: =(AA51*AG51+AB9)*AH51 -> 58328.724 | Q59: =(AA51+AB10)*$AH$51 -> 58285.044 | R59: =(AA51*AG51+AB10)*$AH51 -> 58328.724 | S59: =(AA51+AB12)*$AH$51 -> 528590.4 | AB59: 2 a 50 | AC59: =$AM$45*AF59 -> 195 | AD59: =AC59*$AM$40 -> 76050 | AE59: =AC59*$AM$41 -> 20013.158 | AF59: 5 | AG59: 3.5
B60: 501 a 1000 | C60: =(AA52+AB11)*$AH$52 -> 184879.53 | D60: =(AA52*AG52+AB11)*$AH$52 -> 184921.85 | E60: =(AA52+AB4)*$AH$52 -> 219406.18 | F60: =(AA52*AG52+AB4)*AH$52 -> 219448.49 | G60: =(AA52+AB5)*$AH$52 -> 188071.07 | H60: =(AA52*AG52+AB5)*AH$52 -> 188113.39 | I60: =(AA52+AB6)*$AH$52 -> 137934.91 | J60: =(AA52*AG52+AB6)*AH$52 -> 137977.22 | K60: =(AA52+AB7)*$AH$52 -> 94065.761 | L60: =(AA52*AG52+AB7)*AH$52 -> 94108.076 | M60: =(AA52+AB8)*$AH$52 -> 72131.189 | N60: =(AA52*AG52+AB8)*$AH52 -> 72173.504 | O60: =(AA52+AB9)*AH$52 -> 56463.637 | P60: =(AA52*AG52+AB9)*AH52 -> 56505.952 | Q60: =(AA52+AB10)*$AH$52 -> 56463.637 | R60: =(AA52*AG52+AB10)*$AH52 -> 56505.952 | S60: =(AA52+AB12)*$AH$52 -> 512071.95 | AB60: 51 a 100 | AC60: =$AM$45*AF60 -> 175.5 | AD60: =AC60*$AM$40 -> 68445 | AE60: =AC60*$AM$41 -> 18011.842 | AF60: 4.5 | AG60: 3
B61: 1001 a 5000 | C61: =(AA53+AB11)*$AH$53 -> 178915.68 | D61: =(AA53*AG53+AB11)*$AH$53 -> 178956.63 | E61: =(AA53+AB4)*$AH$53 -> 212328.56 | F61: =(AA53*AG53+AB4)*AH$53 -> 212369.51 | G61: =(AA53+AB5)*$AH$53 -> 182004.26 | H61: =(AA53*AG53+AB5)*AH$53 -> 182045.21 | I61: =(AA53+AB6)*$AH$53 -> 133485.39 | J61: =(AA53*AG53+AB6)*AH$53 -> 133526.34 | K61: =(AA53+AB7)*$AH$53 -> 91031.382 | L61: =(AA53*AG53+AB7)*AH$53 -> 91072.332 | M61: =(AA53+AB8)*$AH$53 -> 69804.376 | N61: =(AA53*AG53+AB8)*$AH53 -> 69845.326 | O61: =(AA53+AB9)*AH$53 -> 54642.229 | P61: =(AA53*AG53+AB9)*AH53 -> 54683.179 | Q61: =(AA53+AB10)*$AH$53 -> 54642.229 | R61: =(AA53*AG53+AB10)*$AH53 -> 54683.179 | S61: =(AA53+AB12)*$AH$53 -> 495553.5 | W61: 5color | AB61: 101 a 500 | AC61: =$AM$45*AF61 -> 156 | AD61: =AC61*$AM$40 -> 60840 | AE61: =AC61*$AM$41 -> 16010.526 | AF61: 4 | AG61: 2.5
W62: 1.3 | AB62: 501 a 1000 | AC62: =$AM$45*AF62 -> 117 | AD62: =AC62*$AM$40 -> 45630 | AE62: =AC62*$AM$41 -> 12007.895 | AF62: 3 | AG62: 2
B63: Bajada XL | C63: Triplex | E63: 350g | G63: 300g | I63: 200g | K63: 150g | M63: 115g | O63: 90g | Q63: OBRA | S63: Sticker | W63: 130 | X63: =W63*W62 -> 169 | AB63: 1001 a 5000 | AC63: =$AM$45*AF63 -> 78 | AD63: =AC63*$AM$40 -> 30420 | AE63: =AC63*$AM$41 -> 8005.2632 | AF63: 2 | AG63: 2
B64: 70x30 cm | C64: 1/0 | D64: 1/1 | E64: 1/0 | F64: 1/1 | G64: 1/0 | H64: 1/1 | I64: 1/0 | J64: 1/1 | K64: 1/0 | L64: 1/1 | M64: 1/0 | N64: 1/1 | O64: 1/0 | P64: 1/1 | Q64: 1/0 | R64: 1/1 | S64: 1/0 | W64: 119.6 | X64: =W64*W62 -> 155.48 | AB64: 1002 a 5000 | AC64: 1.5 | AD64: =AC64*$AM$40 -> 585 | AE64: =AC64*$AM$41 -> 153.94737 | AF64: 2 | AG64: 1.5
B65: 1 | C65: =(AA11+AA48*AN40)*AH$48 -> 339976.84 | D65: =(AA11+AA48*AN40)*AG48*$AH48 -> 577960.63 | E65: =(AA4+AA48*AN40)*$AH48 -> 403461.31 | F65: =(AA4+AA48*AN40)*AH48*AG48 -> 685884.23 | G65: =(AA5+AA48*AN40)*AH48 -> 345845.15 | H65: =(AA5+AA48*AN40)*AH48*AG48 -> 587936.76 | I65: =(AA6+AA48*AN40)*AH48 -> 253659.3 | J65: =(AA6+AA48*AN40)*AH48*AG48 -> 431220.81 | K65: =(AA7+AA48*AN40)*AH48 -> 172996.68 | L65: =(AA7+AA48*AN40)*AH48*AG48 -> 294094.35 | M65: =(AA8+AA48*AN40)*AH48 -> 132665.36 | N65: =(AA8+AA48*AN40)*AH48*AG48 -> 225531.12 | O65: =(AA9+AA48*AN40)*$AH$48 -> 103857.29 | P65: =(AA9+AA48*AN40)*AH48*AG48 -> 176557.39 | Q65: =(AA10+AA48*AN40)*$AH$48 -> 103857.29 | R65: =(AC9+AA48*AN40)*AH48*AG48 -> 99079.656 | S65: =(AA12+AA48*AN40)*$AH$48 -> 941588.7 | W65: 110.5 | X65: =W65*W62 -> 143.65
B66: 2 a 50 | C66: =(AA11+AA49*AN40)*AH$49 -> 304189.8 | D66: =(AA11+AA49*AN40)*AG49*$AH49 -> 517122.67 | E66: =(AA4+AA49*AN40)*$AH49 -> 360991.7 | F66: =(AA4+AA49*AN40)*AH49*AG49 -> 613685.89 | G66: =(AA5+AA49*AN40)*AH49 -> 309440.4 | H66: =(AA5+AA49*AN40)*AH49*AG49 -> 526048.68 | I66: =(AA6+AA49*AN40)*AH49 -> 226958.32 | J66: =(AA6+AA49*AN40)*AH49*AG49 -> 385829.14 | K66: =(AA7+AA49*AN40)*AH49 -> 154786.5 | L66: =(AA7+AA49*AN40)*AH49*AG49 -> 263137.05 | M66: =(AA8+AA49*AN40)*AH49 -> 118700.59 | N66: =(AA8+AA49*AN40)*AH49*AG49 -> 201791 | O66: =(AA9+AA49*AN40)*$AH$49 -> 92924.94 | P66: =(AA9+AA49*AN40)*AH49*AG49 -> 157972.4 | Q66: =(AA10+AA49*AN40)*$AH$49 -> 92924.94 | R66: =(AA10+AA49*AN40)*AH49*AG49 -> 157972.4 | S66: =(AA12+AA49*AN40)*$AH$49 -> 842474.1 | W66: 91 | X66: =W66*W62 -> 118.3
B67: 51 a 100 | C67: =(AA11+AA50*AN40)*AH$50 -> 295243.04 | D67: =(AA11+AA50*AN40)*AG50*$AH50 -> 501913.18 | E67: =(AA4+AA50*AN40)*$AH50 -> 350374.3 | F67: =(AA4+AA50*AN40)*AH50*AG50 -> 595636.3 | G67: =(AA5+AA50*AN40)*AH50 -> 300339.21 | H67: =(AA5+AA50*AN40)*AH50*AG50 -> 510576.66 | I67: =(AA6+AA50*AN40)*AH50 -> 220283.07 | J67: =(AA6+AA50*AN40)*AH50*AG50 -> 374481.23 | K67: =(AA7+AA50*AN40)*AH50 -> 150233.96 | L67: =(AA7+AA50*AN40)*AH50*AG50 -> 255397.72 | M67: =(AA8+AA50*AN40)*AH50 -> 115209.4 | N67: =(AA8+AA50*AN40)*AH50*AG50 -> 195855.97 | O67: =(AA9+AA50*AN40)*$AH$50 -> 90191.853 | P67: =(AA9+AA50*AN40)*AH50*AG50 -> 153326.15 | Q67: =(AA10+AA50*AN40)*$AH$50 -> 90191.853 | R67: =(AA10+AA50*AN40)*AH50*AG50 -> 153326.15 | S67: =(AA12+AA50*AN40)*$AH$50 -> 817695.45 | W67: 92.3 | X67: =W67*W62 -> 119.99 | AB67: costo clic ByN | AC67: 0.3
B68: 101 a 500 | C68: =(AA11+AA51*AN40)*AH$51 -> 286296.29 | D68: =(AA11+AA51*AN40)*AG51*$AH51 -> 486703.69 | E68: =(AA4+AA51*AN40)*$AH51 -> 339756.89 | F68: =(AA4+AA51*AN40)*AH51*AG51 -> 577586.72 | G68: =(AA5+AA51*AN40)*AH51 -> 291238.02 | H68: =(AA5+AA51*AN40)*AH51*AG51 -> 495104.64 | I68: =(AA6+AA51*AN40)*AH51 -> 213607.83 | J68: =(AA6+AA51*AN40)*AH51*AG51 -> 363133.31 | K68: =(AA7+AA51*AN40)*AH51 -> 145681.41 | L68: =(AA7+AA51*AN40)*AH51*AG51 -> 247658.4 | M68: =(AA8+AA51*AN40)*AH51 -> 111718.2 | N68: =(AA8+AA51*AN40)*AH51*AG51 -> 189920.94 | O68: =(AA9+AA51*AN40)*$AH$51 -> 87458.767 | P68: =(AA9+AA51*AN40)*AH51*AG51 -> 148679.9 | Q68: =(AA10+AA51*AN40)*$AH$51 -> 87458.767 | R68: =(AA10+AA51*AN40)*AH51*AG51 -> 148679.9 | S68: =(AA12+AA51*AN40)*$AH$51 -> 792916.8 | W68: 83.2 | X68: =W68*W62 -> 108.16
B69: 501 a 1000 | C69: =(AA11+AA52*AN40)*AH$52 -> 277349.53 | D69: =(AA11+AA52*AN40)*AG52*$AH52 -> 471494.2 | E69: =(AA4+AA52*AN40)*$AH52 -> 329139.49 | F69: =(AA4+AA52*AN40)*AH52*AG52 -> 559537.13 | G69: =(AA5+AA52*AN40)*AH52 -> 282136.83 | H69: =(AA5+AA52*AN40)*AH52*AG52 -> 479632.62 | I69: =(AA6+AA52*AN40)*AH52 -> 206932.59 | J69: =(AA6+AA52*AN40)*AH52*AG52 -> 351785.39 | K69: =(AA7+AA52*AN40)*AH52 -> 141128.87 | L69: =(AA7+AA52*AN40)*AH52*AG52 -> 239919.07 | M69: =(AA8+AA52*AN40)*AH52 -> 108227.01 | N69: =(AA8+AA52*AN40)*AH52*AG52 -> 183985.91 | O69: =(AA9+AA52*AN40)*$AH$52 -> 84725.68 | P69: =(AA9+AA52*AN40)*AH52*AG52 -> 144033.66 | Q69: =(AA10+AA52*AN40)*$AH$52 -> 84725.68 | R69: =(AA10+AA52*AN40)*AH52*AG52 -> 144033.66 | S69: =(AA12+AA52*AN40)*$AH$52 -> 768138.15 | W69: 72.8 | X69: =W69*W62 -> 94.64 | AB69: A3 PLUS | AC69: Triplex | AE69: 350g | AG69: 300g | AI69: 200g | AK69: 150g | AM69: 90g | AO69: Sticker | AP69: Imán | AR69: OPP + blco
B70: 1001 a 5000 | C70: =(AA11+AA53*AN40)*AH$53 -> 268402.77 | D70: =(AA11+AA53*AN40)*AG53*$AH53 -> 456284.71 | E70: =(AA4+AA53*AN40)*$AH53 -> 318522.09 | F70: =(AA4+AA53*AN40)*AH53*AG53 -> 541487.55 | G70: =(AA5+AA53*AN40)*AH53 -> 273035.65 | H70: =(AA5+AA53*AN40)*AH53*AG53 -> 464160.6 | I70: =(AA6+AA53*AN40)*AH53 -> 200257.34 | J70: =(AA6+AA53*AN40)*AH53*AG53 -> 340437.48 | K70: =(AA7+AA53*AN40)*AH53 -> 136576.32 | L70: =(AA7+AA53*AN40)*AH53*AG53 -> 232179.75 | M70: =(AA8+AA53*AN40)*AH53 -> 104735.81 | N70: =(AA8+AA53*AN40)*AH53*AG53 -> 178050.88 | O70: =(AA9+AA53*AN40)*$AH$53 -> 81992.594 | P70: =(AA10+AA53*AN40)*AH53*AG53 -> 139387.41 | Q70: =(AA10+AA53*AN40)*$AH$53 -> 81992.594 | R70: =(AA10+AA53*AN40)*AH53*AG53 -> 139387.41 | S70: =(AA12+AA53*AN40)*$AH$53 -> 743359.5 | AB70: 32x47 cm | AC70: 4/0 | AD70: 4/4 | AE70: 4/0 | AF70: 4/4 | AG70: 4/0 | AH70: 4/4 | AI70: 4/0 | AJ70: 4/4 | AK70: 4/0 | AL70: 4/4 | AM70: 4/0 | AN70: 4/4 | AO70: 4/0 | AP70: 4/0 | AR70: 4/0
AB71: 1 | AE71: =$AM$42*(AH48+1)+$AC$4 -> 119553.12 | AF71: =$AM$42*(AI48+1)+$AC$4 -> 119514.12
B72: Bajada A4 | C72: Triplex | E72: 350g | G72: 300g | I72: 200g | K72: 150g | M72: 115g | O72: 90g | Q72: OBRA | S72: Sticker | AB72: 2 a 25 | AE72: =$AM$42*(AH49+1)+$AC$4 -> 119514.12 | AF72: =$AM$42*(AI49+1)+$AC$4 -> 119514.12
B73: 22x31 cm | C73: 1/0 | D73: 1/1 | E73: 1/0 | F73: 1/1 | G73: 1/0 | H73: 1/1 | I73: 1/0 | J73: 1/1 | K73: 1/0 | L73: 1/1 | M73: 1/0 | N73: 1/1 | O73: 1/0 | P73: 1/1 | Q73: 1/0 | R73: 1/1 | S73: 1/0 | AB73: 26 a 50 | AE73: =$AM$42*(AH50+1)+$AC$4 -> 119504.37 | AF73: =$AM$42*(AI50+1)+$AC$4 -> 119514.12
B74: 1 | C74: =(AA48+AD11)*$AH$48 -> 136005.56 | D74: =(AA48*AG48+AD11)*$AH$48 -> 136057.43 | E74: =(AA48+AD4)*$AH$48 -> 135719.99 | F74: =(AA48*AG48+AD4)*AH$48 -> 135771.86 | G74: =(AA48+AD5)*$AH$48 -> 116342 | H74: =(AA48*AG48+AD5)*AH$48 -> 116393.87 | I74: =(AA48+AD6)*$AH$48 -> 85337.228 | J74: =(AA48*AG48+AD6)*AH$48 -> 85389.098 | K74: =(AA48+AD7)*$AH$48 -> 58208.051 | L74: =(AA48*AG48+AD7)*AH$48 -> 58259.921 | M74: =(AA48+AD8)*$AH$48 -> 44643.462 | N74: =(AA48*AG48+AD8)*$AH48 -> 44695.332 | O74: =(AA48+AD9)*AH$48 -> 34954.471 | P74: =(AA48*AG48+AD9)*AH48 -> 35006.341 | Q74: =(AA48+AD10)*$AH$48 -> 34954.471 | R74: =(AA48*AG48+AD10)*$AH48 -> 35006.341 | S74: =(AA48+AD12)*AH$48 -> 313887.6 | AB74: 51 a 100 | AE74: =$AM$42*(AH51+1)+$AC$4 -> 119494.62 | AF74: =$AM$42*(AI51+1)+$AC$4 -> 119514.12
B75: 2 a 50 | C75: =(AA49+AD11)*$AH$49 -> 121689.18 | D75: =(AA49*AG49+AD11)*$AH$49 -> 121735.59 | E75: =(AA49+AD4)*$AH$49 -> 121433.67 | F75: =(AA49*AG49+AD4)*AH$49 -> 121480.08 | G75: =(AA48+AD5)*$AH$49 -> 104095.48 | H75: =(AA49*AG49+AD5)*AH$49 -> 104141.89 | I75: =(AA49+AD6)*$AH$49 -> 76354.362 | J75: =(AA49*AG49+AD6)*AH$49 -> 76400.772 | K75: =(AA49+AD7)*$AH$49 -> 52080.888 | L75: =(AA49*AG49+AD7)*AH$49 -> 52127.298 | M75: =(AA49+AD8)*$AH$49 -> 39944.151 | N75: =(AA49*AG49+AD8)*$AH49 -> 39990.561 | O75: =(AA49+AD9)*AH$49 -> 31275.053 | P75: =(AA49*AG49+AD9)*AH49 -> 31321.463 | Q75: =(AA49+AD10)*$AH$49 -> 31275.053 | R75: =(AA49*AG49+AD10)*$AH49 -> 31321.463 | S75: =(AA49+AD12)*AH$49 -> 280846.8 | AB75: 101 a 300 | AE75: =$AM$42*(AH52+1)+$AC$4 -> 119484.87 | AF75: =$AM$42*(AI52+1)+$AC$4 -> 119514.12
B76: 51 a 100 | C76: =(AA50+AD11)*$AH$50 -> 118110.09 | D76: =(AA50*AG50+AD11)*$AH$50 -> 118155.13 | E76: =(AA50+AD4)*$AH$50 -> 117862.09 | F76: =(AA50*AG50+AD4)*AH$50 -> 117907.14 | G76: =(AA50+AD5)*$AH$50 -> 101033.84 | H76: =(AA50*AG50+AD5)*AH$50 -> 101078.89 | I76: =(AA50+AD6)*$AH$50 -> 74108.645 | J76: =(AA50*AG50+AD6)*AH$50 -> 74153.69 | K76: =(AA50+AD7)*$AH$50 -> 50549.097 | L76: =(AA50*AG50+AD7)*AH$50 -> 50594.142 | M76: =(AA50+AD8)*$AH$50 -> 38769.323 | N76: =(AA50*AG50+AD8)*$AH50 -> 38814.368 | O76: =(AA50+AD8)*AH$50 -> 38769.323 | P76: =(AA50*AG50+AD9)*AH50 -> 30400.243 | Q76: =(AA50+AD10)*$AH$50 -> 30355.198 | R76: =(AA50*AG50+AD10)*$AH50 -> 30400.243 | S76: =(AA50+AD12)*AH$50 -> 272586.6 | AB76: 301 a 500 | AE76: =$AM$42*(AH53+1)+$AC$4 -> 119475.12 | AF76: =$AM$42*(AI53+1)+$AC$4 -> 119514.12
B77: 101 a 500 | C77: =(AA51+AD11)*$AH$51 -> 114530.99 | D77: =(AA51*AG51+AD11)*$AH$51 -> 114574.67 | E77: =(AA51+AD4)*$AH$51 -> 114290.51 | F77: =(AA51*AG51+AD4)*AH$51 -> 114334.19 | G77: =(AA51+AD5)*$AH$51 -> 97972.212 | H77: =(AA51*AG51+AD5)*AH$51 -> 98015.892 | I77: =(AA51+AD6)*$AH$51 -> 71862.929 | J77: =(AA51*AG51+AD6)*AH$51 -> 71906.609 | K77: =(AA51+AD7)*$AH$51 -> 49017.306 | L77: =(AA51*AG51+AD7)*AH$51 -> 49060.986 | M77: =(AA51+AD8)*$AH$51 -> 37594.495 | N77: =(AA51*AG51+AD8)*$AH51 -> 37638.175 | O77: =(AA51+AD9)*AH$51 -> 29435.344 | P77: =(AA51*AG51+AD9)*AH51 -> 29479.024 | Q77: =(AA51+AD10)*$AH$51 -> 29435.344 | R77: =(AA51*AG51+AD10)*$AH51 -> 29479.024 | S77: =(AA51+AD12)*AH$51 -> 264326.4 | AB77: 501 a 1000 | AE77: =$AM$42*(AH54+1)+$AC$4 -> 119465.37 | AF77: =$AM$42*(AI54+1)+$AC$4 -> 119514.12
B78: 501 a 1000 | C78: =(AA52+AD11)*$AH$52 -> 110951.9 | D78: =(AA52*AG52+AD11)*$AH$52 -> 110994.22 | E78: =(AA52+AD4)*$AH$52 -> 110718.94 | F78: =(AA52*AG52+AD4)*AH$52 -> 110761.25 | G78: =(AA52+AD5)*$AH$52 -> 94910.58 | H78: =(AA52*AG52+AD5)*AH$52 -> 94952.895 | I78: =(AA52+AD6)*$AH$52 -> 69617.212 | J78: =(AA52*AG52+AD6)*AH$52 -> 69659.527 | K78: =(AA52+AD7)*$AH$52 -> 47485.515 | L78: =(AA52*AG52+AD7)*AH$52 -> 47527.83 | M78: =(AA52+AD8)*$AH$52 -> 36419.667 | N78: =(AA52*AG52+AD8)*$AH52 -> 36461.982 | O78: =(AA52+AD9)*AH$52 -> 28515.489 | P78: =(AA52*AG52+AD9)*AH52 -> 28557.804 | Q78: =(AA52+AD10)*$AH$52 -> 28515.489 | R78: =(AA52*AG52+AD10)*$AH52 -> 28557.804 | S78: =(AA52+AD12)*AH$52 -> 256066.2
B79: 1001 a 5000 | C79: =(AA53+AD11)*$AH$53 -> 107372.81 | D79: =(AA53*AG53+AD11)*$AH$53 -> 107413.76 | E79: =(AA53+AD4)*$AH$53 -> 107147.36 | F79: =(AA53*AG53+AD4)*AH$53 -> 107188.31 | G79: =(AA52+AD5)*$AH$53 -> 91848.949 | H79: =(AA53*AG53+AD5)*AH$53 -> 91889.899 | I79: =(AA53+AD6)*$AH$53 -> 67371.496 | J79: =(AA53*AG53+AD6)*AH$53 -> 67412.446 | K79: =(AA53+AD7)*$AH$53 -> 45953.724 | L79: =(AA53*AG53+AD7)*AH$53 -> 45994.674 | M79: =(AA53+AD8)*$AH$53 -> 35244.839 | N79: =(AA53*AG53+AD8)*$AH53 -> 35285.789 | O79: =(AA53+AD9)*AH$53 -> 27595.635 | P79: =(AA53*AG53+AD9)*AH53 -> 27636.585 | Q79: =(AA53+AD10)*$AH$53 -> 27595.635 | R79: =(AA53*AG53+AD10)*$AH53 -> 27636.585 | S79: =(AA53+AD12)*AH$53 -> 247806
B84: Encuadernacion
B86: biender | C86: ringwire | D86: espiral | E86: acaballado
B87: 242.7685 | C87: 228.488 | D87: 219.9197 | E87: 82.8269
B88: 211.3514 | C88: 202.7831 | D88: 179.9343 | E88: 62.8342
B89: 188.5026 | C89: 165.6538 | D89: 151.3733 | E89: 48.5537
B90: 151.3733 | C90: 137.0928 | D90: 122.8123 | E90: 42.8415
B91: 139.9489 | C91: 134.2367 | D91: 108.5318 | E91: 37.1293
B92: 131.3806 | C92: 122.8123 | D92: 94.2513 | E92: 31.4171

Sheet PAPEL US$
J1: 32x47 | T1: uss | U1: cambio | AA1: uss | AB1: cambio
C2: dólar | D2: 80 | E2: uss | F2: 1400 | G2: 0.0065 | H2: 1.21 | I2: 4 | J2: 1 | K2: 2 | L2: 3 | M2: 1000 | T2: 2 | U2: 1 | AA2: 3.2 | AB2: 134 | AC2: 1050 | AD2: 2600 | AE2: 5150
B3: obra 70 grs. 65x95cm | E3: =T3 -> 0.08645 | F3: =E3*F2 -> 121.03 | H3: =F3*H2 -> 146.4463 | I3: =H3/I2 -> 36.611575 | J3: =I3*J2 -> 36.611575 | K3: =J3/K2*1.25 -> 22.882234 | P3: 65 | Q3: 95 | R3: 70 | S3: =P3*Q3*R3/20000 -> 21.6125 | T3: =S3*T2*U2/500 -> 0.08645 | U3: =T3/4 -> 0.0216125 | W3: 72 | X3: 102 | Y3: 150 | Z3: =W3*X3*Y3/20000 -> 55.08 | AA3: =Z3*AA2*AB2/500 -> 47.236608 | AB3: =AA3*1.21 -> 57.156296 | AC3: =AB3*$AC$2 -> 60014.11 | AD3: =AB3*AD$2 -> 148606.37 | AE3: =AB3*AE$2 -> 294354.92
B4: obra 80 grs. 65x95cm | E4: =T4 -> 0.0988 | F4: =E:E*F2 -> 138.32 | H4: =F4*H2 -> 167.3672 | I4: =H4/I2 -> 41.8418 | J4: =I4*J2 -> 41.8418 | K4: =J4/K2*1.25 -> 26.151125 | P4: 65 | Q4: 95 | R4: 80 | S4: =P4*Q4*R4/20000 -> 24.7 | T4: =S4*T2*U2/500 -> 0.0988 | U4: =T4/4 -> 0.0247 | W4: 95 | X4: 65 | Y4: 150 | Z4: =W4*X4*Y4/20000 -> 46.3125 | AA4: =Z4*AA2*AB2/500 -> 39.7176 | AB4: =AA4*1.21 -> 48.058296 | AC4: =AB4*$AC$2 -> 50461.211 | AD4: =AB4*AD$2 -> 124951.57 | AE4: =AB4*AE$2 -> 247500.22
B5: obra 90 grs. 65x95cm | E5: =T5 -> 0.11115 | F5: =E5*F2 -> 155.61 | H5: =F5*H2 -> 188.2881 | I5: =H5/I2 -> 47.072025 | J5: =I5*J2 -> 47.072025 | K5: =J5/K2*1.25 -> 29.420016 | P5: 65 | Q5: 95 | R5: 90 | S5: =P5*Q5*R5/20000 -> 27.7875 | T5: =S5*T2*U2/500 -> 0.11115 | U5: =T5/4 -> 0.0277875 | W5: 95 | X5: 65 | Y5: 115 | Z5: =W5*X5*Y5/20000 -> 35.50625 | AA5: =Z5*AA2*AB2/500 -> 30.45016 | AB5: =AA5*1.21 -> 36.844694 | AC5: =AB5*$AC$2 -> 38686.928 | AD5: =AB5*AD$2 -> 95796.203 | AE5: =AB5*AE$2 -> 189750.17
B6: obra 90 grs. 65x95cm boreal | E6: =T6 -> 0.11115 | F6: =E6*F2 -> 155.61 | H6: =F6*H2 -> 188.2881 | I6: =H6/I2 -> 47.072025 | J6: =I6*J2 -> 47.072025 | K6: =J6/K2*1.25 -> 29.420016 | M6: 0.0232925 | P6: 65 | Q6: 95 | R6: 90 | S6: =P6*Q6*R6/20000 -> 27.7875 | T6: =S6*T2*U2/500 -> 0.11115 | U6: =T6/4 -> 0.0277875 | W6: 72 | X6: 102 | Y6: 115 | Z6: =W6*X6*Y6/20000 -> 42.228 | AA6: =Z6*AA2*AB2/500 -> 36.214733 | AB6: =AA6*1.21 -> 43.819827 | AC6: =AB6*$AC$2 -> 46010.818 | AD6: =AB6*AD$2 -> 113931.55 | AE6: =AB6*AE$2 -> 225672.11
B7: obra 90 grs. 72x102 cm | E7: =T7 -> 0.132192 | F7: =E7*F2 -> 185.0688 | H7: =F7*H2 -> 223.93325 | I7: =H7/I2 -> 55.983312 | J7: =I7*J2 -> 55.983312 | K7: =J7/K2*1.25 -> 34.98957 | L7: =H7/L2 -> 74.644416 | P7: 72 | Q7: 102 | R7: 90 | S7: =P7*Q7*R7/20000 -> 33.048 | T7: =S7*T2*U2/500 -> 0.132192 | U7: =T7/4 -> 0.033048 | W7: 72 | X7: 102 | Y7: 220 | Z7: =W7*X7*Y7/20000 -> 80.784 | AA7: =Z7*AA2*AB2/500 -> 69.280358 | AB7: =AA7*1.21 -> 83.829234 | AC7: =AB7*$AC$2 -> 88020.695 | AD7: =AB7*AD$2 -> 217956.01 | AE7: =AB7*AE$2 -> 431720.55
B8: obra 90 grs. 72x102 cm boreal | E8: =T8 -> 0.132192 | F8: =E8*F2 -> 185.0688 | H8: =F8*H2 -> 223.93325 | I8: =H8/I2 -> 55.983312 | J8: =I8*J2 -> 55.983312 | K8: =J8/K2*1.25 -> 34.98957 | L8: =H8/L2 -> 74.644416 | M8: 0.036784 | P8: 72 | Q8: 102 | R8: 90 | S8: =P8*Q8*R8/20000 -> 33.048 | T8: =S8*T2*U2/500 -> 0.132192 | U8: =T8/4 -> 0.033048 | W8: 65 | X8: 95 | Y8: 300 | Z8: =W8*X8*Y8/20000 -> 92.625 | AA8: =Z8*AA2*AB2/500 -> 79.4352 | AB8: =AA8*1.21 -> 96.116592 | AC8: =AB8*$AC$2 -> 100922.42 | AD8: =AB8*AD$2 -> 249903.14 | AE8: =AB8*AE$2 -> 495000.45
F9: =E9*F4 -> 0 | I9: =H9/I7 -> 0 | K9: =J9/K2 -> 0 | W9: 65 | X9: 95 | Y9: 350 | Z9: =W9*X9*Y9/20000 -> 108.0625 | AA9: =Z9*AA2*AB2/500 -> 92.6744 | AB9: =AA9*1.21 -> 112.13602 | AC9: =AB9*$AC$2 -> 117742.83 | AD9: =AB9*AD$2 -> 291553.66 | AE9: =AB9*AE$2 -> 577500.52
B10: ilustracion 90 grs. 65x95cm | E10: =T10 -> 0.11115 | F10: =E10*F2 -> 155.61 | H10: =F10*H2 -> 188.2881 | I10: =H10/I2 -> 47.072025 | J10: =I10*J2 -> 47.072025 | K10: =J10/K2*1.25 -> 29.420016 | L10: 0.02783 | M10: 0.01739375 | P10: 65 | Q10: 95 | R10: 90 | S10: =P10*Q10*R10/20000 -> 27.7875 | T10: =S10*T2*U2/500 -> 0.11115 | U10: =T10/2 -> 0.055575 | W10: 65 | X10: 50 | Y10: 90 | Z10: =W10*X10*Y10/20000 -> 14.625 | AA10: =Z10*AA2*AB2/500*1.21 -> 15.176304 | AB10: =AA10*1.21 -> 18.363328 | AC10: =AB10*$AC$2 -> 19281.494 | AD10: =AB10*AD$2 -> 47744.652 | AE10: =AB10*AE$2 -> 94571.138
B11: ilustracion 115 grs. 65x95cm | E11: =T11 -> 0.142025 | F11: =E11*F2 -> 198.835 | H11: =F11*H2 -> 240.59035 | I11: =H11/I2 -> 60.147588 | J11: =I11*J2 -> 60.147588 | K11: =J11/K2*1.25 -> 37.592242 | P11: 65 | Q11: 95 | R11: 115 | S11: =P11*Q11*R11/20000 -> 35.50625 | T11: =S11*T2*U2/500 -> 0.142025 | U11: =T11/4 -> 0.03550625
B12: ilustracion 150 grs. 65x95cm | E12: =T12 -> 0.18525 | F12: =E12*F2 -> 259.35 | H12: =F12*H2 -> 313.8135 | I12: =H12/I2 -> 78.453375 | J12: =I12*J2 -> 78.453375 | K12: =J12/K2*1.25 -> 49.033359 | P12: 65 | Q12: 95 | R12: 150 | S12: =P12*Q12*R12/20000 -> 46.3125 | T12: =S12*T2*U2/500 -> 0.18525 | U12: =T12/4 -> 0.0463125
B13: ilustracion 200 grs. 65x95cm | E13: =T13 -> 0.2717 | F13: =E13*F2 -> 380.38 | H13: =F13*H2 -> 460.2598 | I13: =H13/I2 -> 115.06495 | J13: =I13*J2 -> 115.06495 | K13: =J13/K2*1.25 -> 71.915594 | P13: 65 | Q13: 95 | R13: 220 | S13: =P13*Q13*R13/20000 -> 67.925 | T13: =S13*T2*U2/500 -> 0.2717 | U13: =T13/4 -> 0.067925
F14: =E14*F3 -> 0 | I14: =H14/I3 -> 0
B15: ilustracion 90 grs. 72x102 cm | E15: =T15 -> 0.132192 | F15: =E15*F2 -> 185.0688 | H15: =F15*H2 -> 223.93325 | I15: =H15/I2 -> 55.983312 | J15: =I15*J2 -> 55.983312 | K15: =J15/K2*1.25 -> 34.98957 | L15: =H15/L2 -> 74.644416 | P15: 72 | Q15: 102 | R15: 90 | S15: =P15*Q15*R15/20000 -> 33.048 | T15: =S15*T2*U2/500 -> 0.132192 | U15: =T15/4 -> 0.033048
B16: ilustracion 115 grs. 72x102 cm | E16: =T16 -> 0.168912 | F16: =E16*F2 -> 236.4768 | H16: =F16*H2 -> 286.13693 | I16: =H16/I2 -> 71.534232 | J16: =I16*J2 -> 71.534232 | K16: =J16/K2*1.25 -> 44.708895 | L16: =H16/L2 -> 95.378976 | P16: 72 | Q16: 102 | R16: 115 | S16: =P16*Q16*R16/20000 -> 42.228 | T16: =S16*T2*U2/500 -> 0.168912 | U16: =T16/4 -> 0.042228
B17: ilustracion 150 grs. 72x102cm | E17: =T17 -> 0.22032 | F17: =E17*F2 -> 308.448 | H17: =F17*H2 -> 373.22208 | I17: =H17/I2 -> 93.30552 | J17: =I17*J2 -> 93.30552 | K17: =J17/K2*1.25 -> 58.31595 | L17: =H17/L2 -> 124.40736 | P17: 72 | Q17: 102 | R17: 150 | S17: =P17*Q17*R17/20000 -> 55.08 | T17: =S17*T2*U2/500 -> 0.22032 | U17: =T17/4 -> 0.05508
B18: ilustracion 200 grs 72x102 | E18: =T18 -> 0.323136 | F18: =E18*F2 -> 452.3904 | H18: =F18*H2 -> 547.39238 | I18: =H18/I2 -> 136.8481 | J18: =I18*J2 -> 136.8481 | K18: =J18/K2*1.25 -> 85.53006 | L18: =H18/L2 -> 182.46413 | P18: 72 | Q18: 102 | R18: 220 | S18: =P18*Q18*R18/20000 -> 80.784 | T18: =S18*T2*U2/500 -> 0.323136 | U18: =T18/4 -> 0.080784
F19: =E19*F13 -> 0 | H19: =F19*H9 -> 0 | I19: =H19/I2 -> 0 | J19: =I19*J2 -> 0 | K19: =J19/K2*1.25 -> 0
B20: ilustracion 300 grs brillo 65x95 cm | E20: =T20 -> 0.3705 | F20: =E20*F2 -> 518.7 | H20: =F20*H2 -> 627.627 | I20: =H20/I2 -> 156.90675 | J20: =I20*J2 -> 156.90675 | K20: =J20/K2*1.25 -> 98.066719 | P20: 65 | Q20: 95 | R20: 300 | S20: =P20*Q20*R20/20000 -> 92.625 | T20: =S20*T2*U2/500 -> 0.3705 | U20: =T20/4 -> 0.092625
B21: ilustracion 300 grs brillo 72x102 cm | E21: =T21 -> 0.44064 | F21: =E21*F2 -> 616.896 | H21: =F21*H2 -> 746.44416 | I21: =H21/I2 -> 186.61104 | J21: =I21*J2 -> 186.61104 | K21: =J21/K2*1.25 -> 116.6319 | L21: =H21/L2 -> 248.81472 | P21: 72 | Q21: 102 | R21: 300 | S21: =P21*Q21*R21/20000 -> 110.16 | T21: =S21*T2*U2/500 -> 0.44064 | U21: =T21/4 -> 0.11016
F22: =E22*F17 -> 0 | H22: =F22*H12 -> 0 | I22: =H22/I2 -> 0 | J22: =I22*J2 -> 0 | K22: =J22/K2*1.25 -> 0
B23: ilustracion 350 grs mate 65x95 cm | E23: =T23 -> 0.43225 | F23: =E23*F2 -> 605.15 | H23: =F23*H2 -> 732.2315 | I23: =H23/I2 -> 183.05787 | J23: =I23*J2 -> 183.05787 | K23: =J23/K2*1.25 -> 114.41117 | P23: 65 | Q23: 95 | R23: 350 | S23: =P23*Q23*R23/20000 -> 108.0625 | T23: =S23*T2*U2/500 -> 0.43225 | U23: =T23/4 -> 0.1080625
B24: ilustracion 350 grs mate 72x102 cm | E24: =T24 -> 0.51408 | F24: =E24*F2 -> 719.712 | H24: =F24*H2 -> 870.85152 | I24: =H24/I2 -> 217.71288 | J24: =I24*J2 -> 217.71288 | K24: =J24/K2*1.25 -> 136.07055 | L24: =H24/L2 -> 290.28384 | P24: 72 | Q24: 102 | R24: 350 | S24: =P24*Q24*R24/20000 -> 128.52 | T24: =S24*T2*U2/500 -> 0.51408 | U24: =T24/4 -> 0.12852
D25: MARCOUX | E25: 0.3925 | F25: =E25*F2 -> 549.5 | H25: =F25*H2 -> 664.895 | I25: =H25/I2 -> 166.22375 | J25: =I25*J2 -> 166.22375 | K25: =J25/K2*1.25 -> 103.88984
B26: Cartulina duplex 68x96 325 | E26: =T26 -> 0.43225 | F26: =E26*F2 -> 605.15 | H26: =F26*H2 -> 732.2315 | I26: =H26/I2 -> 183.05787 | J26: =I26*J2 -> 183.05787 | K26: =J26/K2*1.25 -> 114.41117 | P26: 65 | Q26: 95 | R26: 350 | S26: =P26*Q26*R26/20000 -> 108.0625 | T26: =S26*T2*U2/500 -> 0.43225 | U26: =T26/4 -> 0.1080625 | X26: 6
B27: Cartulina maule x 68x96 300 | E27: 0.8 | F27: =E27*F2 -> 1120 | H27: =F27*H2 -> 1355.2 | I27: =H27/I2 -> 338.8 | J27: =I27*J2 -> 338.8 | K27: =J27/K2*1.25 -> 211.75 | P27: 72 | Q27: 102 | R27: 350 | S27: =P27*Q27*R27/20000 -> 128.52 | T27: =S27*T2*U2/500 -> 0.51408 | U27: =T27/4 -> 0.12852 | X27: blanca | Y27: impresa
F28: =E28*F23 -> 0 | H28: =F28*H19 -> 0 | I28: =H28/I2 -> 0 | J28: =I28*J12 -> 0 | K28: =J7/K2*1.25 -> 34.98957 | W28: solapa | X28: =(J20/X26*2)*1.5 -> 78.453375 | Y28: =X28*2 -> 156.90675
B29: Cartulina triplex 68x96 325 | E29: =T29 -> 0.43316 | F29: =E29*F2 -> 606.424 | H29: =F29*H2 -> 733.77304 | I29: =H29/I2 -> 183.44326 | J29: =I29*J2 -> 183.44326 | K29: =J29/K2*1.25 -> 114.65204 | P29: 68 | Q29: 98 | R29: 325 | S29: =P29*Q29*R29/20000 -> 108.29 | T29: =S29*T2*U2/500 -> 0.43316 | U29: =T29/4 -> 0.10829
F30: =E30*F25 -> 0 | H30: =F30*H21 -> 0 | I30: =H30/I2 -> 0 | J30: =I30*J3 -> 0 | K30: =J30/K3*1.25 -> 0 | T30: 10 | U30: 1
B31: autoadhesivo 90 50x65 | E31: 0.5 | F31: =E31*F2 -> 700 | H31: =F31*H2 -> 847 | I31: =H31/K2 -> 423.5 | J31: =I31*J2 -> 423.5 | K31: =J31/K2*1.25 -> 264.6875 | P31: 65 | Q31: 50 | R31: 90 | S31: =P31*Q31*R31/20000 -> 14.625 | T31: =S31*T30*U30/500 -> 0.2925 | U31: =T31/4 -> 0.073125
B32: autoadhesivo 90 50x65 | E32: 0.5 | F32: =E32*F2 -> 700 | H32: =F32*H2 -> 847 | I32: =H32/K2 -> 423.5 | J32: =I32*J2 -> 423.5 | K32: =J32/K2*1.25 -> 264.6875 | P32: 65 | Q32: 50 | R32: 90 | S32: =P32*Q32*R32/20000 -> 14.625 | T32: =S32*T30*U30/500 -> 0.2925 | U32: =T32/4 -> 0.073125
B33: autoadhesivo 90 100x70 | E33: 0.9 | F33: =E33*F2 -> 1260 | H33: =F33*H2 -> 1524.6 | I33: =H33/I2 -> 381.15 | J33: =I33*J2 -> 381.15 | K33: =J33/K2*1.25 -> 238.21875 | L33: =H33/L2 -> 508.2
F34: =E34*F3 -> 0 | H34: =F34*H3 -> 0 | I34: =H34/I3 -> 0 | J34: =I34*J3 -> 0 | K34: =J34/K3*1.25 -> 0
F35: =E35*F4 -> 0 | H35: =F35*H4 -> 0 | I35: =H35/I4 -> 0 | J35: =I35*J4 -> 0 | K35: =J35/K4*1.25 -> 0
B36: OPP BLANCO | D36: 50x70 | E36: 1.4 | F36: 1.3 | H36: =F36*H2 -> 1.573 | I36: =H36/K2 -> 0.7865 | J36: =I36*J2 -> 0.7865 | K36: =J36/K2*1.25 -> 0.4915625 | P36: 1.2 | Q36: 72x52 | R36: 72x102 | T36: 72x52 | U36: 72x102
B37: OPP CLEAR | P37: ctp x chapa | Q37: 800 | R37: 1000
P38: millar | Q38: 1000 | R38: 1400
F39: 295 | P39: postura sin millar | Q39: 1800 | R39: 2400
B40: Craft 80 grs medida??? | D40: 85x120 | E40: kg u$s 2,21
B41: Craft 200 grs medida??? | D41: 85x120 | Q41: 4/0 | R41: 4//4
B42: Craft 270 grs medida??? | D42: 85x120 | L42: tacho 22 kilos rinde | N42: 4000 | O42: pliegos | P42: 72x102
M43: leito | N43: 1500 | P43: x1000 | Q43: =R37*4+R38+R39 -> 7800 | R43: =R37*8+R38*2+R39*2 -> 15600
M44: remis | N44: 600 | P44: x2500 | Q44: =R37*4+R38*3+R39 -> 10600 | R44: =R37*8+R38*6+R39*2 -> 21200 | U44: tarot papel
M45: cola | N45: 1600 | P45: x5000 | Q45: =R37*4+R38*5+R39 -> 13400 | R45: =R37*8+R38*10+R39*2 -> 26800 | U45: impresión | V45: 92785
B46: 1121051052 | C46: CÓD: 80082 | M46: cada pliego | N46: 3.7 | U46: troquel | V46: 50880
B47: LACA DIGITAL AQUALINA | E47: 28 | F47: =E47*F2 -> 39200 | H47: =F47*H2 -> 47432 | I47: =H47/M2*1.5 -> 71.148 | J47: pliego laca digital con iva | Q47: 72x52 | R47: 72x102 | U47: troquelado
B48: IMAN ILPEA | C48: bobina x2000 cm | D48: 62110 | E48: 3000 | F48: =D48/E48 -> 20.703333 | G48: =F48*48 -> 993.76 | H48: =G48 -> 993.76 | J48: pliego iman 31x47 con iva | P48: ctp x chapa | Q48: =+Q37*$P$36 -> 960 | R48: =+R37*$P$36 -> 1200
B49: montado | F49: 0.0477419 | I49: =F49*F2 -> 66.83866 | J49: =I47+H48+I49 -> 1131.7467 | P49: millar | Q49: =+Q38*$P$36 -> 1200 | R49: =+R38*$P$36 -> 1680
A50: COLA IMAN | B50: QM-175 3 .10 U$/kg | C50: tacho kg | D50: 22 | F50: 3.2 | G50: rinde | H50: 4000 | I50: =D50*F50/H50*F2 -> 24.64 | P50: postura sin millar | Q50: =+Q39*$P$36 -> 2160 | R50: =+R39*$P$36 -> 2880
B51: TINTA | C51: kg | F51: 7.14
B52: CHAPAS 72x52 | C52: c/u | D52: DLT | F52: 5.54347 | H52: =F52*H2 -> 6.7075987 | I52: =H52*F2 -> 9390.6382 | P52: 4 chapas | Q52: =Q48*4 -> 3840 | R52: =R48*4 -> 4800
D53: MARCOUX | F53: 5.235 | H53: =F53*H2 -> 6.33435 | I53: =H53*F2 -> 8868.09 | P53: 8 chapas | Q53: =Q48*8 -> 7680 | R53: =R48*8 -> 9600
P55: 4/0 x 1000 | Q55: =Q50+Q49+Q52 -> 7200 | R55: =R50+R49+R52 -> 9360
C56: cm | I56: cm lineal | J56: digital | P56: 4/0 x 2500 | Q56: =Q49*3+Q50+Q52 -> 9600 | R56: =R49*3+R50+R52 -> 12720
A57: bobina | B57: 55 cm, | C57: 300000 | D57: 600000 | F57: 147 | H57: =F57*'[1]PAPEL US$'!F2*'[1]PAPEL US$'!H2 -> #REF! | I57: =H57/C57 -> #REF! | J57: =I57*L57 -> #REF! | K57: offset | L57: 72 | P57: 4/0 x 5000 | Q57: =Q49*5+Q50+Q52 -> 12000 | R57: =R48*4+R49*5+R50 -> 16080
B58: 50 cm | C58: 300000 | D58: 133 | F58: 133 | H58: =F58*'[1]PAPEL US$'!F2*'[1]PAPEL US$'!H2 -> #REF! | I58: =H58/C58 -> #REF! | J58: =I58*L58 -> #REF! | K58: digital | L58: 33
B59: 73 cm | C59: 300000 | P59: 4/4 x 1000 | Q59: =Q55*2 -> 14400 | R59: =R55*2 -> 18720
D60: total de cm2 | E60: $ cm2 | F60: 0.33 | H60: total $ | I60: IVA | K60: 202 | P60: 4/4 x 2500 | Q60: =Q56*2 -> 19200 | R60: =R56*2 -> 25440
B61: 0.52 | C61: 3000 | D61: =B61*C61 -> 1560 | E61: 0.27 | F61: =C61/F60 -> 9090.9091 | H61: =D61*E61 -> 421.2 | I61: =H61*H2 -> 509.652 | J61: =I61/F61 -> 0.05606172 | K61: =K60*J61 -> 11.324467 | P61: 4/4 x 5000 | Q61: =Q57*2 -> 24000 | R61: =R57*2 -> 32160
P64: 21.5 | Q64: 59125
P66: 23000
M67: ctp/postura/millar/laminado | P67: 73000
M68: iman | P68: 7000
M69: montado/cola | P69: 7000
M70: troquelado/ postura / cortante | P70: =SUM(P66:P69) -> 110000
P71: 11000
O72: 0.1 | P72: =SUM(P70:P71) -> 121000

Sheet Hoja2
B1: 10x17 | C1: 7 posturas | D1: 7 | E1: ringwire | F1: 160 | G1: cartu | H1: 300 | I1: 1 | K1: 1.1
F2: base sin laminar | G2: base 4/0 | H2: 1 | I2: total con armado | J2: c/u | K2: c/u
B3: 150 grs | C3: 6 | D3: =Bajadas!L8*C3 -> 477333.6 | E3: =F1*D1 -> 1120 | F3: =H1*D1 -> 2100 | H3: =SUM(D3:F3) -> 480553.6 | I3: =H3*I1 -> 480553.6 | J3: =I3/D1 -> 68650.515 | K3: =I3/D1*K1 -> 75515.566 | L3: =Bajadas!C10 -> 173178.02
C4: 7 | D4: =Bajadas!L8*C4 -> 556889.2 | E4: =F1*D$1 -> 1120 | F4: =H1*D1 -> 2100 | H4: =SUM(D4:F4) -> 560109.2 | I4: =H4*I1 -> 560109.2 | J4: =I4/D1 -> 80015.6 | K4: =I4/D1*K1 -> 88017.16 | L4: =Bajadas!C10 -> 173178.02
C5: 12 | D5: =Bajadas!L8*C5 -> 954667.2 | E5: =F1*D$1 -> 1120 | F5: =H1*D1 -> 2100 | H5: =SUM(D5:F5) -> 957887.2 | I5: =H5*I1 -> 957887.2 | J5: =I5/D1 -> 136841.03 | K5: =I5/D1*K1 -> 150525.13 | L5: =Bajadas!C10 -> 173178.02
C6: 13 | D6: =Bajadas!L8*C6 -> 1034222.8 | E6: =F1*D$1 -> 1120 | F6: =H1*D1 -> 2100 | H6: =SUM(D6:F6) -> 1037442.8 | I6: =H6*I1 -> 1037442.8 | J6: =I6/D1 -> 148206.11 | K6: =I6/D1*K1 -> 163026.73 | L6: =Bajadas!C10 -> 173178.02
B10: 10x17 | C10: 7 posturas | D10: 7 | E10: ringwire | F10: 160 | G10: cartu | H10: 300 | I10: 1 | K10: 1.1
F11: base sin laminar | G11: base 4/0 | H11: 1 | I11: total con armado | J11: c/u | K11: c/u
B12: 300 | C12: 6 | D12: =Bajadas!H8*C12 -> 951584.25 | E12: =F10*D10 -> 1120 | F12: =H10*D10 -> 2100 | H12: =SUM(D12:F12) -> 954804.25 | I12: =H12*I10 -> 954804.25 | J12: =I12/D10 -> 136400.61 | K12: =I12/D10*K10 -> 150040.67 | L12: =Bajadas!C19 -> 179149.68
C13: 7 | D13: =Bajadas!H8*C13 -> 1110181.6 | E13: =F10*D$1 -> 1120 | F13: =H10*D10 -> 2100 | H13: =SUM(D13:F13) -> 1113401.6 | I13: =H13*I10 -> 1113401.6 | J13: =I13/D10 -> 159057.38 | K13: =I13/D10*K10 -> 174963.11 | L13: =Bajadas!C19 -> 179149.68
C14: 12 | D14: =Bajadas!H8*C14 -> 1903168.5 | E14: =F10*D$1 -> 1120 | F14: =H10*D10 -> 2100 | H14: =SUM(D14:F14) -> 1906388.5 | I14: =H14*I10 -> 1906388.5 | J14: =I14/D10 -> 272341.22 | K14: =I14/D10*K10 -> 299575.34 | L14: =Bajadas!C19 -> 179149.68
C15: 13 | D15: =Bajadas!H8*C15 -> 2061765.9 | E15: =F10*D$1 -> 1120 | F15: =H10*D10 -> 2100 | H15: =SUM(D15:F15) -> 2064985.9 | I15: =H15*I10 -> 2064985.9 | J15: =I15/D10 -> 294997.98 | K15: =I15/D10*K10 -> 324497.78 | L15: =Bajadas!C19 -> 179149.68
B17: 10x17 | C17: 4 posturas | D17: 4 | E17: ringwire | F17: 160 | G17: cartu | H17: 300 | I17: 1 | K17: 1.1
F18: base sin laminar | G18: base 4/0 | H18: 1 | I18: total con armado | J18: c/u | K18: c/u
B19: 150 grs | C19: 6 | D19: =Bajadas!L8*C19 -> 477333.6 | E19: =F17*D17 -> 640 | F19: =H17*D17 -> 1200 | H19: =SUM(D19:F19) -> 479173.6 | I19: =H19*I17 -> 479173.6 | J19: =I19/D17 -> 119793.4 | K19: =I19/D17*K17 -> 131772.74 | L19: =Bajadas!C26 -> 295757.84
C20: 7 | D20: =Bajadas!L8*C20 -> 556889.2 | E20: =F17*D17 -> 640 | F20: =H17*D17 -> 1200 | H20: =SUM(D20:F20) -> 558729.2 | I20: =H20*I17 -> 558729.2 | J20: =I20/D17 -> 139682.3 | K20: =I20/D17*K17 -> 153650.53 | L20: =Bajadas!C26 -> 295757.84
C21: 12 | D21: =Bajadas!L8*C21 -> 954667.2 | E21: =F17*D17 -> 640 | F21: =H17*D17 -> 1200 | H21: =SUM(D21:F21) -> 956507.2 | I21: =H21*I17 -> 956507.2 | J21: =I21/D17 -> 239126.8 | K21: =I21/D17*K17 -> 263039.48 | L21: =Bajadas!C26 -> 295757.84
C22: 13 | D22: =Bajadas!L8*C22 -> 1034222.8 | E22: =F17*D17 -> 640 | F22: =H17*D17 -> 1200 | H22: =SUM(D22:F22) -> 1036062.8 | I22: =H22*I17 -> 1036062.8 | J22: =I22/D17 -> 259015.7 | K22: =I22/D17*K17 -> 284917.27 | L22: =Bajadas!C26 -> 295757.84
B26: 10x17 | C26: 4 posturas | D26: 4 | E26: ringwire | F26: 160 | G26: cartu | H26: 300 | I26: 1 | K26: 1.1
F27: base sin laminar | G27: base 4/0 | H27: 1 | I27: total con armado | J27: c/u | K27: c/u
B28: 150 grs | C28: 6 | D28: =Bajadas!H8*C28 -> 951584.25 | E28: =F26*D26 -> 640 | F28: =H26*D26 -> 1200 | H28: =SUM(D28:F28) -> 953424.25 | I28: =H28*I26 -> 953424.25 | J28: =I28/D26 -> 238356.06 | K28: =I28/D26*K26 -> 262191.67 | L28: =Bajadas!C35 -> 121797.36
C29: 7 | D29: =Bajadas!H8*C29 -> 1110181.6 | E29: =F26*D26 -> 640 | F29: =H26*D26 -> 1200 | H29: =SUM(D29:F29) -> 1112021.6 | I29: =H29*I26 -> 1112021.6 | J29: =I29/D26 -> 278005.41 | K29: =I29/D26*K26 -> 305805.95 | L29: =Bajadas!C35 -> 121797.36
C30: 12 | D30: =Bajadas!H8*C30 -> 1903168.5 | E30: =F26*D26 -> 640 | F30: =H26*D26 -> 1200 | H30: =SUM(D30:F30) -> 1905008.5 | I30: =H30*I26 -> 1905008.5 | J30: =I30/D26 -> 476252.13 | K30: =I30/D26*K26 -> 523877.34 | L30: =Bajadas!C35 -> 121797.36
C31: 13 | D31: =Bajadas!H8*C31 -> 2061765.9 | E31: =F26*D26 -> 640 | F31: =H26*D26 -> 1200 | H31: =SUM(D31:F31) -> 2063605.9 | I31: =H31*I26 -> 2063605.9 | J31: =I31/D26 -> 515901.47 | K31: =I31/D26*K26 -> 567491.62 | L31: =Bajadas!C35 -> 121797.36

Sheet Adicionales
F3: Puntas redondas | I3: Agujereado | L3: Trazado 1/2 flejeS | O3: Puntillado 1 fleje | R3: Troquelado postura primer millar
F4: Cantidad | G4: Precio | I4: Cantidad | J4: Precio | L4: Cantidad | M4: Precio | O4: Cantidad | P4: Precio | R4: Cantidad | S4: Precio
F5: 1 a 100 | G5: 35 | I5: 1 a 100 | J5: 35 | L5: 1 a 50 | M5: 140 | O5: 1 a 50 | P5: 160 | R5: 1 a 50 | S5: 220
F6: 101 a 250 | G6: 50 | I6: 101 a 250 | J6: 50 | L6: 51 a 100 | M6: 200 | O6: 51 a 100 | P6: 220 | R6: 51 a 100 | S6: 250
F7: 251 a 500 | G7: 70 | I7: 251 a 500 | J7: 70 | L7: 101 a 250 | M7: 240 | O7: 101 a 250 | P7: 260 | R7: 101 a 250 | S7: 290
F8: 501 a 1000 | G8: 130 | I8: 501 a 1000 | J8: 130 | L8: 251 a 500 | M8: 260 | O8: 251 a 500 | P8: 280 | R8: 251 a 500 | S8: 320
F9: * Tiempo de producción + 24 hs | I9: * Tiempo de producción + 24 hs | L9: 501 a 1000 | M9: 300 | O9: 501 a 1000 | P9: 375 | R9: 501 a 1000 | S9: 485
L10: * Tiempo de producción + 24 a 48 hs | O10: * Tiempo de producción + 24 a 48 hs | R10: * Millar adicional: $200
L11: 2 FLEJES EN PARALELO | R11: * Cortantes desde $400
J12: =130*10 -> 1300 | L12: Tamaño máximo de pliego XA3 | R12: * Consultar por cortantes disponibles. Uso de cortante existente $50.
R13: * Tiempo de producción + 48 - 72hs
G14: ADICIONAL TRABAJO EXPRESS + 40%
F19: DOBLADO DÍPTICO | I19: DOBLADO TRIPTICO | M19: NUMERADO | N19: costo por bajada
F20: Cantidad | G20: Precio | I20: Cantidad | J20: Precio | M20: 0 a 1 | N20: 5
F21: 1 a 100 | G21: 150 | I21: 1 a 100 | J21: 190 | M21: 2 a 10 | N21: 4
F22: 101 a 250 | G22: 180 | I22: 101 a 250 | J22: 220 | M22: 11 a 50 | N22: 3.25
F23: 251 a 500 | G23: 210 | I23: 251 a 500 | J23: 250 | M23: 51 a 100 | N23: 3
F24: 501 a 1000 | G24: 230 | I24: 501 a 1000 | J24: 275 | M24: 101 a 250 | N24: 2.5
F25: Hasta 150g | M25: 251 a 500 | N25: 2.2
F26: Tiempo de producción +24 a 48hs | M26: 501 a 1000 | N26: 2
F28: AGREGAR DETALLE DE TIPOS DE DOBLADOS
F33: s111
G34: Plancha troquelada | S34: Impresión quinto color
G35: Area disponible 29x44 cm | S35: pasada
G36: No incluye costo de impresión | S36: por lado x hoja
H37: Tamaño de cada troquelado | N37: A3 PLUS | O37: OPP blco o blanco
G38: Cantidad | H38: hasta 3x3 cm | I38: hasta 5x5 cm | J38: Hasta 10x10 cm | K38: Hasta 29x44 cm | N38: 32x47 cm | O38: 4/0 | P38: 4/0 + blanco | Q38: blanco | S38: Cantidad | T38: Precio por lado
G39: 1 | H39: 21.5 | I39: 19 | J39: 16 | K39: 14 | N39: 1 | O39: 19.6 | P39: 31.6 | Q39: 22 | S39: 1 | T39: 12
G40: 2 a 5 | H40: 18 | I40: 16 | J40: 14 | K40: 10 | N40: 2 a 25 | O40: 17.8 | P40: 28 | Q40: 17 | S40: 2 a 5 | T40: 10
G41: 6 a 25 | H41: 16 | I41: 14 | J41: 11 | K41: 6.5 | N41: 26 a 50 | O41: 16.9 | P41: 25 | Q41: 15 | S41: 6 a 25 | T41: 9
G42: 26 a 50 | H42: 12.5 | I42: 9.5 | J42: 7 | K42: 4 | N42: 51 a 100 | O42: 16.75 | P42: 23.75 | Q42: 13.5 | S42: 26 a 50 | T42: 8
G43: 51 a 100 | H43: 9.5 | I43: 7 | J43: 5 | K43: 3 | N43: 101 a 300 | O43: 16.6 | P43: 22.6 | Q43: 12 | S43: 51 a 100 | T43: 7
G44: 101 a 500 | H44: 5 | I44: 4 | J44: 3 | K44: 2 | N44: 301 a 500 | O44: 16.45 | P44: 22.45 | Q44: 11 | S44: 101 a 500 | T44: 6
G45: Tiempo de producción 48 - 72hs | N45: 501 a 1000 | O45: 16.3 | P45: 21 | Q45: 10 | S45: 501 a 1000 | T45: 5
G46: Penalización por alta complejidad +10% (a evaluación de Promo directa)
S48: Envarillado metalico
N49: TAPAS PARA ENCUADERNACION
T50: Precio por unid
N51: negro | S51: Cantidad | T51: hasta 46 cm
N52: cristal | S52: 1 | T52: 10
S53: 2 a 5 | T53: 5
S54: 6 a 25 | T54: 3.5
S55: 26 a 50 | T55: 3
S56: 51 a 100 | T56: 2.5
S57: 101 a 500 | T57: 2.3
S58: 501 a 1000 | T58: 1.8

Sheet carpetas
B1: 46 | C1: 39 | D1: =B1*C1 -> 1794
H2: 0.75
A3: A4 | B3: SIN LAMINAR O LAMINADAS BRILLO | E3: LAMINADAS | H3: PREMIUM | J3: DELUXE
B4: 4/0 | C4: 4/1 | D4: 4/4 | E4: 4/0 | F4: 4/1 | G4: 4/4 | H4: 4/0 | I4: 4/4 | J4: 4/0 | K4: 4/4
A5: 500 | B5: =(D1*B8)+E8+F8 -> 506094.82 | C5: =(D1*C8)+E8+F8 -> 548917.6 | D5: =(D1*D8)+E8+F8 -> 564346 | E5: =(D1*B8)+E8+$F$8 -> 506094.82 | F5: =(D1*C8)+E8+$F$8 -> 548917.6 | G5: =(D1*D8)+F8+$E$8 -> 564346 | H5: =I5*H2 -> 583871.83 | I5: =(D1*H8)+F8+$E$8 -> 778495.78 | J5: =(D1*J8)+F8+$E$8 -> 1075546.3 | K5: =(D1*K8)+F8+$E$8 -> 1233777.1
A6: 1000 | B6: =(D1*B9)+E9+F9 -> 805027.8 | C6: =(D1*C9)+E9+F9 -> 902370.24 | D6: =(D1*D9)+E9+F9 -> 902370.24 | E6: =(D1*B9)+E9+$F$9 -> 805027.8 | F6: =(D1*C9)+E9+$F$9 -> 902370.24 | G6: =(D1*D9)+F9+$E$9 -> 902370.24 | H6: =I6*H2 -> 816292.57 | I6: =(D1*H9)+F9+$E$9 -> 1088390.1 | J6: =(D1*J9)+F9+$E$9 -> 1358010.4 | K6: =(D1*K9)+F9+$E$9 -> 1554973.6
E7: troquelado | F7: pegado
A8: 500 | B8: 276.53 | C8: 300.4 | D8: 309 | E8: 5000 | F8: 5000 | H8: 428.37 | J8: 593.95 | K8: 682.15
A9: 1000 | B9: 438.7 | C9: 492.96 | D9: 492.96 | E9: 8000 | F9: 10000 | H9: 596.65 | J9: 746.94 | K9: 856.73
B12: 48 | C12: 45 | D12: =B12*C12 -> 2160
A14: OFICIO | B14: SIN LAMINAR | E14: LAMINADAS | H14: PREMIUM | J14: DELUXE
B15: 4/0 | C15: 4/1 | D15: 4/4 | E15: 4/0 | F15: 4/1 | G15: 4/4 | H15: 4/0 | I15: 4/4 | J15: 4/0 | K15: 4/4
A16: 500 | B16: =(D12*B19)+E19+F19 -> 607304.8 | C16: =(D12*C19)+E19+F19 -> 658864 | D16: =(D12*D19)+E19+F19 -> 677440 | E16: =(D12*B19)+E19+$F$8 -> 607304.8 | F16: =(D12*C19)+E19+$F$8 -> 658864 | G16: =(D12*D19)+F19+$E$8 -> 677440 | H16: =I16*H2 -> 701459.4 | I16: =(D12*H19)+F19+$E$8 -> 935279.2 | J16: =(D12*J19)+F19+$E$8 -> 1292932 | K16: =(D12*K19)+F19+$E$8 -> 1483444
A17: 1000 | B17: =(D12*B20)+E20+F20 -> 965592 | C17: =(D12*C20)+E20+F20 -> 1082793.6 | D17: =(D12*D20)+E20+F20 -> 1082793.6 | E17: =(D12*B20)+E20+$F$9 -> 965592 | F17: =(D12*C20)+E20+$F$9 -> 1082793.6 | G17: =(D12*D20)+F20+$E$9 -> 1082793.6 | H17: =I17*H2 -> 980073 | I17: =(D12*H20)+F20+$E$9 -> 1306764 | J17: =(D12*J20)+F20+$E$9 -> 1631390.4 | K17: =(D12*K20)+F20+$E$9 -> 1868536.8
E18: troquelado | F18: pegado
A19: 500 | B19: 276.53 | C19: 300.4 | D19: 309 | E19: 5000 | F19: 5000 | H19: 428.37 | J19: 593.95 | K19: 682.15
A20: 1000 | B20: 438.7 | C20: 492.96 | D20: 492.96 | E20: 8000 | F20: 10000 | H20: 596.65 | J20: 746.94 | K20: 856.73
R23: =Laminado!C6 -> brillo | S23: =Laminado!D6 -> mate | T23: =Laminado!E6 -> Laca UV
R24: =Laminado!C7 -> 163.51525 | S24: =Laminado!D7 -> 189.67768 | T24: =Laminado!E7 -> 136.2627
R25: =Laminado!C8 -> 151.2516 | S25: =Laminado!D8 -> 175.45186 | T25: =Laminado!E8 -> 126.043
B26: 1130.4709 | C26: 1313.1882 | D26: 1476.594 | E26: 1884.1181 | F26: 2188.647 | G26: 2460.99 | H26: 3079.9513 | I26: 4246.0743 | R26: =Laminado!C9 -> 138.98796 | S26: =Laminado!D9 -> 161.22603 | T26: =Laminado!E9 -> 115.8233
B27: 1744.7948 | C27: 2093.7537 | D27: 2257.9697 | E27: 2907.9913 | F27: 3489.5896 | G27: 3763.2829 | H27: 3622.1613 | I27: 5092.8133 | K27: 98.043465 | L27: 112.60143 | M27: 123.29708 | N27: 141.42027 | R27: =Laminado!C10 -> 126.72432 | S27: =Laminado!D10 -> 147.00021 | T27: =Laminado!E10 -> 105.6036
B28: 42.04645 | C28: 48.858333 | D28: 50.21549 | E28: 70.077416 | F28: 81.430555 | G28: 83.692484 | H28: 78.761584 | I28: 110.2989 | R28: =Laminado!C11 -> 118.54855 | S28: =Laminado!D11 -> 137.51632 | T28: =Laminado!E11 -> 98.790461
B29: 39.60956 | C29: 46.766733 | D29: 48.139341 | E29: 66.015933 | F29: 77.944555 | G29: 80.232236 | H29: 73.205787 | I29: 101.9652 | R29: =Laminado!C12 -> 110.37279 | S29: =Laminado!D12 -> 128.03244 | T29: =Laminado!E12 -> 91.977326
R30: =Laminado!C13 -> 102.19703 | S30: =Laminado!D13 -> 118.54855 | T30: =Laminado!E13 -> 85.16419
A31: DIGITAL | S31: entran
A32: Cantidad | B32: Sin laminar | D32: Laca UV | F32: Laminado Brillo | H32: Laminado Mate | J32: Solapa | P32: solapa | Q32: 6
B33: 4/0 | C33: 4/4 | D33: 4/0 | E33: 4/4 | F33: 4/0 | G33: 4/4 | H33: 4/0 | I33: 4/4 | J33: impresa | M33: troquealdo | N33: =troquelados!Y44 -> MEDIO | P33: hoja A3 | Q33: =Bajadas!AB4 -> 141513.37 | R33: =(N34+Q33)/Q32 -> 23653.162
A34: =Bajadas!B4 -> 1 | B34: =(Q34+P34)*S34 -> 375150.21 | C34: =(R34+P34)*S34 -> 375539.23 | D34: =B34+T24 -> 375286.47 | E34: =C34+T24 -> 375675.49 | F34: =B34+R24 -> 375313.72 | G34: =C34+R24 -> 375702.75 | H34: =B34+S24 -> 375339.88 | I34: =C34+S24 -> 375728.91 | J34: =(N34+Q34)/Q32 -> 37808.763 | M34: =troquelados!W45 -> 1 a 2 | N34: =troquelados!Y45 -> 405.6 | P34: =(Q33+N34)/Q32 -> 23653.162 | Q34: =Bajadas!E4 -> 226446.98 | R34: =Bajadas!F4 -> 226706.33 | S34: 1.5
A35: =Bajadas!B5 -> 2 a 25 | B35: =(Q35+P35)*S35 -> 307718.51 | C35: =(R35+P35)*S35 -> 308034.1 | D35: =B35+T25 -> 307844.56 | E35: =C35+T25 -> 308160.15 | F35: =B35+R25 -> 307869.77 | G35: =C35+R25 -> 308185.35 | H35: =B35+S25 -> 307893.97 | I35: =C35+S25 -> 308209.55 | J35: =(N35+Q35)/Q32 -> 33829.863 | M35: =troquelados!W46 -> 3 a 9 | N35: =troquelados!Y46 -> 368.72727 | P35: =R33 -> 23653.162 | Q35: =Bajadas!E5 -> 202610.45 | R35: =Bajadas!F5 -> 202842.5 | S35: 1.36
A36: =Bajadas!B6 -> 26 a 50 | B36: =(Q36+P36)*S36 -> 290801.92 | C36: =(R36+P36)*S36 -> 291099.21 | D36: =B36+T26 -> 290917.74 | E36: =C36+T26 -> 291215.04 | F36: =B36+R26 -> 290940.91 | G36: =C36+R26 -> 291238.2 | H36: =B36+S26 -> 290963.14 | I36: =C36+S26 -> 291260.44 | J36: =(N36+Q36)/Q32 -> 32831.088 | M36: =troquelados!W47 -> 10 a 25 | N36: =troquelados!Y47 -> 335.20661 | P36: =R33 -> 23653.162 | Q36: =Bajadas!E6 -> 196651.32 | R36: =Bajadas!F6 -> 196876.55 | S36: 1.32
A37: =Bajadas!B7 -> 51 a 100 | B37: =(Q37+P37)*S37 -> 274362.05 | C37: =(R37+P37)*S37 -> 274641.6 | D37: =B37+T27 -> 274467.65 | E37: =C37+T27 -> 274747.21 | F37: =B37+R27 -> 274488.77 | G37: =C37+R27 -> 274768.33 | H37: =B37+S27 -> 274509.05 | I37: =C37+S27 -> 274788.6 | J37: =(N37+Q37)/Q32 -> 31832.821 | M37: =troquelados!W48 -> 26 a 50 | N37: =troquelados!Y48 -> 304.73328 | P37: =R33 -> 23653.162 | Q37: =Bajadas!E7 -> 190692.19 | R37: =Bajadas!F7 -> 190910.59 | S37: 1.28
A38: =Bajadas!B8 -> 101 a 300 | B38: =(Q38+P38)*S38 -> 258398.91 | C38: =(R38+P38)*S38 -> 258661.27 | D38: =B38+T28 -> 258497.7 | E38: =C38+T28 -> 258760.06 | F38: =B38+R28 -> 258517.46 | G38: =C38+R28 -> 258779.82 | H38: =B38+S28 -> 258536.43 | I38: =C38+S28 -> 258798.78 | J38: =(N38+Q38)/Q32 -> 30835.015 | M38: =troquelados!W49 -> 51 a 100 | N38: =troquelados!Y49 -> 277.03026 | P38: =R33 -> 23653.162 | Q38: =Bajadas!E8 -> 184733.06 | R38: =Bajadas!F8 -> 184944.63 | S38: 1.24
A39: =Bajadas!B9 -> 301 a 500 | B39: =(Q39+P39)*S39 -> 242912.51 | C39: =(R39+P39)*S39 -> 243158.21 | D39: =B39+T29 -> 243004.49 | E39: =C39+T29 -> 243250.19 | F39: =B39+R29 -> 243022.88 | G39: =C39+R29 -> 243268.58 | H39: =B39+S29 -> 243040.54 | I39: =C39+S29 -> 243286.24 | J39: =(N39+Q39)/Q32 -> 29837.629 | M39: =troquelados!W50 -> mas de 100 | N39: =troquelados!Y50 -> 251.84569 | P39: =R33 -> 23653.162 | Q39: =Bajadas!E9 -> 178773.93 | R39: =Bajadas!F9 -> 178978.68 | S39: 1.2
A40: =Bajadas!B10 -> 501 a 1000 | B40: =(Q40+P40)*S40 -> 227902.83 | C40: =(R40+P40)*S40 -> 228132.43 | D40: =B40+T30 -> 227988 | E40: =C40+T30 -> 228217.59 | F40: =B40+R30 -> 228005.03 | G40: =C40+R30 -> 228234.62 | H40: =B40+S30 -> 228021.38 | I40: =C40+S30 -> 228250.97 | J40: =(N40+Q40)/Q32 -> 28844.466 | M40: =troquelados!W51 | N40: 252 | P40: =R33 -> 23653.162 | Q40: =Bajadas!E10 -> 172814.8 | R40: =Bajadas!F10 -> 173012.72 | S40: 1.16

Sheet Productos
A1: pliego 32x47 | AF1: 0.8333 | AG1: 0.8333 | AH1: 0.8333 | AI1: 0.8333 | AJ1: 0.8333 | AK1: 0.8333 | AL1: 0.8333 | AM1: 0.8333 | AO1: dólar | AP1: 240 | AY1: 240 | AZ1: 0.7 | BA1: 1.1 | BB1: 1 | BC1: 1.2666 | BD1: 1.136 | BE1: 1.15 | BF1: 1.18 | BG1: 1.05
A2: impresión digital | AF2: 1.04 | AG2: 1.04 | AH2: 1.04 | AI2: 1.04 | AJ2: 1.04 | AK2: 1.04 | AL2: 1.04 | AM2: 1.04 | AZ2: 9x2,5 | BA2: =BB10*AZ1/AY1 -> 3041.3855 | BB2: 1.75 | BC2: 1.75 | BD2: 1.75
AF3: 1.458 | AG3: 1.458 | AH3: 1.458 | AI3: 1.458 | AJ3: 1.458 | AK3: 1.458 | AL3: 1.458 | AM3: 1.458 | AZ3: 9x5 | BA3: =BB10*BB1/AY1 -> 4344.8365 | BB3: 2.5 | BC3: 2.5 | BD3: 2.5
A4: Tarjetas | AF4: 2.08 | AG4: 2.08 | AH4: 2.08 | AI4: 2.08 | AJ4: 2.08 | AK4: 2.08 | AL4: 2.08 | AM4: 2.08 | AZ4: 8,5x5,5 | BA4: =BB10*BA1/AY1 -> 4779.3201 | BB4: 4 | BC4: 4 | BD4: 4
A5: Tiempo de producción | AF5: 3.33 | AG5: 3.33 | AH5: 3.33 | AI5: 3.33 | AJ5: 3.33 | AK5: 3.33 | AL5: 3.33 | AM5: 3.33 | AO5: 300 | BB5: 7.5 | BC5: 7.5 | BD5: 7.5 | BO5: impresión
A6: Papel ilustración 300g | BA6: Tamaño 9x5 | BO6: costo sobre | BP6: 1.6 | BQ6: 1.6 | BR6: 2 | BS6: 2 | BT6: 1.8 | BU6: 1.8 | BV6: 0.7 | BW6: 0.7
A7: Tamaño 9x5 | D7: cantidad de bajadas - 24 x ´postura | L7: costo de impresión x bajada | V7: costo de laminado | AE7: costo de corte | BA7: 1.2 | BB7: 1.2 | BC7: 1.2 | BD7: 1.2 | BE7: 1.2 | BF7: 1.2 | BG7: 1.2 | BH7: 1.2 | BI7: 1.2 | BO7: Cantidad | BP7: Sobre Bolsa | BR7: Sobre bolsa | BT7: Sobre bolsa | BV7: Oficio Ingles | BZ7: Sobre Bolsa A4 | CB7: Sobre bolsa | CD7: Sobre bolsa | CF7: Oficio Ingles
A8: Cantidad | B8: Sin laminar | D8: Laca UV | F8: Laminado brillo | H8: Laminado mate | K8: Cantidad | L8: Sin laminar | N8: Laca UV | P8: Laminado brillo | R8: Laminado mate | U8: Cantidad | V8: Sin laminar | X8: Laca UV | Z8: Laminado brillo | AB8: Laminado mate | AE8: Cantidad | AF8: Sin laminar | AH8: Laca UV | AJ8: Laminado brillo | AL8: Laminado mate | AO8: Tarjetas | AP8: Sin laminar | AR8: Laca UV | AT8: Laminado brillo | AV8: Laminado mate | AZ8: 1.2 | BA8: Tarjetas | BB8: Sin laminar | BD8: Laca UV | BF8: Laminado brillo | BH8: Laminado mate | BJ8: Laminado soft touch | BL8: Sectorizado o blanco | BO8: Tamaño | BP8: 22,9x32,4 | BR8: 27x37 | BT8: 25x35,3 | BV8: 12x23,5 | BY8: Tamaño | BZ8: 22,9x32,4 | CB8: 27x37 | CD8: 25x35,3 | CF8: 12x23,5
A9: Tarjetas | B9: 4/0 | C9: 4/4 | D9: 4/0 | E9: 4/4 | F9: 4/0 | G9: 4/4 | H9: 4/0 | I9: 4/4 | K9: Tarjetas | L9: 4/0 | M9: 4/4 | N9: 4/0 | O9: 4/4 | P9: 4/0 | Q9: 4/4 | R9: 4/0 | S9: 4/4 | U9: Tarjetas | V9: 4/0 | W9: 4/4 | X9: 4/0 | Y9: 4/4 | Z9: 4/0 | AA9: 4/4 | AB9: 4/0 | AC9: 4/4 | AE9: Tarjetas | AF9: 4/0 | AG9: 4/4 | AH9: 4/0 | AI9: 4/4 | AJ9: 4/0 | AK9: 4/4 | AL9: 4/0 | AM9: 4/4 | AO9: Cantidad | AP9: 4/0 | AQ9: 4/4 | AR9: 4/0 | AS9: 4/4 | AT9: 4/0 | AU9: 4/4 | AV9: 4/0 | AW9: 4/4 | AZ9: 1.2 | BA9: Cantidad | BB9: 4/0 | BC9: 4/4 | BD9: 4/0 | BE9: 4/4 | BF9: 4/0 | BG9: 4/4 | BH9: 4/0 | BI9: 4/4 | BJ9: 4/0 | BK9: 4/4 | BL9: 4/0 | BM9: 4/4 | BP9: 4/0 | BQ9: 4/4 | BR9: 4/0 | BS9: 4/4 | BT9: 4/0 | BU9: 4/4 | BV9: 4/0 | BW9: 4/4 | BY9: Cantidad | BZ9: 4/0 | CA9: 4/4 | CB9: 4/0 | CC9: 4/4 | CD9: 4/0 | CE9: 4/4 | CF9: 4/0 | CG9: 4/4
A10: 100 | B10: 5 | C10: 5 | D10: 5 | E10: 5 | F10: 5 | G10: 5 | H10: 5 | I10: 5 | K10: 100 | L10: =Bajadas!$G$5 -> 173713.46 | M10: =Bajadas!$H$5 -> 173945.51 | N10: =Bajadas!$G$5 -> 173713.46 | O10: =Bajadas!$H$5 -> 173945.51 | P10: =Bajadas!$G$5 -> 173713.46 | Q10: =Bajadas!$H$5 -> 173945.51 | R10: =Bajadas!$G$5 -> 173713.46 | S10: =Bajadas!$H$5 -> 173945.51 | U10: 100 | X10: =Laminado!J7 -> 136.2627 | Z10: =Laminado!C7 -> 163.51525 | AB10: =Laminado!C7 -> 163.51525 | AC10: =Laminado!C7*2 -> 327.03049 | AE10: 100 | AF10: 400 | AG10: 400 | AH10: 400 | AI10: 400 | AJ10: 400 | AK10: 400 | AL10: 400 | AM10: 400 | AO10: 100 | AP10: =(B10*L10)+V10*B10+AF10 -> 868967.29 | AQ10: =(C10*M10)+W10*C10+AG10 -> 870127.54 | AR10: =(D10*N10)+X10*D10+AH10 -> 869648.61 | AS10: =(E10*O10)+X10*E10+AI10 -> 870808.86 | AT10: =(F10*P10)+Z10*F10+AJ10 -> 869784.87 | AU10: =(E10*Q10)+Z10*E10+AK10 -> 870945.12 | AV10: =(H10*R10)+AB10*H10+AL10 -> 869784.87 | AW10: =(I10*S10)+AC10*I10+AM10 -> 871762.7 | AZ10: 1.2 | BA10: 100 | BB10: =AP10*AZ8 -> 1042760.8 | BC10: =AQ10*AZ9 -> 1044153.1 | BD10: =AR10*AZ10 -> 1043578.3 | BE10: =AS10*AZ9 -> 1044970.6 | BF10: =AT10*AZ10 -> 1043741.8 | BG10: =AU10*AZ10 -> 1045134.1 | BH10: =AV10*AZ10 -> 1043741.8 | BI10: =AW10*AZ10 -> 1046115.2 | BJ10: 118 | BK10: 153 | BL10: =BH10*1.4 -> 1461238.6 | BM10: =BI10*1.4 -> 1464561.3 | BO10: 100 | BP10: 3 | BQ10: 6 | BR10: 3 | BS10: 6 | BT10: 3 | BU10: 6 | BV10: 3 | BW10: 6 | BY10: 100 | BZ10: =CEILING(BP10*BP$6,0.05) -> 4.8 | CA10: =CEILING(BQ10*BQ$6,0.05) -> 9.6 | CB10: =CEILING(BR10*BR$6,0.05) -> 6 | CC10: =CEILING(BS10*BS$6,0.05) -> 12 | CD10: =CEILING(BT10*BT$6,0.05) -> 5.4 | CE10: =CEILING(BU10*BU$6,0.05) -> 10.8 | CF10: =CEILING(BV10*BV$6,0.05) -> 2.1 | CG10: =CEILING(BW10*BW$6,0.05) -> 4.2
A11: 200 | B11: 9 | C11: 9 | D11: 9 | E11: 9 | F11: 9 | G11: 9 | H11: 9 | I11: 9 | K11: 200 | L11: =Bajadas!G5 -> 173713.46 | M11: =Bajadas!H5 -> 173945.51 | N11: =Bajadas!G5 -> 173713.46 | O11: =Bajadas!$H$5 -> 173945.51 | P11: =Bajadas!G5 -> 173713.46 | Q11: =Bajadas!H5 -> 173945.51 | R11: =Bajadas!$G$5 -> 173713.46 | S11: =Bajadas!$H$5 -> 173945.51 | U11: 200 | X11: =Laminado!J7 -> 136.2627 | Z11: =Laminado!C8 -> 151.2516 | AB11: =Laminado!C7 -> 163.51525 | AC11: =Laminado!C7*2 -> 327.03049 | AE11: 200 | AF11: 500 | AG11: 500 | AH11: 500 | AI11: 500 | AJ11: 500 | AK11: 500 | AL11: 500 | AM11: 500 | AO11: 200 | AP11: =(B11*L11)+V11*B11+AF11 -> 1563921.1 | AQ11: =(C11*M11)+W11*C11+AG11 -> 1566009.6 | AR11: =(D11*N11)+X11*D11+AH11 -> 1565147.5 | AS11: =(E11*O11)+X11*E11+AI11 -> 1567235.9 | AT11: =(F11*P11)+Z11*F11+AJ11 -> 1565282.4 | AU11: =(E11*Q11)+Z11*E11+AK11 -> 1567370.8 | AV11: =(H11*R11)+AB11*H11+AL11 -> 1565392.8 | AW11: =(I11*S11)+AC11*I11+AM11 -> 1568952.9 | AZ11: 1.2 | BA11: 200 | BB11: =AP11*AZ9 -> 1876705.4 | BC11: =AQ11*AZ10 -> 1879211.5 | BD11: =AR11*AZ11 -> 1878177 | BE11: =AS11*AZ10 -> 1880683.1 | BF11: =AT11*AZ11 -> 1878338.9 | BG11: =AU11*AZ11 -> 1880845 | BH11: =AV11*AZ11 -> 1878471.3 | BI11: =AW11*AZ11 -> 1882743.4 | BJ11: 211 | BK11: 276 | BL11: =BH11*1.4 -> 2629859.8 | BM11: =BI11*1.4 -> 2635840.8 | BO11: 200 | BP11: 2.9 | BQ11: 5.8 | BR11: 2.9 | BS11: 5.8 | BT11: 2.9 | BU11: 5.8 | BV11: 2.9 | BW11: 5.8 | BY11: 200 | BZ11: =CEILING(BP11*BP$6,0.05) -> 4.65 | CA11: =CEILING(BQ11*BQ$6,0.05) -> 9.3 | CB11: =CEILING(BR11*BR$6,0.05) -> 5.8 | CC11: =CEILING(BS11*BS$6,0.05) -> 11.6 | CD11: =CEILING(BT11*BT$6,0.05) -> 5.25 | CE11: =CEILING(BU11*BU$6,0.05) -> 10.45 | CF11: =CEILING(BV11*BV$6,0.05) -> 2.05 | CG11: =CEILING(BW11*BW$6,0.05) -> 4.1
A12: 300 | B12: 13 | C12: 13 | D12: 13 | E12: 13 | F12: 13 | G12: 13 | H12: 13 | I12: 13 | K12: 300 | L12: =Bajadas!G5 -> 173713.46 | M12: =Bajadas!H5 -> 173945.51 | N12: =Bajadas!G5 -> 173713.46 | O12: =Bajadas!$H$5 -> 173945.51 | P12: =Bajadas!G5 -> 173713.46 | Q12: =Bajadas!H5 -> 173945.51 | R12: =Bajadas!$G$5 -> 173713.46 | S12: =Bajadas!$H$5 -> 173945.51 | U12: 300 | X12: =Laminado!J9 -> 115.8233 | Z12: =Laminado!C9 -> 138.98796 | AB12: =Laminado!C8 -> 151.2516 | AC12: =Laminado!C8*2 -> 302.5032 | AE12: 300 | AF12: 700 | AG12: 700 | AH12: 700 | AI12: 700 | AJ12: 700 | AK12: 700 | AL12: 700 | AM12: 700 | AO12: 300 | AP12: =(B12*L12)+V12*B12+AF12 -> 2258975 | AQ12: =(C12*M12)+W12*C12+AG12 -> 2261991.6 | AR12: =(D12*N12)+X12*D12+AH12 -> 2260480.7 | AS12: =(E12*O12)+X12*E12+AI12 -> 2263497.3 | AT12: =(F12*P12)+Z12*F12+AJ12 -> 2260781.8 | AU12: =(E12*Q12)+Z12*E12+AK12 -> 2263798.5 | AV12: =(H12*R12)+AB12*H12+AL12 -> 2260941.2 | AW12: =(I12*S12)+AC12*I12+AM12 -> 2265924.2 | AZ12: 1.2 | BA12: 300 | BB12: =AP12*AZ10 -> 2710770 | BC12: =AQ12*AZ11 -> 2714389.9 | BD12: =AR12*AZ12 -> 2712576.8 | BE12: =AS12*AZ11 -> 2716196.8 | BF12: =AT12*AZ12 -> 2712938.2 | BG12: =AU12*AZ12 -> 2716558.1 | BH12: =AV12*AZ12 -> 2713129.5 | BI12: =AW12*AZ12 -> 2719109 | BJ12: 255 | BK12: 345 | BL12: =BH12*1.4 -> 3798381.3 | BM12: =BI12*1.4 -> 3806752.6 | BO12: 300 | BP12: 2.7 | BQ12: 5.5 | BR12: 2.7 | BS12: 5.5 | BT12: 2.7 | BU12: 5.5 | BV12: 2.7 | BW12: 5.5 | BY12: 300 | BZ12: =CEILING(BP12*BP$6,0.05) -> 4.35 | CA12: =CEILING(BQ12*BQ$6,0.05) -> 8.8 | CB12: =CEILING(BR12*BR$6,0.05) -> 5.4 | CC12: =CEILING(BS12*BS$6,0.05) -> 11 | CD12: =CEILING(BT12*BT$6,0.05) -> 4.9 | CE12: =CEILING(BU12*BU$6,0.05) -> 9.9 | CF12: =CEILING(BV12*BV$6,0.05) -> 1.9 | CG12: =CEILING(BW12*BW$6,0.05) -> 3.85
A13: 500 | B13: 21 | C13: 21 | D13: 21 | E13: 21 | F13: 21 | G13: 21 | H13: 21 | I13: 21 | K13: 500 | L13: =Bajadas!G5 -> 173713.46 | M13: =Bajadas!H5 -> 173945.51 | N13: =Bajadas!G5 -> 173713.46 | O13: =Bajadas!$H$5 -> 173945.51 | P13: =Bajadas!G5 -> 173713.46 | Q13: =Bajadas!H5 -> 173945.51 | R13: =Bajadas!$G$5 -> 173713.46 | S13: =Bajadas!$H$5 -> 173945.51 | U13: 500 | X13: =Laminado!J10 -> 105.6036 | Z13: =Laminado!C10 -> 126.72432 | AB13: =Laminado!C8 -> 151.2516 | AC13: =Laminado!C8*2 -> 302.5032 | AE13: 500 | AF13: 1000 | AG13: 1000 | AH13: 1000 | AI13: 1000 | AJ13: 1000 | AK13: 1000 | AL13: 1000 | AM13: 1000 | AO13: 500 | AP13: =(B13*L13)+V13*B13+AF13 -> 3648982.6 | AQ13: =(C13*M13)+W13*C13+AG13 -> 3653855.7 | AR13: =(D13*N13)+X13*D13+AH13 -> 3651200.3 | AS13: =(E13*O13)+X13*E13+AI13 -> 3656073.4 | AT13: =(F13*P13)+Z13*F13+AJ13 -> 3651643.8 | AU13: =(E13*Q13)+Z13*E13+AK13 -> 3656516.9 | AV13: =(H13*R13)+AB13*H13+AL13 -> 3652158.9 | AW13: =(I13*S13)+AC13*I13+AM13 -> 3660208.3 | AZ13: 1.2 | BA13: 500 | BB13: =AP13*AZ11 -> 4378779.2 | BC13: =AQ13*AZ12 -> 4384626.8 | BD13: =AR13*AZ13 -> 4381440.4 | BE13: =AS13*AZ12 -> 4387288 | BF13: =AT13*AZ13 -> 4381972.6 | BG13: =AU13*AZ13 -> 4387820.3 | BH13: =AV13*AZ13 -> 4382590.7 | BI13: =AW13*AZ13 -> 4392249.9 | BJ13: 348 | BK13: 493 | BL13: =BH13*1.4 -> 6135627 | BM13: =BI13*1.4 -> 6149149.9 | BO13: 500 | BP13: 2.5 | BQ13: 5 | BR13: 2.5 | BS13: 5 | BT13: 2.5 | BU13: 5 | BV13: 2.5 | BW13: 5 | BY13: 500 | BZ13: =CEILING(BP13*BP$6,0.05) -> 4 | CA13: =CEILING(BQ13*BQ$6,0.05) -> 8 | CB13: =CEILING(BR13*BR$6,0.05) -> 5 | CC13: =CEILING(BS13*BS$6,0.05) -> 10 | CD13: =CEILING(BT13*BT$6,0.05) -> 4.5 | CE13: =CEILING(BU13*BU$6,0.05) -> 9 | CF13: =CEILING(BV13*BV$6,0.05) -> 1.75 | CG13: =CEILING(BW13*BW$6,0.05) -> 3.5
A14: 1000 | B14: 42 | C14: 42 | D14: 42 | E14: 42 | F14: 42 | G14: 42 | H14: 42 | I14: 42 | K14: 1000 | L14: =Bajadas!G6 -> 168604.24 | M14: =Bajadas!H6 -> 168829.46 | N14: =Bajadas!G6 -> 168604.24 | O14: =Bajadas!H6 -> 168829.46 | P14: =Bajadas!G6 -> 168604.24 | Q14: =Bajadas!H6 -> 168829.46 | R14: =Bajadas!G6 -> 168604.24 | S14: =Bajadas!$H$6 -> 168829.46 | U14: 1000 | X14: =Laminado!J11 -> 98.790461 | Z14: =Laminado!C11 -> 118.54855 | AB14: =Laminado!C8 -> 151.2516 | AC14: =Laminado!C8*2 -> 302.5032 | AE14: 1000 | AF14: 1600 | AG14: 1600 | AH14: 1600 | AI14: 1600 | AJ14: 1600 | AK14: 1600 | AL14: 1600 | AM14: 1600 | AO14: 1000 | AP14: =(B14*L14)+V14*B14+AF14 -> 7082978.1 | AQ14: =(C14*M14)+W14*C14+AG14 -> 7092437.5 | AR14: =(D14*N14)+X14*D14+AH14 -> 7087127.3 | AS14: =(E14*O14)+X14*E14+AI14 -> 7096586.7 | AT14: =(F14*P14)+Z14*F14+AJ14 -> 7087957.1 | AU14: =(E14*Q14)+Z14*E14+AK14 -> 7097416.5 | AV14: =(H14*R14)+AB14*H14+AL14 -> 7089330.6 | AW14: =(I14*S14)+AC14*I14+AM14 -> 7105142.6 | AZ14: 1.2 | BA14: 1000 | BB14: =AP14*AZ12 -> 8499573.7 | BC14: =AQ14*AZ13 -> 8510925 | BD14: =AR14*AZ14 -> 8504552.7 | BE14: =AS14*AZ13 -> 8515904 | BF14: =AT14*AZ14 -> 8505548.5 | BG14: =AU14*AZ14 -> 8516899.9 | BH14: =AV14*AZ14 -> 8507196.7 | BI14: =AW14*AZ14 -> 8526171.2 | BJ14: 548 | BK14: 831 | BL14: =BH14*1.4 -> 11910075 | BM14: =BI14*1.4 -> 11936640 | BO14: 1000 | BP14: 2 | BQ14: 4 | BR14: 2 | BS14: 4 | BT14: 2 | BU14: 4 | BV14: 2 | BW14: 4 | BY14: 1000 | BZ14: =CEILING(BP14*BP$6,0.05) -> 3.2 | CA14: =CEILING(BQ14*BQ$6,0.05) -> 6.4 | CB14: =CEILING(BR14*BR$6,0.05) -> 4 | CC14: =CEILING(BS14*BS$6,0.05) -> 8 | CD14: =CEILING(BT14*BT$6,0.05) -> 3.6 | CE14: =CEILING(BU14*BU$6,0.05) -> 7.2 | CF14: =CEILING(BV14*BV$6,0.05) -> 1.4 | CG14: =CEILING(BW14*BW$6,0.05) -> 2.8
A16: Tarjetas | BY16: obra primera
A17: Tiempo de producción | AO17: triplex | BA17: triplex | BY17: Gramaje 63g
A18: cartulina triplex | BY18: Impresión 1 lado
A19: Tamaño 9x5 | D19: cantidad de bajadas - 24 x ´postura | L19: costo de impresión x bajada | V19: costo de laminado | AE19: costo de corte | AO19: PRECIO DE VENTA | BA19: PRECIO DE VENTA | BY19: Color blanco
A20: Cantidad | B20: Sin laminar | D20: Laca UV | F20: Laminado brillo | H20: Laminado mate | K20: Cantidad | L20: Sin laminar | N20: Laca UV | P20: Laminado brillo | R20: Laminado mate | U20: Cantidad | V20: Sin laminar | X20: Laca UV | Z20: Laminado brillo | AB20: Laminado mate | AE20: Cantidad | AF20: Sin laminar | AH20: Laca UV | AJ20: Laminado brillo | AL20: Laminado mate | AO20: Cantidad | AP20: Sin laminar | AR20: Laca UV | AT20: Laminado brillo | AV20: Laminado mate | AY20: 3/4/5 mm | BA20: Cantidad | BB20: Sin laminar | BD20: Laca UV | BF20: Laminado brillo | BH20: Laminado mate | BJ20: Laminado soft touch | BL20: Sectorizado o blanco
A21: Tarjetas | B21: 4/0 | C21: 4/4 | D21: 4/0 | E21: 4/4 | F21: 4/0 | G21: 4/4 | H21: 4/0 | I21: 4/4 | K21: Tarjetas | L21: 4/0 | M21: 4/4 | N21: 4/0 | O21: 4/4 | P21: 4/0 | Q21: 4/4 | R21: 4/0 | S21: 4/4 | U21: Tarjetas | V21: 4/0 | W21: 4/4 | X21: 4/0 | Y21: 4/4 | Z21: 4/0 | AA21: 4/4 | AB21: 4/0 | AC21: 4/4 | AE21: Tarjetas | AF21: 4/0 | AG21: 4/4 | AH21: 4/0 | AI21: 4/4 | AJ21: 4/0 | AK21: 4/4 | AL21: 4/0 | AM21: 4/4 | AO21: Tarjetas | AP21: 4/0 | AQ21: 4/4 | AR21: 4/0 | AS21: 4/4 | AT21: 4/0 | AU21: 4/4 | AV21: 4/0 | AW21: 4/4 | AY21: 600 | AZ21: 1.2 | BA21: Tarjetas | BB21: 4/0 | BC21: 4/4 | BD21: 4/0 | BE21: 4/4 | BF21: 4/0 | BG21: 4/4 | BH21: 4/0 | BI21: 4/4 | BJ21: 4/0 | BK21: 4/4 | BL21: 4/0 | BM21: 4/4 | BY21: LA IMPRESION NO PUEDE CUBRIR EL 100% DE LA CARA DEL SOBRE.
A22: 100 | B22: 5 | C22: 5 | D22: 5 | E22: 5 | F22: 5 | G22: 5 | H22: 5 | I22: 5 | K22: 100 | L22: =Bajadas!$C$5 -> 203036.3 | M22: =Bajadas!$D$5 -> 203268.35 | N22: =$L22 -> 203036.3 | O22: =$M22 -> 203268.35 | P22: =$L22 -> 203036.3 | Q22: =$M22 -> 203268.35 | R22: =$L22 -> 203036.3 | S22: =$M22 -> 203268.35 | U22: 100 | X22: =X10 -> 136.2627 | Y22: =Y10 | Z22: =Z10 -> 163.51525 | AA22: =AA10 | AB22: =AB10 -> 163.51525 | AC22: =AC10 -> 327.03049 | AE22: 100 | AF22: 400 | AG22: 400 | AH22: 400 | AI22: 400 | AJ22: 400 | AK22: 400 | AL22: 400 | AM22: 400 | AO22: 100 | AP22: =(B22*L22)+V22*B22+AF22 -> 1015581.5 | AQ22: =(C22*M22)+W22*C22+AG22 -> 1016741.8 | AR22: =(D22*N22)+X22*D22+AH22 -> 1016262.8 | AS22: =(E22*O22)+X22*E22+AI22 -> 1017423.1 | AT22: =(F22*P22)+Z22*F22+AJ22 -> 1016399.1 | AU22: =(E22*Q22)+Z22*E22+AK22 -> 1017559.3 | AV22: =(H22*R22)+AB22*H22+AL22 -> 1016399.1 | AW22: =(I22*S22)+AC22*I22+AM22 -> 1018376.9 | AY22: 1200 | AZ22: 1.2 | BA22: 100 | BB22: =AP22*AZ22 -> 1218697.8 | BC22: =AQ22*AZ22 -> 1220090.1 | BD22: =AR22*AZ21 -> 1219515.4 | BE22: =AS22*AZ22 -> 1220907.7 | BF22: =AT22*AZ22 -> 1219678.9 | BG22: =AU22*AZ22 -> 1221071.2 | BH22: =AV22*AZ22 -> 1219678.9 | BI22: =AW22*AZ22 -> 1222052.3 | BJ22: =CEILING(BH22*1.15,1) -> 1402631 | BK22: =CEILING(BI22*1.15,1) -> 1405361 | BL22: =BH22*1.4 -> 1707550.5 | BM22: =BI22*1.4 -> 1710873.2
A23: 200 | B23: 9 | C23: 9 | D23: 9 | E23: 9 | F23: 9 | G23: 9 | H23: 9 | I23: 9 | K23: 200 | L23: =Bajadas!$C$5 -> 203036.3 | M23: =Bajadas!$D$5 -> 203268.35 | N23: =$L23 -> 203036.3 | O23: =$M23 -> 203268.35 | P23: =$L23 -> 203036.3 | Q23: =$M23 -> 203268.35 | R23: =$L23 -> 203036.3 | S23: =$M23 -> 203268.35 | U23: 200 | X23: =X11 -> 136.2627 | Y23: =Y11 | Z23: =Z11 -> 151.2516 | AA23: =AA11 | AB23: =AB11 -> 163.51525 | AC23: =AC11 -> 327.03049 | AE23: 200 | AF23: 500 | AG23: 500 | AH23: 500 | AI23: 500 | AJ23: 500 | AK23: 500 | AL23: 500 | AM23: 500 | AO23: 200 | AP23: =(B23*L23)+V23*B23+AF23 -> 1827826.7 | AQ23: =(C23*M23)+W23*C23+AG23 -> 1829915.2 | AR23: =(D23*N23)+X23*D23+AH23 -> 1829053.1 | AS23: =(E23*O23)+X23*E23+AI23 -> 1831141.5 | AT23: =(F23*P23)+Z23*F23+AJ23 -> 1829188 | AU23: =(E23*Q23)+Z23*E23+AK23 -> 1831276.4 | AV23: =(H23*R23)+AB23*H23+AL23 -> 1829298.4 | AW23: =(I23*S23)+AC23*I23+AM23 -> 1832858.4 | AY23: 1800 | AZ23: 1.2 | BA23: 200 | BB23: =AP23*AZ23 -> 2193392.1 | BC23: =AQ23*AZ23 -> 2195898.2 | BD23: =AR23*AZ22 -> 2194863.7 | BE23: =AS23*AZ23 -> 2197369.8 | BF23: =AT23*AZ23 -> 2195025.6 | BG23: =AU23*AZ23 -> 2197531.7 | BH23: =AV23*AZ23 -> 2195158 | BI23: =AW23*AZ23 -> 2199430.1 | BJ23: =CEILING(BH23*1.15,1) -> 2524432 | BK23: =CEILING(BI23*1.15,1) -> 2529345 | BL23: =BH23*1.4 -> 3073221.2 | BM23: =BI23*1.4 -> 3079202.2
A24: 300 | B24: 13 | C24: 13 | D24: 13 | E24: 13 | F24: 13 | G24: 13 | H24: 13 | I24: 13 | K24: 300 | L24: =Bajadas!$C$5 -> 203036.3 | M24: =Bajadas!$D$5 -> 203268.35 | N24: =$L24 -> 203036.3 | O24: =$M24 -> 203268.35 | P24: =$L24 -> 203036.3 | Q24: =$M24 -> 203268.35 | R24: =$L24 -> 203036.3 | S24: =$M24 -> 203268.35 | U24: 300 | X24: =X12 -> 115.8233 | Y24: =Y12 | Z24: =Z12 -> 138.98796 | AA24: =AA12 | AB24: =AB12 -> 151.2516 | AC24: =AC12 -> 302.5032 | AE24: 300 | AF24: 700 | AG24: 700 | AH24: 700 | AI24: 700 | AJ24: 700 | AK24: 700 | AL24: 700 | AM24: 700 | AO24: 300 | AP24: =(B24*L24)+V24*B24+AF24 -> 2640171.9 | AQ24: =(C24*M24)+W24*C24+AG24 -> 2643188.6 | AR24: =(D24*N24)+X24*D24+AH24 -> 2641677.6 | AS24: =(E24*O24)+X24*E24+AI24 -> 2644694.3 | AT24: =(F24*P24)+Z24*F24+AJ24 -> 2641978.8 | AU24: =(E24*Q24)+Z24*E24+AK24 -> 2644995.4 | AV24: =(H24*R24)+AB24*H24+AL24 -> 2642138.2 | AW24: =(I24*S24)+AC24*I24+AM24 -> 2647121.1 | AY24: 2150 | AZ24: 1.2 | BA24: 300 | BB24: =AP24*AZ24 -> 3168206.3 | BC24: =AQ24*AZ24 -> 3171826.3 | BD24: =AR24*AZ23 -> 3170013.2 | BE24: =AS24*AZ24 -> 3173633.1 | BF24: =AT24*AZ24 -> 3170374.5 | BG24: =AU24*AZ24 -> 3173994.5 | BH24: =AV24*AZ24 -> 3170565.8 | BI24: =AW24*AZ24 -> 3176545.3 | BJ24: =CEILING(BH24*1.15,1) -> 3646151 | BK24: =CEILING(BI24*1.15,1) -> 3653028 | BL24: =BH24*1.4 -> 4438792.2 | BM24: =BI24*1.4 -> 4447163.5
A25: 500 | B25: 21 | C25: 21 | D25: 21 | E25: 21 | F25: 21 | G25: 21 | H25: 21 | I25: 21 | K25: 500 | L25: =Bajadas!$C$5 -> 203036.3 | M25: =Bajadas!$D$5 -> 203268.35 | N25: =$L25 -> 203036.3 | O25: =$M25 -> 203268.35 | P25: =$L25 -> 203036.3 | Q25: =$M25 -> 203268.35 | R25: =$L25 -> 203036.3 | S25: =$M25 -> 203268.35 | U25: 500 | X25: =X13 -> 105.6036 | Y25: =Y13 | Z25: =Z13 -> 126.72432 | AA25: =AA13 | AB25: =AB13 -> 151.2516 | AC25: =AC13 -> 302.5032 | AE25: 500 | AF25: 1000 | AG25: 1000 | AH25: 1000 | AI25: 1000 | AJ25: 1000 | AK25: 1000 | AL25: 1000 | AM25: 1000 | AO25: 500 | AP25: =(B25*L25)+V25*B25+AF25 -> 4264762.3 | AQ25: =(C25*M25)+W25*C25+AG25 -> 4269635.4 | AR25: =(D25*N25)+X25*D25+AH25 -> 4266980 | AS25: =(E25*O25)+X25*E25+AI25 -> 4271853.1 | AT25: =(F25*P25)+Z25*F25+AJ25 -> 4267423.6 | AU25: =(E25*Q25)+Z25*E25+AK25 -> 4272296.6 | AV25: =(H25*R25)+AB25*H25+AL25 -> 4267938.6 | AW25: =(I25*S25)+AC25*I25+AM25 -> 4275988 | AY25: 3000 | AZ25: 1.2 | BA25: 500 | BB25: =AP25*AZ25 -> 5117714.8 | BC25: =AQ25*AZ25 -> 5123562.5 | BD25: =AR25*AZ24 -> 5120376 | BE25: =AS25*AZ25 -> 5126223.7 | BF25: =AT25*AZ25 -> 5120908.3 | BG25: =AU25*AZ25 -> 5126755.9 | BH25: =AV25*AZ25 -> 5121526.4 | BI25: =AW25*AZ25 -> 5131185.6 | BJ25: =CEILING(BH25*1.15,1) -> 5889756 | BK25: =CEILING(BI25*1.15,1) -> 5900864 | BL25: =BH25*1.4 -> 7170136.9 | BM25: =BI25*1.4 -> 7183659.8
A26: 1000 | B26: 42 | C26: 42 | D26: 42 | E26: 42 | F26: 42 | G26: 42 | H26: 42 | I26: 42 | K26: 1000 | L26: =Bajadas!$C$6 -> 197064.65 | M26: =Bajadas!$D$6 -> 197289.87 | N26: =$L26 -> 197064.65 | O26: =$M26 -> 197289.87 | P26: =$L26 -> 197064.65 | Q26: =$M26 -> 197289.87 | R26: =$L26 -> 197064.65 | S26: =$M26 -> 197289.87 | U26: 1000 | X26: =X14 -> 98.790461 | Y26: =Y14 | Z26: =Z14 -> 118.54855 | AA26: =AA14 | AB26: =AB14 -> 151.2516 | AC26: =AC14 -> 302.5032 | AE26: 1000 | AF26: 1600 | AG26: 1600 | AH26: 1600 | AI26: 1600 | AJ26: 1600 | AK26: 1600 | AL26: 1600 | AM26: 1600 | AO26: 1000 | AP26: =(B26*L26)+V26*B26+AF26 -> 8278315.1 | AQ26: =(C26*M26)+W26*C26+AG26 -> 8287774.6 | AR26: =(D26*N26)+X26*D26+AH26 -> 8282464.3 | AS26: =(E26*O26)+X26*E26+AI26 -> 8291923.8 | AT26: =(F26*P26)+Z26*F26+AJ26 -> 8283294.2 | AU26: =(E26*Q26)+Z26*E26+AK26 -> 8292753.6 | AV26: =(H26*R26)+AB26*H26+AL26 -> 8284667.7 | AW26: =(I26*S26)+AC26*I26+AM26 -> 8300479.7 | AZ26: 1.2 | BA26: 1000 | BB26: =AP26*AZ26 -> 9933978.2 | BC26: =AQ26*AZ26 -> 9945329.5 | BD26: =AR26*AZ25 -> 9938957.2 | BE26: =AS26*AZ26 -> 9950308.6 | BF26: =AT26*AZ26 -> 9939953 | BG26: =AU26*AZ26 -> 9951304.4 | BH26: =AV26*AZ26 -> 9941601.3 | BI26: =AW26*AZ26 -> 9960575.7 | BJ26: =CEILING(BH26*1.15,1) -> 11432842 | BK26: =CEILING(BI26*1.15,1) -> 11454663 | BL26: =BH26*1.4 -> 13918242 | BM26: =BI26*1.4 -> 13944806 | BY26: Hoja membrete 4/0
AX28: 269 | BY28: A4
A29: Tarjetas | BA29: TARJETAS | BR29: Individuales | BT29: Papel kraf | BW29: Papel obra | BX29: Cantidad | BY29: impresión | BZ29: corte | CB29: precio
A30: Tiempo de producción | AO30: 350 | BA30: Papel ilustración 350g | BR30: 100 | BW30: impresión 4/0 | BX30: 100 | BY30: =BO10*Pack!$K$22 -> 455.74 | BZ30: =BX30/95 -> 1.0526316 | CA30: 50 | CB30: =CA30+BY30 -> 505.74
A31: Papel ilustración 350g | BA31: Tamaño 9x5 | BR31: 200 | BX31: 200 | BY31: =BO11*Pack!$K$22 -> 911.48 | BZ31: =BX31/95 -> 2.1052632 | CA31: 50 | CB31: =CA31+BY31 -> 961.48
A32: Tamaño 9x5 | D32: cantidad de bajadas - 24 x ´postura | L32: costo de impresión x bajada | V32: costo de laminado | AE32: costo de corte | AO32: PRECIO DE VENTA | AZ32: 1.1 | BA32: PRECIO DE VENTA TARJETAS | BR32: 300 | BX32: 300 | BY32: =BO12*Pack!$K$22 -> 1367.22 | BZ32: =BX32/95 -> 3.1578947 | CA32: 60 | CB32: =CA32+BY32 -> 1427.22
A33: Cantidad | B33: Sin laminar | D33: Laca UV | F33: Laminado brillo | H33: Laminado mate | K33: Cantidad | L33: Sin laminar | N33: Laca UV | P33: Laminado brillo | R33: Laminado mate | U33: Cantidad | V33: Sin laminar | X33: Laca UV | Z33: Laminado brillo | AB33: Laminado mate | AE33: Cantidad | AF33: Sin laminar | AH33: Laca UV | AJ33: Laminado brillo | AL33: Laminado mate | AO33: Cantidad | AP33: Sin laminar | AR33: Laca UV | AT33: Laminado brillo | AV33: Laminado mate | AZ33: 1.1 | BA33: Cantidad | BB33: Sin laminar | BD33: Laca UV | BF33: Laminado brillo | BH33: Laminado mate | BJ33: Laminado soft touch | BL33: Sectorizado o blanco | BR33: 500 | BX33: 500 | BY33: =BO13*Pack!$K$23 -> 2191.2 | BZ33: =BX33/95 -> 5.2631579 | CA33: 60 | CB33: =CA33+BY33 -> 2251.2
A34: Tarjetas | B34: 4/0 | C34: 4/4 | D34: 4/0 | E34: 4/4 | F34: 4/0 | G34: 4/4 | H34: 4/0 | I34: 4/4 | K34: Tarjetas | L34: 4/0 | M34: 4/4 | N34: 4/0 | O34: 4/4 | P34: 4/0 | Q34: 4/4 | R34: 4/0 | S34: 4/4 | U34: Tarjetas | V34: 4/0 | W34: 4/4 | X34: 4/0 | Y34: 4/4 | Z34: 4/0 | AA34: 4/4 | AB34: 4/0 | AC34: 4/4 | AE34: Tarjetas | AF34: 4/0 | AG34: 4/4 | AH34: 4/0 | AI34: 4/4 | AJ34: 4/0 | AK34: 4/4 | AL34: 4/0 | AM34: 4/4 | AO34: Tarjetas | AP34: 4/0 | AQ34: 4/4 | AR34: 4/0 | AS34: 4/4 | AT34: 4/0 | AU34: 4/4 | AV34: 4/0 | AW34: 4/4 | AZ34: 1.1 | BA34: Tarjetas | BB34: 4/0 | BC34: 4/4 | BD34: 4/0 | BE34: 4/4 | BF34: 4/0 | BG34: 4/4 | BH34: 4/0 | BI34: 4/4 | BJ34: 4/0 | BK34: 4/4 | BL34: 4/0 | BM34: 4/4 | BR34: 1000 | BX34: 1000 | BY34: =BO14*Pack!$K$24 -> 4207.4 | BZ34: =BX34/95 -> 10.526316 | CA34: 70 | CB34: =CA34+BY34 -> 4277.4
A35: 100 | B35: 5 | C35: 5 | D35: 5 | E35: 5 | F35: 5 | G35: 5 | H35: 5 | I35: 5 | K35: 100 | L35: =Bajadas!$E$5 -> 202610.45 | M35: =Bajadas!$F$5 -> 202842.5 | N35: =L35 -> 202610.45 | O35: =M35 -> 202842.5 | P35: =N35 -> 202610.45 | Q35: =O35 -> 202842.5 | R35: =P35 -> 202610.45 | S35: =Q35 -> 202842.5 | U35: 100 | X35: =X22 -> 136.2627 | Y35: =Y22 | Z35: =Z22 -> 163.51525 | AA35: =AA22 | AB35: =AB22 -> 163.51525 | AC35: =AC22 -> 327.03049 | AE35: 100 | AF35: 400 | AG35: 400 | AH35: 400 | AI35: 400 | AJ35: 400 | AK35: 400 | AL35: 400 | AM35: 400 | AO35: 100 | AP35: =(B35*L35)+V35*B35+AF35 -> 1013452.3 | AQ35: =(C35*M35)+W35*C35+AG35 -> 1014612.5 | AR35: =(D35*N35)+X35*D35+AH35 -> 1014133.6 | AS35: =(E35*O35)+X35*E35+AI35 -> 1015293.8 | AT35: =(F35*P35)+Z35*F35+AJ35 -> 1014269.8 | AU35: =(E35*Q35)+Z35*E35+AK35 -> 1015430.1 | AV35: =(H35*R35)+AB35*H35+AL35 -> 1014269.8 | AW35: =(I35*S35)+AC35*I35+AM35 -> 1016247.7 | AZ35: 1.1 | BA35: 100 | BB35: =AP35*AZ21 -> 1216142.7 | BC35: =AQ35*AZ21 -> 1217535 | BD35: =AR35*AZ22 -> 1216960.3 | BE35: =AS35*AZ21 -> 1218352.6 | BF35: =AT35*AZ22 -> 1217123.8 | BG35: =AU35*AZ22 -> 1218516.1 | BH35: =AV35*AZ22 -> 1217123.8 | BI35: =AW35*AZ22 -> 1219497.2 | BJ35: =CEILING(BH35*1.15,1) -> 1399693 | BK35: =CEILING(BI35*1.15,1) -> 1402422 | BL35: =BH35*1.4 -> 1703973.3 | BM35: =BI35*1.4 -> 1707296.1
A36: 200 | B36: 9 | C36: 9 | D36: 9 | E36: 9 | F36: 9 | G36: 9 | H36: 9 | I36: 9 | K36: 200 | L36: =Bajadas!$E$5 -> 202610.45 | M36: =Bajadas!$F$5 -> 202842.5 | N36: =L36 -> 202610.45 | O36: =M36 -> 202842.5 | P36: =N36 -> 202610.45 | Q36: =O36 -> 202842.5 | R36: =P36 -> 202610.45 | S36: =Q36 -> 202842.5 | U36: 200 | X36: =X23 -> 136.2627 | Y36: =Y23 | Z36: =Z23 -> 151.2516 | AA36: =AA23 | AB36: =AB23 -> 163.51525 | AC36: =AC23 -> 327.03049 | AE36: 200 | AF36: 500 | AG36: 500 | AH36: 500 | AI36: 500 | AJ36: 500 | AK36: 500 | AL36: 500 | AM36: 500 | AO36: 200 | AP36: =(B36*L36)+V36*B36+AF36 -> 1823994.1 | AQ36: =(C36*M36)+W36*C36+AG36 -> 1826082.5 | AR36: =(D36*N36)+X36*D36+AH36 -> 1825220.4 | AS36: =(E36*O36)+X36*E36+AI36 -> 1827308.9 | AT36: =(F36*P36)+Z36*F36+AJ36 -> 1825355.3 | AU36: =(E36*Q36)+Z36*E36+AK36 -> 1827443.8 | AV36: =(H36*R36)+AB36*H36+AL36 -> 1825465.7 | AW36: =(I36*S36)+AC36*I36+AM36 -> 1829025.8 | AZ36: 1.1 | BA36: 200 | BB36: =AP36*AZ22 -> 2188792.9 | BC36: =AQ36*AZ22 -> 2191299 | BD36: =AR36*AZ23 -> 2190264.5 | BE36: =AS36*AZ22 -> 2192770.7 | BF36: =(R36*AB36)+AL36*R36+AV36 -> 1.3626059e+08 | BG36: =(Q36*AC36)+AL36*Q36+AW36 -> 1.6958596e+08 | BH36: =AV36*AZ23 -> 2190558.8 | BI36: =AW36*AZ23 -> 2194831 | BJ36: =CEILING(BH36*1.15,1) -> 2519143 | BK36: =CEILING(BI36*1.15,1) -> 2524056 | BL36: =BH36*1.4 -> 3066782.4 | BM36: =BI36*1.4 -> 3072763.3
A37: 300 | B37: 13 | C37: 13 | D37: 13 | E37: 13 | F37: 13 | G37: 13 | H37: 13 | I37: 13 | K37: 300 | L37: =Bajadas!$E$5 -> 202610.45 | M37: =Bajadas!$F$5 -> 202842.5 | N37: =L37 -> 202610.45 | O37: =M37 -> 202842.5 | P37: =N37 -> 202610.45 | Q37: =O37 -> 202842.5 | R37: =P37 -> 202610.45 | S37: =Q37 -> 202842.5 | U37: 300 | X37: =X24 -> 115.8233 | Y37: =Y24 | Z37: =Z24 -> 138.98796 | AA37: =AA24 | AB37: =AB24 -> 151.2516 | AC37: =AC24 -> 302.5032 | AE37: 300 | AF37: 700 | AG37: 700 | AH37: 700 | AI37: 700 | AJ37: 700 | AK37: 700 | AL37: 700 | AM37: 700 | AO37: 300 | AP37: =(B37*L37)+V37*B37+AF37 -> 2634635.9 | AQ37: =(C37*M37)+W37*C37+AG37 -> 2637652.5 | AR37: =(D37*N37)+X37*D37+AH37 -> 2636141.6 | AS37: =(E37*O37)+X37*E37+AI37 -> 2639158.2 | AT37: =(F37*P37)+Z37*F37+AJ37 -> 2636442.7 | AU37: =(E37*Q37)+Z37*E37+AK37 -> 2639459.4 | AV37: =(H37*R37)+AB37*H37+AL37 -> 2636602.1 | AW37: =(I37*S37)+AC37*I37+AM37 -> 2641585.1 | AZ37: 1.1 | BA37: 300 | BB37: =AP37*AZ23 -> 3161563 | BC37: =AQ37*AZ23 -> 3165183 | BD37: =AR37*AZ24 -> 3163369.9 | BE37: =AS37*AZ23 -> 3166989.9 | BF37: =(R37*AB37)+AL37*R37+AV37 -> 1.7510907e+08 | BG37: =(Q37*AC37)+AL37*Q37+AW37 -> 2.0599184e+08 | BH37: =AV37*AZ24 -> 3163922.6 | BI37: =AW37*AZ24 -> 3169902.1 | BJ37: =CEILING(BH37*1.15,1) -> 3638511 | BK37: =CEILING(BI37*1.15,1) -> 3645388 | BL37: =BH37*1.4 -> 4429491.6 | BM37: =BI37*1.4 -> 4437862.9
A38: 500 | B38: 21 | C38: 21 | D38: 21 | E38: 21 | F38: 21 | G38: 21 | H38: 21 | I38: 21 | K38: 500 | L38: =Bajadas!$E$5 -> 202610.45 | M38: =Bajadas!$F$5 -> 202842.5 | N38: =L38 -> 202610.45 | O38: =M38 -> 202842.5 | P38: =N38 -> 202610.45 | Q38: =O38 -> 202842.5 | R38: =P38 -> 202610.45 | S38: =Q38 -> 202842.5 | U38: 500 | X38: =X25 -> 105.6036 | Y38: =Y25 | Z38: =Z25 -> 126.72432 | AA38: =AA25 | AB38: =AB25 -> 151.2516 | AC38: =AC25 -> 302.5032 | AE38: 500 | AF38: 1000 | AG38: 1000 | AH38: 1000 | AI38: 1000 | AJ38: 1000 | AK38: 1000 | AL38: 1000 | AM38: 1000 | AO38: 500 | AP38: =(B38*L38)+V38*B38+AF38 -> 4255819.5 | AQ38: =(C38*M38)+W38*C38+AG38 -> 4260692.5 | AR38: =(D38*N38)+X38*D38+AH38 -> 4258037.2 | AS38: =(E38*O38)+X38*E38+AI38 -> 4262910.2 | AT38: =(F38*P38)+Z38*F38+AJ38 -> 4258480.7 | AU38: =(E38*Q38)+Z38*E38+AK38 -> 4263353.8 | AV38: =(H38*R38)+AB38*H38+AL38 -> 4258995.8 | AW38: =(I38*S38)+AC38*I38+AM38 -> 4267045.1 | AZ38: 1.1 | BA38: 500 | BB38: =AP38*AZ24 -> 5106983.4 | BC38: =AQ38*AZ24 -> 5112831 | BD38: =AR38*AZ25 -> 5109644.6 | BE38: =AS38*AZ24 -> 5115492.3 | BF38: =(R38*AB38)+AL38*R38+AV38 -> 2.375146e+08 | BG38: =(Q38*AC38)+AL38*Q38+AW38 -> 2.6847005e+08 | BH38: =AV38*AZ25 -> 5110794.9 | BI38: =AW38*AZ25 -> 5120454.1 | BJ38: =CEILING(BH38*1.15,1) -> 5877415 | BK38: =CEILING(BI38*1.15,1) -> 5888523 | BL38: =BH38*1.4 -> 7155112.9 | BM38: =BI38*1.4 -> 7168635.8
A39: 1000 | B39: 42 | C39: 42 | D39: 42 | E39: 42 | F39: 42 | G39: 42 | H39: 42 | I39: 42 | K39: 1000 | L39: =Bajadas!$E$6 -> 196651.32 | M39: =Bajadas!$F$6 -> 196876.55 | N39: =L39 -> 196651.32 | O39: =M39 -> 196876.55 | P39: =N39 -> 196651.32 | Q39: =O39 -> 196876.55 | R39: =P39 -> 196651.32 | S39: =Q39 -> 196876.55 | U39: 1000 | X39: =X26 -> 98.790461 | Y39: =Y26 | Z39: =Z26 -> 118.54855 | AA39: =AA26 | AB39: =AB26 -> 151.2516 | AC39: =AC26 -> 302.5032 | AE39: 1000 | AF39: 1600 | AG39: 1600 | AH39: 1600 | AI39: 1600 | AJ39: 1600 | AK39: 1600 | AL39: 1600 | AM39: 1600 | AO39: 1000 | AP39: =(B39*L39)+V39*B39+AF39 -> 8260955.5 | AQ39: =(C39*M39)+W39*C39+AG39 -> 8270414.9 | AR39: =(D39*N39)+X39*D39+AH39 -> 8265104.7 | AS39: =(E39*O39)+X39*E39+AI39 -> 8274564.1 | AT39: =(F39*P39)+Z39*F39+AJ39 -> 8265934.5 | AU39: =(E39*Q39)+Z39*E39+AK39 -> 8275394 | AV39: =(H39*R39)+AB39*H39+AL39 -> 8267308 | AW39: =(I39*S39)+AC39*I39+AM39 -> 8283120.1 | AZ39: 1.1 | BA39: 1000 | BB39: =AP39*AZ25 -> 9913146.6 | BC39: =AQ39*AZ25 -> 9924497.9 | BD39: =AR39*AZ26 -> 9918125.6 | BE39: =AS39*AZ25 -> 9929477 | BF39: =(R39*AB39)+AL39*R39+AV39 -> 3.5265325e+08 | BG39: =(Q39*AC39)+AL39*Q39+AW39 -> 3.8284138e+08 | BH39: =AV39*AZ26 -> 9920769.7 | BI39: =AW39*AZ26 -> 9939744.1 | BJ39: =CEILING(BH39*1.15,1) -> 11408886 | BK39: =CEILING(BI39*1.15,1) -> 11430706 | BL39: =BH39*1.4 -> 13889078 | BM39: =BI39*1.4 -> 13915642
AZ40: 1.1
A41: Postales | AZ41: 1.1 | BA41: POSTALES
A42: Tiempo de producción | AZ42: 1.1 | BA42: Papel ilustración 300g
A43: Papel ilustración 300g | AZ43: 1.1 | BA43: Tamaño 10x15
A44: Tamaño 10x15 | D44: cantidad de bajadas - 9 x ´postura | L44: costo de impresión x bajada | V44: costo de laminado | AE44: costo de corte | AO44: PRECIO DE VENTA | AZ44: 1.1 | BA44: PRECIO DE VENTA POSTALES
A45: Cantidad | B45: Sin laminar | D45: Laca UV | F45: Laminado brillo | H45: Laminado mate | K45: Cantidad | L45: Sin laminar | N45: Laca UV | P45: Laminado brillo | R45: Laminado mate | U45: Cantidad | V45: Sin laminar | X45: Laca UV | Z45: Laminado brillo | AB45: Laminado mate | AE45: Cantidad | AF45: Sin laminar | AH45: Laca UV | AJ45: Laminado brillo | AL45: Laminado mate | AO45: Cantidad | AP45: Sin laminar | AR45: Laca UV | AT45: Laminado brillo | AV45: Laminado mate | AZ45: 1.1 | BA45: Postales | BB45: Sin laminar | BD45: Laca UV | BF45: Laminado brillo | BH45: Laminado mate | BJ45: Laminado soft touch | BL45: Sectorizado o blanco
A46: Postales | B46: 4/0 | C46: 4/4 | D46: 4/0 | E46: 4/4 | F46: 4/0 | G46: 4/4 | H46: 4/0 | I46: 4/4 | K46: Postales | L46: 4/0 | M46: 4/4 | N46: 4/0 | O46: 4/4 | P46: 4/0 | Q46: 4/4 | R46: 4/0 | S46: 4/4 | U46: Postales | V46: 4/0 | W46: 4/4 | X46: 4/0 | Y46: 4/4 | Z46: 4/0 | AA46: 4/4 | AB46: 4/0 | AC46: 4/4 | AE46: Postales | AF46: 4/0 | AG46: 4/4 | AH46: 4/0 | AI46: 4/4 | AJ46: 4/0 | AK46: 4/4 | AL46: 4/0 | AM46: 4/4 | AO46: Postales | AP46: 4/0 | AQ46: 4/4 | AR46: 4/0 | AS46: 4/4 | AT46: 4/0 | AU46: 4/4 | AV46: 4/0 | AW46: 4/4 | AZ46: 1.1 | BA46: Cantidad | BB46: 4/0 | BC46: 4/4 | BD46: 4/0 | BE46: 4/4 | BF46: 4/0 | BG46: 4/4 | BH46: 4/0 | BI46: 4/4 | BJ46: 4/0 | BK46: 4/4 | BL46: 4/0 | BM46: 4/4
A47: 100 | B47: 12 | C47: 12 | D47: 12 | E47: 12 | F47: 12 | G47: 12 | H47: 12 | I47: 12 | K47: 100 | L47: =Bajadas!$G5 -> 173713.46 | M47: =Bajadas!$H5 -> 173945.51 | N47: =Bajadas!$G5 -> 173713.46 | O47: =Bajadas!$H5 -> 173945.51 | P47: =Bajadas!$G5 -> 173713.46 | Q47: =Bajadas!$H5 -> 173945.51 | R47: =Bajadas!$G5 -> 173713.46 | S47: =Bajadas!$H5 -> 173945.51 | U47: 100 | X47: =X35 -> 136.2627 | Y47: =Y35 | Z47: =Z35 -> 163.51525 | AA47: =AA35 | AB47: =AB35 -> 163.51525 | AC47: =AC35 -> 327.03049 | AE47: 100 | AF47: 400 | AG47: 400 | AH47: 400 | AI47: 400 | AJ47: 400 | AK47: 400 | AL47: 400 | AM47: 400 | AO47: 100 | AP47: =(B47*L47)+V47*B47+AF47 -> 2084961.5 | AQ47: =(C47*M47)+W47*C47+AG47 -> 2087746.1 | AR47: =(D47*N47)+X47*D47+AH47 -> 2086596.7 | AS47: =(E47*O47)+Y47*E47+AI47 -> 2087746.1 | AT47: =(F47*P47)+Z47*F47+AJ47 -> 2086923.7 | AU47: =(G47*Q47)+AA47*G47+AK47 -> 2087746.1 | AV47: =(H47*R47)+AB47*H47+AL47 -> 2086923.7 | AW47: =(I47*S47)+AC47*I47+AM47 -> 2091670.5 | AZ47: 1.1 | BA47: 100 | BB47: =AP47*AZ33 -> 2293457.7 | BC47: =AQ47*AZ33 -> 2296520.7 | BD47: =AR47*AZ34 -> 2295256.3 | BE47: =AS47*AZ33 -> 2296520.7 | BF47: =AT47*AZ34 -> 2295616.1 | BG47: =AU47*AZ34 -> 2296520.7 | BH47: =AV47*AZ34 -> 2295616.1 | BI47: =AW47*AZ34 -> 2300837.5 | BJ47: =CEILING(BH47*1.15,1) -> 2639959 | BK47: =CEILING(BI47*1.15,1) -> 2645964 | BL47: =BH47*1.4 -> 3213862.5 | BM47: =BI47*1.4 -> 3221172.5
A48: 200 | B48: 23 | C48: 23 | D48: 23 | E48: 23 | F48: 23 | G48: 23 | H48: 23 | I48: 23 | K48: 200 | L48: =Bajadas!$G5 -> 173713.46 | M48: =Bajadas!$H5 -> 173945.51 | N48: =Bajadas!$G5 -> 173713.46 | O48: =Bajadas!$H5 -> 173945.51 | P48: =Bajadas!$G5 -> 173713.46 | Q48: =Bajadas!$H5 -> 173945.51 | R48: =Bajadas!$G5 -> 173713.46 | S48: =Bajadas!$H5 -> 173945.51 | U48: 200 | X48: =X36 -> 136.2627 | Y48: =Y36 | Z48: =Z36 -> 151.2516 | AA48: =AA36 | AB48: =AB36 -> 163.51525 | AC48: =AC36 -> 327.03049 | AE48: 200 | AF48: 500 | AG48: 500 | AH48: 500 | AI48: 500 | AJ48: 500 | AK48: 500 | AL48: 500 | AM48: 500 | AO48: 200 | AP48: =(B48*L48)+V48*B48+AF48 -> 3995909.6 | AQ48: =(C48*M48)+W48*C48+AG48 -> 4001246.7 | AR48: =(D48*N48)+X48*D48+AH48 -> 3999043.6 | AS48: =(E48*O48)+Y48*E48+AI48 -> 4001246.7 | AT48: =(F48*P48)+Z48*F48+AJ48 -> 3999388.3 | AU48: =(G48*Q48)+AA48*G48+AK48 -> 4001246.7 | AV48: =(H48*R48)+AB48*H48+AL48 -> 3999670.4 | AW48: =(I48*S48)+AC48*I48+AM48 -> 4008768.4 | AZ48: 1.1 | BA48: 200 | BB48: =AP48*AZ34 -> 4395500.5 | BC48: =AQ48*AZ34 -> 4401371.4 | BD48: =AR48*AZ35 -> 4398948 | BE48: =AS48*AZ34 -> 4401371.4 | BF48: =(R48*AB48)+AL48*R48+AV48 -> 1.192612e+08 | BG48: =(Q48*AC48)+AL48*Q48+AW48 -> 1.4786701e+08 | BH48: =AV48*AZ35 -> 4399637.4 | BI48: =AW48*AZ35 -> 4409645.2 | BJ48: =CEILING(BH48*1.15,1) -> 5059584 | BK48: =CEILING(BI48*1.15,1) -> 5071093 | BL48: =BH48*1.4 -> 6159492.4 | BM48: =BI48*1.4 -> 6173503.3
A49: 300 | B49: 34 | C49: 34 | D49: 34 | E49: 34 | F49: 34 | G49: 34 | H49: 34 | I49: 34 | K49: 300 | L49: =Bajadas!$G6 -> 168604.24 | M49: =Bajadas!$H6 -> 168829.46 | N49: =Bajadas!$G6 -> 168604.24 | O49: =Bajadas!$H6 -> 168829.46 | P49: =Bajadas!$G6 -> 168604.24 | Q49: =Bajadas!$H6 -> 168829.46 | R49: =Bajadas!$G6 -> 168604.24 | S49: =Bajadas!$H6 -> 168829.46 | U49: 300 | X49: =X37 -> 115.8233 | Y49: =Y37 | Z49: =Z37 -> 138.98796 | AA49: =AA37 | AB49: =AB37 -> 151.2516 | AC49: =AC37 -> 302.5032 | AE49: 300 | AF49: 700 | AG49: 700 | AH49: 700 | AI49: 700 | AJ49: 700 | AK49: 700 | AL49: 700 | AM49: 700 | AO49: 300 | AP49: =(B49*L49)+V49*B49+AF49 -> 5733244.1 | AQ49: =(C49*M49)+W49*C49+AG49 -> 5740901.8 | AR49: =(D49*N49)+X49*D49+AH49 -> 5737182.1 | AS49: =(E49*O49)+Y49*E49+AI49 -> 5740901.8 | AT49: =(F49*P49)+Z49*F49+AJ49 -> 5737969.7 | AU49: =(G49*Q49)+AA49*G49+AK49 -> 5740901.8 | AV49: =(H49*R49)+AB49*H49+AL49 -> 5738386.7 | AW49: =(I49*S49)+AC49*I49+AM49 -> 5751186.9 | AZ49: 1.1 | BA49: 300 | BB49: =AP49*AZ35 -> 6306568.6 | BC49: =AQ49*AZ35 -> 6314992 | BD49: =AR49*AZ36 -> 6310900.3 | BE49: =AS49*AZ35 -> 6314992 | BF49: =(R49*AB49)+AL49*R49+AV49 -> 1.4926302e+08 | BG49: =(Q49*AC49)+AL49*Q49+AW49 -> 1.7500327e+08 | BH49: =AV49*AZ36 -> 6312225.4 | BI49: =AW49*AZ36 -> 6326305.6 | BJ49: =CEILING(BH49*1.15,1) -> 7259060 | BK49: =CEILING(BI49*1.15,1) -> 7275252 | BL49: =BH49*1.4 -> 8837115.5 | BM49: =BI49*1.4 -> 8856827.8
A50: 500 | B50: 56 | C50: 56 | D50: 56 | E50: 56 | F50: 56 | G50: 56 | H50: 56 | I50: 56 | K50: 500 | L50: =Bajadas!$G7 -> 163495.02 | M50: =Bajadas!$H7 -> 163713.42 | N50: =Bajadas!$G7 -> 163495.02 | O50: =Bajadas!$H7 -> 163713.42 | P50: =Bajadas!$G7 -> 163495.02 | Q50: =Bajadas!$H7 -> 163713.42 | R50: =Bajadas!$G7 -> 163495.02 | S50: =Bajadas!$H7 -> 163713.42 | U50: 500 | X50: =X38 -> 105.6036 | Y50: =Y38 | Z50: =Z38 -> 126.72432 | AA50: =AA38 | AB50: =AB38 -> 151.2516 | AC50: =AC38 -> 302.5032 | AE50: 500 | AF50: 1000 | AG50: 1000 | AH50: 1000 | AI50: 1000 | AJ50: 1000 | AK50: 1000 | AL50: 1000 | AM50: 1000 | AO50: 500 | AP50: =(B50*L50)+V50*B50+AF50 -> 9156721.1 | AQ50: =(C50*M50)+W50*C50+AG50 -> 9168951.5 | AR50: =(D50*N50)+X50*D50+AH50 -> 9162634.9 | AS50: =(E50*O50)+Y50*E50+AI50 -> 9168951.5 | AT50: =(F50*P50)+Z50*F50+AJ50 -> 9163817.7 | AU50: =(G50*Q50)+AA50*G50+AK50 -> 9168951.5 | AV50: =(H50*R50)+AB50*H50+AL50 -> 9165191.2 | AW50: =(I50*S50)+AC50*I50+AM50 -> 9185891.7 | AZ50: 1.1 | BA50: 500 | BB50: =AP50*AZ36 -> 10072393 | BC50: =AQ50*AZ36 -> 10085847 | BD50: =AR50*AZ37 -> 10078898 | BE50: =AS50*AZ36 -> 10085847 | BF50: =(R50*AB50)+AL50*R50+AV50 -> 1.9738909e+08 | BG50: =(Q50*AC50)+AL50*Q50+AW50 -> 2.2242315e+08 | BH50: =AV50*AZ37 -> 10081710 | BI50: =AW50*AZ37 -> 10104481 | BJ50: =CEILING(BH50*1.15,1) -> 11593967 | BK50: =CEILING(BI50*1.15,1) -> 11620153 | BL50: =BH50*1.4 -> 14114394 | BM50: =BI50*1.4 -> 14146273
A51: 1000 | B51: 112 | C51: 112 | D51: 112 | E51: 112 | F51: 112 | G51: 112 | H51: 112 | I51: 112 | K51: 1000 | L51: =Bajadas!$G8 -> 158385.8 | M51: =Bajadas!$H8 -> 158597.38 | N51: =Bajadas!$G8 -> 158385.8 | O51: =Bajadas!$H8 -> 158597.38 | P51: =Bajadas!$G8 -> 158385.8 | Q51: =Bajadas!$H8 -> 158597.38 | R51: =Bajadas!$G8 -> 158385.8 | S51: =Bajadas!$H8 -> 158597.38 | U51: 1000 | X51: =X39 -> 98.790461 | Y51: =Y39 | Z51: =Z39 -> 118.54855 | AA51: =AA39 | AB51: =AB39 -> 151.2516 | AC51: =AC39 -> 302.5032 | AE51: 1000 | AF51: 1600 | AG51: 1600 | AH51: 1600 | AI51: 1600 | AJ51: 1600 | AK51: 1600 | AL51: 1600 | AM51: 1600 | AO51: 1000 | AP51: =(B51*L51)+V51*B51+AF51 -> 17740810 | AQ51: =(C51*M51)+W51*C51+AG51 -> 17764506 | AR51: =(D51*N51)+X51*D51+AH51 -> 17751874 | AS51: =(E51*O51)+Y51*E51+AI51 -> 17764506 | AT51: =(F51*P51)+Z51*F51+AJ51 -> 17754087 | AU51: =(G51*Q51)+AA51*G51+AK51 -> 17764506 | AV51: =(H51*R51)+AB51*H51+AL51 -> 17757750 | AW51: =(I51*S51)+AC51*I51+AM51 -> 17798386 | AZ51: 1.1 | BA51: 1000 | BB51: =AP51*AZ37 -> 19514891 | BC51: =AQ51*AZ37 -> 19540957 | BD51: =AR51*AZ38 -> 19527062 | BE51: =AS51*AZ37 -> 19540957 | BF51: =(R51*AB51)+AL51*R51+AV51 -> 2.9513114e+08 | BG51: =(Q51*AC51)+AL51*Q51+AW51 -> 3.195304e+08 | BH51: =AV51*AZ38 -> 19533525 | BI51: =AW51*AZ38 -> 19578225 | BJ51: =CEILING(BH51*1.15,1) -> 22463554 | BK51: =CEILING(BI51*1.15,1) -> 22514959 | BL51: =BH51*1.4 -> 27346935 | BM51: =BI51*1.4 -> 27409515
AZ52: 1.1
AZ53: 1.1
AZ54: 1.1
A55: Postales | AZ55: 1.1 | BA55: POSTALES
A56: Tiempo de producción | AZ56: 1.1 | BA56: Papel ilustración 350g
A57: Papel ilustración 350g | AZ57: 1.1 | BA57: Tamaño 10x15
A58: Tamaño 10x15 | D58: cantidad de bajadas - 9 x ´postura | L58: costo de impresión x bajada | V58: costo de laminado | AE58: costo de corte | AO58: PRECIO DE VENTA | AZ58: 1.1 | BA58: PRECIO DE VENTA POSTALES
A59: Cantidad | B59: Sin laminar | D59: Laca UV | F59: Laminado brillo | H59: Laminado mate | K59: Cantidad | L59: Sin laminar | N59: Laca UV | P59: Laminado brillo | R59: Laminado mate | U59: Cantidad | V59: Sin laminar | X59: Laca UV | Z59: Laminado brillo | AB59: Laminado mate | AE59: Cantidad | AF59: Sin laminar | AH59: Laca UV | AJ59: Laminado brillo | AL59: Laminado mate | AO59: Cantidad | AP59: Sin laminar | AR59: Laca UV | AT59: Laminado brillo | AV59: Laminado mate | AZ59: 1.1 | BA59: Postales | BB59: Sin laminar | BD59: Laca UV | BF59: Laminado brillo | BH59: Laminado mate | BJ59: Laminado soft touch | BL59: Sectorizado o blanco
A60: Postales | B60: 4/0 | C60: 4/4 | D60: 4/0 | E60: 4/4 | F60: 4/0 | G60: 4/4 | H60: 4/0 | I60: 4/4 | K60: Postales | L60: 4/0 | M60: 4/4 | N60: 4/0 | O60: 4/4 | P60: 4/0 | Q60: 4/4 | R60: 4/0 | S60: 4/4 | U60: Postales | V60: 4/0 | W60: 4/4 | X60: 4/0 | Y60: 4/4 | Z60: 4/0 | AA60: 4/4 | AB60: 4/0 | AC60: 4/4 | AE60: Postales | AF60: 4/0 | AG60: 4/4 | AH60: 4/0 | AI60: 4/4 | AJ60: 4/0 | AK60: 4/4 | AL60: 4/0 | AM60: 4/4 | AO60: Postales | AP60: 4/0 | AQ60: 4/4 | AR60: 4/0 | AS60: 4/4 | AT60: 4/0 | AU60: 4/4 | AV60: 4/0 | AW60: 4/4 | AZ60: 1.1 | BA60: Cantidad | BB60: 4/0 | BC60: 4/4 | BD60: 4/0 | BE60: 4/4 | BF60: 4/0 | BG60: 4/4 | BH60: 4/0 | BI60: 4/4 | BJ60: 4/0 | BK60: 4/4 | BL60: 4/0 | BM60: 4/4
A61: 100 | B61: 12 | C61: 12 | D61: 12 | E61: 12 | F61: 12 | G61: 12 | H61: 12 | I61: 12 | K61: 100 | L61: =Bajadas!E5 -> 202610.45 | M61: =Bajadas!F5 -> 202842.5 | N61: =$L61 -> 202610.45 | O61: =$M61 -> 202842.5 | P61: =$L61 -> 202610.45 | Q61: =$M61 -> 202842.5 | R61: =$L61 -> 202610.45 | S61: =$M61 -> 202842.5 | U61: 100 | X61: =X47 -> 136.2627 | Y61: =Y47 | Z61: =Z47 -> 163.51525 | AA61: =AA47 | AB61: =AB47 -> 163.51525 | AC61: =AC47 -> 327.03049 | AE61: 100 | AF61: 400 | AG61: 400 | AH61: 400 | AI61: 400 | AJ61: 400 | AK61: 400 | AL61: 400 | AM61: 400 | AO61: 100 | AP61: =(B61*L61)+V61*B61+AF61 -> 2431725.4 | AQ61: =(C61*M61)+W61*C61+AG61 -> 2434510 | AR61: =(D61*N61)+X61*D61+AH61 -> 2433360.6 | AS61: =(E61*O61)+Y61*E61+AI61 -> 2434510 | AT61: =(F61*P61)+Z61*F61+AJ61 -> 2433687.6 | AU61: =(G61*Q61)+AA61*G61+AK61 -> 2434510 | AV61: =(H61*R61)+AB61*H61+AL61 -> 2433687.6 | AW61: =(I61*S61)+AC61*I61+AM61 -> 2438434.4 | AZ61: 1.1 | BA61: 100 | BB61: =AP61*AZ47 -> 2674898 | BC61: =AQ61*AZ47 -> 2677961 | BD61: =AR61*AZ48 -> 2676696.6 | BE61: =AS61*AZ47 -> 2677961 | BF61: =AT61*AZ48 -> 2677056.4 | BG61: =AU61*AZ48 -> 2677961 | BH61: =AV61*AZ48 -> 2677056.4 | BI61: =AW61*AZ48 -> 2682277.8 | BJ61: =CEILING(BH61*1.15,1) -> 3078615 | BK61: =CEILING(BI61*1.15,1) -> 3084620 | BL61: =BH61*1.4 -> 3747878.9 | BM61: =BI61*1.4 -> 3755189
A62: 200 | B62: 23 | C62: 23 | D62: 23 | E62: 23 | F62: 23 | G62: 23 | H62: 23 | I62: 23 | K62: 200 | L62: =Bajadas!E5 -> 202610.45 | M62: =Bajadas!F5 -> 202842.5 | N62: =$L62 -> 202610.45 | O62: =$M62 -> 202842.5 | P62: =$L62 -> 202610.45 | Q62: =$M62 -> 202842.5 | R62: =$L62 -> 202610.45 | S62: =$M62 -> 202842.5 | U62: 200 | X62: =X48 -> 136.2627 | Y62: =Y48 | Z62: =Z48 -> 151.2516 | AA62: =AA48 | AB62: =AB48 -> 163.51525 | AC62: =AC48 -> 327.03049 | AE62: 200 | AF62: 500 | AG62: 500 | AH62: 500 | AI62: 500 | AJ62: 500 | AK62: 500 | AL62: 500 | AM62: 500 | AO62: 200 | AP62: =(B62*L62)+V62*B62+AF62 -> 4660540.4 | AQ62: =(C62*M62)+W62*C62+AG62 -> 4665877.5 | AR62: =(D62*N62)+X62*D62+AH62 -> 4663674.4 | AS62: =(E62*O62)+Y62*E62+AI62 -> 4665877.5 | AT62: =(F62*P62)+Z62*F62+AJ62 -> 4664019.2 | AU62: =(G62*Q62)+AA62*G62+AK62 -> 4665877.5 | AV62: =(H62*R62)+AB62*H62+AL62 -> 4664301.2 | AW62: =(I62*S62)+AC62*I62+AM62 -> 4673399.2 | AZ62: 1.1 | BA62: 200 | BB62: =AP62*AZ48 -> 5126594.4 | BC62: =AQ62*AZ48 -> 5132465.3 | BD62: =AR62*AZ49 -> 5130041.9 | BE62: =AS62*AZ48 -> 5132465.3 | BF62: =(R62*AB62)+AL62*R62+AV62 -> 1.3909942e+08 | BG62: =(Q62*AC62)+AL62*Q62+AW62 -> 1.7243033e+08 | BH62: =AV62*AZ49 -> 5130731.4 | BI62: =AW62*AZ49 -> 5140739.2 | BJ62: =CEILING(BH62*1.15,1) -> 5900342 | BK62: =CEILING(BI62*1.15,1) -> 5911851 | BL62: =BH62*1.4 -> 7183023.9 | BM62: =BI62*1.4 -> 7197034.8
A63: 300 | B63: 34 | C63: 34 | D63: 34 | E63: 34 | F63: 34 | G63: 34 | H63: 34 | I63: 34 | K63: 300 | L63: =Bajadas!E6 -> 196651.32 | M63: =Bajadas!F6 -> 196876.55 | N63: =$L63 -> 196651.32 | O63: =$M63 -> 196876.55 | P63: =$L63 -> 196651.32 | Q63: =$M63 -> 196876.55 | R63: =$L63 -> 196651.32 | S63: =$M63 -> 196876.55 | U63: 300 | X63: =X49 -> 115.8233 | Y63: =Y49 | Z63: =Z49 -> 138.98796 | AA63: =AA49 | AB63: =AB49 -> 151.2516 | AC63: =AC49 -> 302.5032 | AE63: 300 | AF63: 700 | AG63: 700 | AH63: 700 | AI63: 700 | AJ63: 700 | AK63: 700 | AL63: 700 | AM63: 700 | AO63: 300 | AP63: =(B63*L63)+V63*B63+AF63 -> 6686844.9 | AQ63: =(C63*M63)+W63*C63+AG63 -> 6694502.6 | AR63: =(D63*N63)+X63*D63+AH63 -> 6690782.9 | AS63: =(E63*O63)+Y63*E63+AI63 -> 6694502.6 | AT63: =(F63*P63)+Z63*F63+AJ63 -> 6691570.5 | AU63: =(G63*Q63)+AA63*G63+AK63 -> 6694502.6 | AV63: =(H63*R63)+AB63*H63+AL63 -> 6691987.5 | AW63: =(I63*S63)+AC63*I63+AM63 -> 6704787.7 | AZ63: 1.1 | BA63: 300 | BB63: =AP63*AZ49 -> 7355529.4 | BC63: =AQ63*AZ49 -> 7363952.8 | BD63: =AR63*AZ50 -> 7359861.2 | BE63: =AS63*AZ49 -> 7363952.8 | BF63: =(R63*AB63)+AL63*R63+AV63 -> 1.7409174e+08 | BG63: =(Q63*AC63)+AL63*Q63+AW63 -> 2.0407416e+08 | BH63: =AV63*AZ50 -> 7361186.2 | BI63: =AW63*AZ50 -> 7375266.4 | BJ63: =CEILING(BH63*1.15,1) -> 8465365 | BK63: =CEILING(BI63*1.15,1) -> 8481557 | BL63: =BH63*1.4 -> 10305661 | BM63: =BI63*1.4 -> 10325373
A64: 500 | B64: 56 | C64: 56 | D64: 56 | E64: 56 | F64: 56 | G64: 56 | H64: 56 | I64: 56 | K64: 500 | L64: =Bajadas!E7 -> 190692.19 | M64: =Bajadas!F7 -> 190910.59 | N64: =$L64 -> 190692.19 | O64: =$M64 -> 190910.59 | P64: =$L64 -> 190692.19 | Q64: =$M64 -> 190910.59 | R64: =$L64 -> 190692.19 | S64: =$M64 -> 190910.59 | U64: 500 | X64: =X50 -> 105.6036 | Y64: =Y50 | Z64: =Z50 -> 126.72432 | AA64: =AA50 | AB64: =AB50 -> 151.2516 | AC64: =AC50 -> 302.5032 | AE64: 500 | AF64: 1000 | AG64: 1000 | AH64: 1000 | AI64: 1000 | AJ64: 1000 | AK64: 1000 | AL64: 1000 | AM64: 1000 | AO64: 500 | AP64: =(B64*L64)+V64*B64+AF64 -> 10679763 | AQ64: =(C64*M64)+W64*C64+AG64 -> 10691993 | AR64: =(D64*N64)+X64*D64+AH64 -> 10685676 | AS64: =(E64*O64)+Y64*E64+AI64 -> 10691993 | AT64: =(F64*P64)+Z64*F64+AJ64 -> 10686859 | AU64: =(G64*Q64)+AA64*G64+AK64 -> 10691993 | AV64: =(H64*R64)+AB64*H64+AL64 -> 10688233 | AW64: =(I64*S64)+AC64*I64+AM64 -> 10708933 | AZ64: 1.1 | BA64: 500 | BB64: =AP64*AZ50 -> 11747739 | BC64: =AQ64*AZ50 -> 11761192 | BD64: =AR64*AZ51 -> 11754244 | BE64: =AS64*AZ50 -> 11761192 | BF64: =(R64*AB64)+AL64*R64+AV64 -> 2.3022292e+08 | BG64: =(Q64*AC64)+AL64*Q64+AW64 -> 2.5937059e+08 | BH64: =AV64*AZ51 -> 11757056 | BI64: =AW64*AZ51 -> 11779827 | BJ64: =CEILING(BH64*1.15,1) -> 13520615 | BK64: =CEILING(BI64*1.15,1) -> 13546801 | BL64: =BH64*1.4 -> 16459878 | BM64: =BI64*1.4 -> 16491757
A65: 1000 | B65: 112 | C65: 112 | D65: 112 | E65: 112 | F65: 112 | G65: 112 | H65: 112 | I65: 112 | K65: 1000 | L65: =Bajadas!E8 -> 184733.06 | M65: =Bajadas!F8 -> 184944.63 | N65: =$L65 -> 184733.06 | O65: =$M65 -> 184944.63 | P65: =$L65 -> 184733.06 | Q65: =$M65 -> 184944.63 | R65: =$L65 -> 184733.06 | S65: =$M65 -> 184944.63 | U65: 1000 | X65: =X51 -> 98.790461 | Y65: =Y51 | Z65: =Z51 -> 118.54855 | AA65: =AA51 | AB65: =AB51 -> 151.2516 | AC65: =AC51 -> 302.5032 | AE65: 1000 | AF65: 1600 | AG65: 1600 | AH65: 1600 | AI65: 1600 | AJ65: 1600 | AK65: 1600 | AL65: 1600 | AM65: 1600 | AO65: 1000 | AP65: =(B65*L65)+V65*B65+AF65 -> 20691703 | AQ65: =(C65*M65)+W65*C65+AG65 -> 20715399 | AR65: =(D65*N65)+X65*D65+AH65 -> 20702767 | AS65: =(E65*O65)+Y65*E65+AI65 -> 20715399 | AT65: =(F65*P65)+Z65*F65+AJ65 -> 20704980 | AU65: =(G65*Q65)+AA65*G65+AK65 -> 20715399 | AV65: =(H65*R65)+AB65*H65+AL65 -> 20708643 | AW65: =(I65*S65)+AC65*I65+AM65 -> 20749279 | AZ65: 1.1 | BA65: 1000 | BB65: =AP65*AZ51 -> 22760873 | BC65: =AQ65*AZ51 -> 22786939 | BD65: =AR65*AZ52 -> 22773044 | BE65: =AS65*AZ51 -> 22786939 | BF65: =(R65*AB65)+AL65*R65+AV65 -> 3.4422271e+08 | BG65: =(Q65*AC65)+AL65*Q65+AW65 -> 3.7260704e+08 | BH65: =AV65*AZ52 -> 22779507 | BI65: =AW65*AZ52 -> 22824207 | BJ65: =CEILING(BH65*1.15,1) -> 26196434 | BK65: =CEILING(BI65*1.15,1) -> 26247839 | BL65: =BH65*1.4 -> 31891310 | BM65: =BI65*1.4 -> 31953890
BA67: POSTALES
A68: postales triplex | BA68: Cartulina triplex
A69: triplex | BA69: Tamaño 10x15
A70: Tamaño 10x15 | D70: cantidad de bajadas - 9 x ´postura | L70: costo de impresión x bajada | V70: costo de laminado | AE70: costo de corte | AO70: PRECIO DE VENTA | BA70: PRECIO DE VENTA POSTALES
A71: Cantidad | B71: Sin laminar | D71: Laca UV | F71: Laminado brillo | H71: Laminado mate | K71: Cantidad | L71: Sin laminar | N71: Laca UV | P71: Laminado brillo | R71: Laminado mate | U71: Cantidad | V71: Sin laminar | X71: Laca UV | Z71: Laminado brillo | AB71: Laminado mate | AE71: Cantidad | AF71: Sin laminar | AH71: Laca UV | AJ71: Laminado brillo | AL71: Laminado mate | AO71: Cantidad | AP71: Sin laminar | AR71: Laca UV | AT71: Laminado brillo | AV71: Laminado mate | BA71: Postales | BB71: Sin laminar | BD71: Laca UV | BF71: Laminado brillo | BH71: Laminado mate | BJ71: Laminado soft touch | BL71: Sectorizado o blanco
A72: Postales | B72: 4/0 | C72: 4/4 | D72: 4/0 | E72: 4/4 | F72: 4/0 | G72: 4/4 | H72: 4/0 | I72: 4/4 | K72: Postales | L72: 4/0 | M72: 4/4 | N72: 4/0 | O72: 4/4 | P72: 4/0 | Q72: 4/4 | R72: 4/0 | S72: 4/4 | U72: Postales | V72: 4/0 | W72: 4/4 | X72: 4/0 | Y72: 4/4 | Z72: 4/0 | AA72: 4/4 | AB72: 4/0 | AC72: 4/4 | AE72: Postales | AF72: 4/0 | AG72: 4/4 | AH72: 4/0 | AI72: 4/4 | AJ72: 4/0 | AK72: 4/4 | AL72: 4/0 | AM72: 4/4 | AO72: Postales | AP72: 4/0 | AQ72: 4/4 | AR72: 4/0 | AS72: 4/4 | AT72: 4/0 | AU72: 4/4 | AV72: 4/0 | AW72: 4/4 | BA72: Cantidad | BB72: 4/0 | BC72: 4/4 | BD72: 4/0 | BE72: 4/4 | BF72: 4/0 | BG72: 4/4 | BH72: 4/0 | BI72: 4/4 | BJ72: 4/0 | BK72: 4/4 | BL72: 4/0 | BM72: 4/4
A73: 100 | B73: 12 | C73: 12 | D73: 12 | E73: 12 | F73: 12 | G73: 12 | H73: 12 | I73: 12 | K73: 100 | L73: =Bajadas!C5 -> 203036.3 | M73: =Bajadas!D5 -> 203268.35 | N73: =L73 -> 203036.3 | O73: =M73 -> 203268.35 | P73: =L73 -> 203036.3 | Q73: =M73 -> 203268.35 | R73: =L73 -> 203036.3 | S73: =M73 -> 203268.35 | U73: 100 | X73: =X61 -> 136.2627 | Y73: =Y61 | Z73: =Z61 -> 163.51525 | AA73: =AA61 | AB73: =AB61 -> 163.51525 | AC73: =AC61 -> 327.03049 | AE73: 100 | AF73: 400 | AG73: 400 | AH73: 400 | AI73: 400 | AJ73: 400 | AK73: 400 | AL73: 400 | AM73: 400 | AO73: 100 | AP73: =(B73*L73)+V73*B73+AF73 -> 2436835.6 | AQ73: =(C73*M73)+W73*C73+AG73 -> 2439620.2 | AR73: =(D73*N73)+X73*D73+AH73 -> 2438470.8 | AS73: =(E73*O73)+Y73*E73+AI73 -> 2439620.2 | AT73: =(F73*P73)+Z73*F73+AJ73 -> 2438797.8 | AU73: =(G73*Q73)+AA73*G73+AK73 -> 2439620.2 | AV73: =(H73*R73)+AB73*H73+AL73 -> 2438797.8 | AW73: =(I73*S73)+AC73*I73+AM73 -> 2443544.6 | BA73: 100 | BB73: 169.9 | BC73: 211.3 | BD73: 184.9 | BE73: 241.3 | BF73: 199.9 | BG73: 271.3 | BH73: 200.5 | BI73: 272.5 | BJ73: =CEILING(BH73*1.15,1) -> 231 | BK73: =CEILING(BI73*1.15,1) -> 314 | BL73: =BH73*1.4 -> 280.7 | BM73: =BI73*1.4 -> 381.5
A74: 200 | B74: 23 | C74: 23 | D74: 23 | E74: 23 | F74: 23 | G74: 23 | H74: 23 | I74: 23 | K74: 200 | L74: =Bajadas!C5 -> 203036.3 | M74: =Bajadas!D5 -> 203268.35 | N74: =L74 -> 203036.3 | O74: =M74 -> 203268.35 | P74: =L74 -> 203036.3 | Q74: =M74 -> 203268.35 | R74: =L74 -> 203036.3 | S74: =M74 -> 203268.35 | U74: 200 | X74: =X62 -> 136.2627 | Y74: =Y62 | Z74: =Z62 -> 151.2516 | AA74: =AA62 | AB74: =AB62 -> 163.51525 | AC74: =AC62 -> 327.03049 | AE74: 200 | AF74: 500 | AG74: 500 | AH74: 500 | AI74: 500 | AJ74: 500 | AK74: 500 | AL74: 500 | AM74: 500 | AO74: 200 | AP74: =(B74*L74)+V74*B74+AF74 -> 4670335 | AQ74: =(C74*M74)+W74*C74+AG74 -> 4675672.1 | AR74: =(D74*N74)+X74*D74+AH74 -> 4673469 | AS74: =(E74*O74)+Y74*E74+AI74 -> 4675672.1 | AT74: =(F74*P74)+Z74*F74+AJ74 -> 4673813.7 | AU74: =(G74*Q74)+AA74*G74+AK74 -> 4675672.1 | AV74: =(H74*R74)+AB74*H74+AL74 -> 4674095.8 | AW74: =(I74*S74)+AC74*I74+AM74 -> 4683193.8 | BA74: 200 | BB74: 261.475 | BC74: 340.825 | BD74: 290.225 | BE74: 398.325 | BF74: 318.975 | BG74: 455.825 | BH74: 320.125 | BI74: 458.125 | BJ74: =CEILING(BH74*1.15,1) -> 369 | BK74: =CEILING(BI74*1.15,1) -> 527 | BL74: =BH74*1.4 -> 448.175 | BM74: =BI74*1.4 -> 641.375
A75: 300 | B75: 34 | C75: 34 | D75: 34 | E75: 34 | F75: 34 | G75: 34 | H75: 34 | I75: 34 | K75: 300 | L75: =Bajadas!C6 -> 197064.65 | M75: =Bajadas!D6 -> 197289.87 | N75: =L75 -> 197064.65 | O75: =M75 -> 197289.87 | P75: =L75 -> 197064.65 | Q75: =M75 -> 197289.87 | R75: =L75 -> 197064.65 | S75: =M75 -> 197289.87 | U75: 300 | X75: =X63 -> 115.8233 | Y75: =Y63 | Z75: =Z63 -> 138.98796 | AA75: =AA63 | AB75: =AB63 -> 151.2516 | AC75: =AC63 -> 302.5032 | AE75: 300 | AF75: 700 | AG75: 700 | AH75: 700 | AI75: 700 | AJ75: 700 | AK75: 700 | AL75: 700 | AM75: 700 | AO75: 300 | AP75: =(B75*L75)+V75*B75+AF75 -> 6700898 | AQ75: =(C75*M75)+W75*C75+AG75 -> 6708555.6 | AR75: =(D75*N75)+X75*D75+AH75 -> 6704836 | AS75: =(E75*O75)+Y75*E75+AI75 -> 6708555.6 | AT75: =(F75*P75)+Z75*F75+AJ75 -> 6705623.6 | AU75: =(G75*Q75)+AA75*G75+AK75 -> 6708555.6 | AV75: =(H75*R75)+AB75*H75+AL75 -> 6706040.5 | AW75: =(I75*S75)+AC75*I75+AM75 -> 6718840.7 | BA75: 300 | BB75: 322.45 | BC75: 434.65 | BD75: 364.95 | BE75: 519.65 | BF75: 407.45 | BG75: 604.65 | BH75: 409.15 | BI75: 608.05 | BJ75: =CEILING(BH75*1.15,1) -> 471 | BK75: =CEILING(BI75*1.15,1) -> 700 | BL75: =BH75*1.4 -> 572.81 | BM75: =BI75*1.4 -> 851.27
A76: 500 | B76: 56 | C76: 56 | D76: 56 | E76: 56 | F76: 56 | G76: 56 | H76: 56 | I76: 56 | K76: 500 | L76: =Bajadas!C7 -> 191092.99 | M76: =Bajadas!D7 -> 191311.39 | N76: =L76 -> 191092.99 | O76: =M76 -> 191311.39 | P76: =L76 -> 191092.99 | Q76: =M76 -> 191311.39 | R76: =L76 -> 191092.99 | S76: =M76 -> 191311.39 | U76: 500 | X76: =X64 -> 105.6036 | Y76: =Y64 | Z76: =Z64 -> 126.72432 | AA76: =AA64 | AB76: =AB64 -> 151.2516 | AC76: =AC64 -> 302.5032 | AE76: 500 | AF76: 1000 | AG76: 1000 | AH76: 1000 | AI76: 1000 | AJ76: 1000 | AK76: 1000 | AL76: 1000 | AM76: 1000 | AO76: 500 | AP76: =(B76*L76)+V76*B76+AF76 -> 10702207 | AQ76: =(C76*M76)+W76*C76+AG76 -> 10714438 | AR76: =(D76*N76)+X76*D76+AH76 -> 10708121 | AS76: =(E76*O76)+Y76*E76+AI76 -> 10714438 | AT76: =(F76*P76)+Z76*F76+AJ76 -> 10709304 | AU76: =(G76*Q76)+AA76*G76+AK76 -> 10714438 | AV76: =(H76*R76)+AB76*H76+AL76 -> 10710678 | AW76: =(I76*S76)+AC76*I76+AM76 -> 10731378 | BA76: 500 | BB76: 477.4 | BC76: 662.2 | BD76: 544.6 | BE76: 796.6 | BF76: 609 | BG76: 925.4 | BH76: 611.8 | BI76: 931 | BJ76: =CEILING(BH76*1.15,1) -> 704 | BK76: =CEILING(BI76*1.15,1) -> 1071 | BL76: =BH76*1.4 -> 856.52 | BM76: =BI76*1.4 -> 1303.4
A77: 1000 | B77: 112 | C77: 112 | D77: 112 | E77: 112 | F77: 112 | G77: 112 | H77: 112 | I77: 112 | K77: 1000 | L77: =Bajadas!C8 -> 185121.33 | M77: =Bajadas!D8 -> 185332.91 | N77: =L77 -> 185121.33 | O77: =M77 -> 185332.91 | P77: =L77 -> 185121.33 | Q77: =M77 -> 185332.91 | R77: =L77 -> 185121.33 | S77: =M77 -> 185332.91 | U77: 1000 | X77: =X65 -> 98.790461 | Y77: =Y65 | Z77: =Z65 -> 118.54855 | AA77: =AA65 | AB77: =AB65 -> 151.2516 | AC77: =AC65 -> 302.5032 | AE77: 1000 | AF77: 1600 | AG77: 1600 | AH77: 1600 | AI77: 1600 | AJ77: 1600 | AK77: 1600 | AL77: 1600 | AM77: 1600 | AO77: 1000 | AP77: =(B77*L77)+V77*B77+AF77 -> 20735189 | AQ77: =(C77*M77)+W77*C77+AG77 -> 20758886 | AR77: =(D77*N77)+X77*D77+AH77 -> 20746254 | AS77: =(E77*O77)+Y77*E77+AI77 -> 20758886 | AT77: =(F77*P77)+Z77*F77+AJ77 -> 20748467 | AU77: =(G77*Q77)+AA77*G77+AK77 -> 20758886 | AV77: =(H77*R77)+AB77*H77+AL77 -> 20752130 | AW77: =(I77*S77)+AC77*I77+AM77 -> 20792766 | BA77: 1000 | BB77: 878 | BC77: 1230.8 | BD77: 1006.8 | BE77: 1488.4 | BF77: 1124.4 | BG77: 1723.6 | BH77: 1130 | BI77: 1734.8 | BJ77: =CEILING(BH77*1.15,1) -> 1300 | BK77: =CEILING(BI77*1.15,1) -> 1996 | BL77: =BH77*1.4 -> 1582 | BM77: =BI77*1.4 -> 2428.72
A80: Folletos
A81: Tiempo de producción | BA81: Folletos
A82: Impresión color | BA82: Papel ilustración 150g
A83: Papel ilustración 150g | AP83: 1 | AQ83: 1.4 | AR83: 1.3 | AS83: 1.83 | AT83: 2.64 | AU83: 3.73 | AV83: 5.05 | AW83: 7.16 | BA83: Impresión Color
B84: cantidad de bajadas | L84: costo de impresión x bajada | U84: costo de corte | AE84: costo de corte | AP84: PRECIO DE VENTA | BA84: PRECIO DE VENTA FOLLETOS
A85: Cantidad | B85: 10x10 | D85: 10x15 | F85: 15x21 | H85: A4 | K85: Cantidad | L85: 10x10 | N85: 10x15 | P85: 15x21 | R85: A4 | U85: Cantidad | V85: Sin laminar | X85: Laca UV | Z85: Laminado brillo | AB85: Laminado mate | AE85: Cantidad | AF85: Sin laminar | AH85: Laca UV | AJ85: Laminado brillo | AL85: Laminado mate | AO85: Cantidad | AP85: 10x10 | AR85: 10x15 | AT85: 15x21 | AV85: A4 | BA85: Folletos | BB85: 10x10 | BD85: 10x15 | BF85: 15x21 | BH85: A4
A86: Folletos | B86: 4/0 | C86: 4/4 | D86: 4/0 | E86: 4/4 | F86: 4/0 | G86: 4/4 | H86: 4/0 | I86: 4/4 | K86: Folletos | L86: 4/0 | M86: 4/4 | N86: 4/0 | O86: 4/4 | P86: 4/0 | Q86: 4/4 | R86: 4/0 | S86: 4/4 | U86: Postales | V86: 4/0 | W86: 4/4 | X86: 4/0 | Y86: 4/4 | Z86: 4/0 | AA86: 4/4 | AB86: 4/0 | AC86: 4/4 | AE86: Postales | AF86: 4/0 | AG86: 4/4 | AH86: 4/0 | AI86: 4/4 | AJ86: 4/0 | AK86: 4/4 | AL86: 4/0 | AM86: 4/4 | AO86: Folletos | AP86: 4/0 | AQ86: 4/4 | AR86: 4/0 | AS86: 4/4 | AT86: 4/0 | AU86: 4/4 | AV86: 4/0 | AW86: 4/4 | BA86: Cantidad | BB86: 4/0 | BC86: 4/4 | BD86: 4/0 | BE86: 4/4 | BF86: 4/0 | BG86: 4/4 | BH86: 4/0 | BI86: 4/4
A87: 100 | B87: 9 | C87: 9 | D87: 12 | E87: 12 | F87: 25 | G87: 25 | H87: 50 | I87: 50 | K87: 100 | L87: =Bajadas!K5 -> 87022.479 | M87: =Bajadas!L5 -> 87254.529 | N87: =Bajadas!K5 -> 87022.479 | O87: =Bajadas!L5 -> 87254.529 | P87: =Bajadas!K5 -> 87022.479 | Q87: =Bajadas!L5 -> 87254.529 | R87: =Bajadas!K6 -> 84462.995 | S87: =Bajadas!L6 -> 84688.22 | U87: 100 | V87: 200 | W87: 200 | X87: 200 | Y87: 200 | Z87: 200 | AA87: 200 | AB87: 200 | AC87: 200 | AE87: 100 | AF87: 400 | AG87: 400 | AH87: 400 | AI87: 400 | AJ87: 400 | AK87: 400 | AL87: 400 | AM87: 400 | AN87: 1 | AO87: 100 | AP87: =B87*L87+V87 -> 783402.31 | AQ87: =C87*M87+W87 -> 785490.76 | AR87: =D87*N87+X87 -> 1044469.8 | AS87: =E87*O87+Y87 -> 1047254.4 | AT87: =F87*P87+Z87 -> 2175762 | AU87: =G87*Q87+AA87 -> 2181563.2 | AV87: =H87*R87+AB87 -> 4223349.7 | AW87: =I87*S87+AC87 -> 4234611 | BA87: 100 | BB87: 130.4251 | BC87: 161.4751 | BD87: 150.5668 | BE87: 191.9668 | BF87: 237.8475 | BG87: 324.0975 | BH87: 340.695 | BI87: 505.695
A88: 200 | B88: 17 | C88: 17 | D88: 23 | E88: 23 | F88: 50 | G88: 50 | H88: 100 | I88: 100 | K88: 200 | L88: =Bajadas!K5 -> 87022.479 | M88: =Bajadas!L5 -> 87254.529 | N88: =Bajadas!K5 -> 87022.479 | O88: =Bajadas!L5 -> 87254.529 | P88: =Bajadas!K6 -> 84462.995 | Q88: =Bajadas!L6 -> 84688.22 | R88: =Bajadas!K7 -> 81903.51 | S88: =Bajadas!L7 -> 82121.91 | U88: 200 | V88: 250 | W88: 250 | X88: 250 | Y88: 250 | Z88: 250 | AA88: 250 | AB88: 250 | AC88: 250 | AE88: 200 | AF88: 500 | AG88: 500 | AH88: 500 | AI88: 500 | AJ88: 500 | AK88: 500 | AL88: 500 | AM88: 500 | AN88: 1.84 | AO88: 200 | AP88: =B88*L88+V88 -> 1479632.1 | AQ88: =C88*M88+W88 -> 1483577 | AR88: =D88*N88+X88 -> 2001767 | AS88: =E88*O88+Y88 -> 2007104.2 | AT88: =F88*P88+Z88 -> 4223399.7 | AU88: =G88*Q88+AA88 -> 4234661 | AV88: =H88*R88+AB88 -> 8190601 | AW88: =I88*S88+AC88 -> 8212441 | BA88: 200 | BB88: 184.1363 | BC88: 242.7863 | BD88: 224.4197 | BE88: 303.7697 | BF88: 360.695 | BG88: 525.695 | BH88: 616.39 | BI88: 946.39
